Workbook

Sheet Índice
B2: Índice de Requerimientos — IncluTec
B3: Plataforma web y móvil de vinculación laboral para personas con discapacidad · Estadía ISC · UPQ · Entrega: 28 de octubre de 2026
B5: Interfaces: Requerimientos Funcionales y No Funcionales por hoja
B6: # | C6: Hoja | D6: Interfaz | E6: Módulo / Rol | F6: # RF | G6: # RNF | H6: Avance RF | I6: Ir
B7: 1 | C7: MOV-00 Splash | D7: MOV-00 — Splash | E7: Móvil / Compartida | F7: =COUNTA('MOV-00 Splash'!B6:B7) -> 2 | G7: =COUNTA('MOV-00 Splash'!B13:B26) -> 14 | H7: =AVERAGE('MOV-00 Splash'!F6:F7) -> 0 | I7: Abrir →
B8: 2 | C8: MOV-01 Login móvil | D8: MOV-01 — Inicio de sesión (móvil) | E8: Móvil / Compartida | F8: =COUNTA('MOV-01 Login móvil'!B6:B10) -> 5 | G8: =COUNTA('MOV-01 Login móvil'!B16:B34) -> 19 | H8: =AVERAGE('MOV-01 Login móvil'!F6:F10) -> 0 | I8: Abrir →
B9: 3 | C9: MOV-02 Registro | D9: MOV-02 — Registro de cuenta | E9: Móvil / Compartida | F9: =COUNTA('MOV-02 Registro'!B6:B12) -> 7 | G9: =COUNTA('MOV-02 Registro'!B18:B41) -> 24 | H9: =AVERAGE('MOV-02 Registro'!F6:F12) -> 0 | I9: Abrir →
B10: 4 | C10: MOV-03 Recuperar contraseña | D10: MOV-03 — Recuperar contraseña | E10: Móvil / Compartida | F10: =COUNTA('MOV-03 Recuperar contraseña'!B6:B9) -> 4 | G10: =COUNTA('MOV-03 Recuperar contraseña'!B15:B33) -> 19 | H10: =AVERAGE('MOV-03 Recuperar contraseña'!F6:F9) -> 0 | I10: Abrir →
B11: 5 | C11: MOV-04 Notificaciones | D11: MOV-04 — Notificaciones | E11: Móvil / Compartida | F11: =COUNTA('MOV-04 Notificaciones'!B6:B11) -> 6 | G11: =COUNTA('MOV-04 Notificaciones'!B17:B34) -> 18 | H11: =AVERAGE('MOV-04 Notificaciones'!F6:F11) -> 0 | I11: Abrir →
B12: 6 | C12: CAN-01 Vacantes | D12: CAN-01 — Vacantes (inicio del candidato) | E12: Móvil / Candidato | F12: =COUNTA('CAN-01 Vacantes'!B6:B11) -> 6 | G12: =COUNTA('CAN-01 Vacantes'!B17:B30) -> 14 | H12: =AVERAGE('CAN-01 Vacantes'!F6:F11) -> 0 | I12: Abrir →
B13: 7 | C13: CAN-02 Detalle vacante | D13: CAN-02 — Detalle de vacante | E13: Móvil / Candidato | F13: =COUNTA('CAN-02 Detalle vacante'!B6:B14) -> 9 | G13: =COUNTA('CAN-02 Detalle vacante'!B20:B38) -> 19 | H13: =AVERAGE('CAN-02 Detalle vacante'!F6:F14) -> 0 | I13: Abrir →
B14: 8 | C14: CAN-03 Mi perfil | D14: CAN-03 — Mi perfil | E14: Móvil / Candidato | F14: =COUNTA('CAN-03 Mi perfil'!B6:B12) -> 7 | G14: =COUNTA('CAN-03 Mi perfil'!B18:B36) -> 19 | H14: =AVERAGE('CAN-03 Mi perfil'!F6:F12) -> 0 | I14: Abrir →
B15: 9 | C15: CAN-04 Mi CV | D15: CAN-04 — Mi CV | E15: Móvil / Candidato | F15: =COUNTA('CAN-04 Mi CV'!B6:B11) -> 6 | G15: =COUNTA('CAN-04 Mi CV'!B17:B35) -> 19 | H15: =AVERAGE('CAN-04 Mi CV'!F6:F11) -> 0 | I15: Abrir →
B16: 10 | C16: CAN-05 Postulaciones | D16: CAN-05 — Mis postulaciones | E16: Móvil / Candidato | F16: =COUNTA('CAN-05 Postulaciones'!B6:B10) -> 5 | G16: =COUNTA('CAN-05 Postulaciones'!B16:B29) -> 14 | H16: =AVERAGE('CAN-05 Postulaciones'!F6:F10) -> 0 | I16: Abrir →
B17: 11 | C17: CAN-06 Detalle postulación | D17: CAN-06 — Detalle de postulación y entrevista | E17: Móvil / Candidato | F17: =COUNTA('CAN-06 Detalle postulación'!B6:B11) -> 6 | G17: =COUNTA('CAN-06 Detalle postulación'!B17:B34) -> 18 | H17: =AVERAGE('CAN-06 Detalle postulación'!F6:F11) -> 0 | I17: Abrir →
B18: 12 | C18: CAN-07 Empresas | D18: CAN-07 — Empresas | E18: Móvil / Candidato | F18: =COUNTA('CAN-07 Empresas'!B6:B9) -> 4 | G18: =COUNTA('CAN-07 Empresas'!B15:B28) -> 14 | H18: =AVERAGE('CAN-07 Empresas'!F6:F9) -> 0 | I18: Abrir →
B19: 13 | C19: REC-01 Organización | D19: REC-01 — Perfil de la organización | E19: Móvil / Reclutador | F19: =COUNTA('REC-01 Organización'!B6:B10) -> 5 | G19: =COUNTA('REC-01 Organización'!B16:B29) -> 14 | H19: =AVERAGE('REC-01 Organización'!F6:F10) -> 0 | I19: Abrir →
B20: 14 | C20: REC-02 Mis vacantes | D20: REC-02 — Mis vacantes | E20: Móvil / Reclutador | F20: =COUNTA('REC-02 Mis vacantes'!B6:B11) -> 6 | G20: =COUNTA('REC-02 Mis vacantes'!B17:B30) -> 14 | H20: =AVERAGE('REC-02 Mis vacantes'!F6:F11) -> 0 | I20: Abrir →
B21: 15 | C21: REC-03 Crear vacante | D21: REC-03 — Crear / editar vacante | E21: Móvil / Reclutador | F21: =COUNTA('REC-03 Crear vacante'!B6:B11) -> 6 | G21: =COUNTA('REC-03 Crear vacante'!B17:B30) -> 14 | H21: =AVERAGE('REC-03 Crear vacante'!F6:F11) -> 0 | I21: Abrir →
B22: 16 | C22: REC-04 Postulados | D22: REC-04 — Candidatos postulados | E22: Móvil / Reclutador | F22: =COUNTA('REC-04 Postulados'!B6:B10) -> 5 | G22: =COUNTA('REC-04 Postulados'!B16:B29) -> 14 | H22: =AVERAGE('REC-04 Postulados'!F6:F10) -> 0 | I22: Abrir →
B23: 17 | C23: REC-05 Detalle postulado | D23: REC-05 — Detalle del postulado | E23: Móvil / Reclutador | F23: =COUNTA('REC-05 Detalle postulado'!B6:B12) -> 7 | G23: =COUNTA('REC-05 Detalle postulado'!B18:B40) -> 23 | H23: =AVERAGE('REC-05 Detalle postulado'!F6:F12) -> 0 | I23: Abrir →
B24: 18 | C24: REC-06 Agenda | D24: REC-06 — Agenda de entrevistas | E24: Móvil / Reclutador | F24: =COUNTA('REC-06 Agenda'!B6:B10) -> 5 | G24: =COUNTA('REC-06 Agenda'!B16:B33) -> 18 | H24: =AVERAGE('REC-06 Agenda'!F6:F10) -> 0 | I24: Abrir →
B25: 19 | C25: WEB-01 Login web | D25: WEB-01 — Inicio de sesión (web) | E25: Web / Administrador | F25: =COUNTA('WEB-01 Login web'!B6:B10) -> 5 | G25: =COUNTA('WEB-01 Login web'!B16:B29) -> 14 | H25: =AVERAGE('WEB-01 Login web'!F6:F10) -> 0 | I25: Abrir →
B26: 20 | C26: WEB-02 Dashboard | D26: WEB-02 — Dashboard y estadísticas | E26: Web / Administrador | F26: =COUNTA('WEB-02 Dashboard'!B6:B12) -> 7 | G26: =COUNTA('WEB-02 Dashboard'!B18:B30) -> 13 | H26: =AVERAGE('WEB-02 Dashboard'!F6:F12) -> 0 | I26: Abrir →
B27: 21 | C27: WEB-03 Usuarios | D27: WEB-03 — Gestión de usuarios | E27: Web / Administrador | F27: =COUNTA('WEB-03 Usuarios'!B6:B11) -> 6 | G27: =COUNTA('WEB-03 Usuarios'!B17:B35) -> 19 | H27: =AVERAGE('WEB-03 Usuarios'!F6:F11) -> 0 | I27: Abrir →
B28: 22 | C28: WEB-04 Empresas | D28: WEB-04 — Empresas y validación | E28: Web / Administrador | F28: =COUNTA('WEB-04 Empresas'!B6:B11) -> 6 | G28: =COUNTA('WEB-04 Empresas'!B17:B34) -> 18 | H28: =AVERAGE('WEB-04 Empresas'!F6:F11) -> 0 | I28: Abrir →
B29: 23 | C29: WEB-05 Vacantes | D29: WEB-05 — Vacantes (moderación) | E29: Web / Administrador | F29: =COUNTA('WEB-05 Vacantes'!B6:B9) -> 4 | G29: =COUNTA('WEB-05 Vacantes'!B15:B28) -> 14 | H29: =AVERAGE('WEB-05 Vacantes'!F6:F9) -> 0 | I29: Abrir →
B30: 24 | C30: WEB-06 Categ. y habilidades | D30: WEB-06 — Categorías y habilidades | E30: Web / Administrador | F30: =COUNTA('WEB-06 Categ. y habilidades'!B6:B9) -> 4 | G30: =COUNTA('WEB-06 Categ. y habilidades'!B15:B28) -> 14 | H30: =AVERAGE('WEB-06 Categ. y habilidades'!F6:F9) -> 0 | I30: Abrir →
B31: 25 | C31: WEB-07 Catálogos | D31: WEB-07 — Catálogos | E31: Web / Administrador | F31: =COUNTA('WEB-07 Catálogos'!B6:B9) -> 4 | G31: =COUNTA('WEB-07 Catálogos'!B15:B28) -> 14 | H31: =AVERAGE('WEB-07 Catálogos'!F6:F9) -> 0 | I31: Abrir →
B32: 26 | C32: WEB-08 Reportes-incidencias | D32: WEB-08 — Reportes e incidencias | E32: Web / Administrador | F32: =COUNTA('WEB-08 Reportes-incidencias'!B6:B11) -> 6 | G32: =COUNTA('WEB-08 Reportes-incidencias'!B17:B34) -> 18 | H32: =AVERAGE('WEB-08 Reportes-incidencias'!F6:F11) -> 0 | I32: Abrir →
B33: 27 | C33: API | D33: API — FastAPI (objetivos del API) | E33: Backend | F33: =COUNTA(API!B6:B18) -> 13 | G33: =COUNTA(API!B24:B34) -> 11 | H33: =AVERAGE(API!F6:F18) -> 0 | I33: Abrir →
B34: Total | F34: =SUM(F7:F33) -> 156 | G34: =SUM(G7:G33) -> 443 | H34: =AVERAGE(H7:H33) -> 0
B37: Requerimientos No Funcionales generales (fuente de los RNF de cada hoja)
B38: # | C38: Hoja | D38: Grupo | E38: Aplica a | F38: # RNF | H38: Avance | I38: Ir
B39: 1 | C39: RNF Accesibilidad | D39: Accesibilidad (todas las interfaces móviles y web) | E39: MOV-*, CAN-*, REC-*, WEB-* | F39: =COUNTA('RNF Accesibilidad'!B6:B14) -> 9 | G39: — | H39: =AVERAGE('RNF Accesibilidad'!F6:F14) -> 0 | I39: Abrir →
B40: 2 | C40: RNF Autenticación | D40: Inicio de sesión, registro y recuperación | E40: MOV-01, MOV-02, MOV-03, WEB-01 | F40: =COUNTA('RNF Autenticación'!B6:B10) -> 5 | G40: — | H40: =AVERAGE('RNF Autenticación'!F6:F10) -> 0 | I40: Abrir →
B41: 3 | C41: RNF Privacidad | D41: Privacidad y datos sensibles | E41: MOV-02, CAN-02, CAN-03, CAN-04, REC-05, WEB-03, API | F41: =COUNTA('RNF Privacidad'!B6:B10) -> 5 | G41: — | H41: =AVERAGE('RNF Privacidad'!F6:F10) -> 0 | I41: Abrir →
B42: 4 | C42: RNF Operativas Móvil | D42: Pantallas móviles (compartidas, candidato y reclutador) | E42: MOV-*, CAN-*, REC-* | F42: =COUNTA('RNF Operativas Móvil'!B6:B10) -> 5 | G42: — | H42: =AVERAGE('RNF Operativas Móvil'!F6:F10) -> 0 | I42: Abrir →
B43: 5 | C43: RNF CRUD Web | D43: Pantallas de administración web | E43: WEB-03 a WEB-08 | F43: =COUNTA('RNF CRUD Web'!B6:B10) -> 5 | G43: — | H43: =AVERAGE('RNF CRUD Web'!F6:F10) -> 0 | I43: Abrir →
B44: 6 | C44: RNF Dashboard | D44: Dashboard y estadísticas | E44: WEB-02 | F44: =COUNTA('RNF Dashboard'!B6:B9) -> 4 | G44: — | H44: =AVERAGE('RNF Dashboard'!F6:F9) -> 0 | I44: Abrir →
B45: 7 | C45: RNF Notificaciones | D45: Notificaciones (push, correo y en app) | E45: MOV-04, CAN-06, REC-05, REC-06, WEB-04, WEB-08 | F45: =COUNTA('RNF Notificaciones'!B6:B9) -> 4 | G45: — | H45: =AVERAGE('RNF Notificaciones'!F6:F9) -> 0 | I45: Abrir →
B46: 8 | C46: RNF API | D46: API REST (FastAPI) | E46: Backend FastAPI | F46: =COUNTA('RNF API'!B6:B11) -> 6 | G46: — | H46: =AVERAGE('RNF API'!F6:F11) -> 0 | I46: Abrir →
B47: Total | F47: =SUM(F39:F46) -> 43 | G47: — | H47: =AVERAGE(H39:H46) -> 0
B50: Simbología de identificadores
B51: MOV | C51: Pantallas móviles compartidas por candidato y reclutador
B52: CAN | C52: App móvil — rol Candidato
B53: REC | C53: App móvil — rol Empresa / Reclutador
B54: WEB | C54: Panel web (Laravel) — rol Administrador
B55: API | C55: Servicio REST (FastAPI) que comparten la app y el panel
B56: RNF-XXX | C56: ACC accesibilidad · AUT autenticación · PRV privacidad · MOV móvil · WEB administración web · DSH dashboard · NOT notificaciones · API

Sheet MOV-00 Splash
B1: ← Índice
B3: Requerimientos Funcionales
B4: Interfaz : MOV-00 — Splash
B5: ID | C5: Requerimiento | D5: Descripción | E5: Prioridad | F5: Avance
B6: RF-01 | C6: Mostrar splash con logo | D6: Mostrar la pantalla inicial con el logotipo de IncluTec y un texto alternativo legible por lector de pantalla; duración máxima de 3 s. | E6: Alta | F6: 0
B7: RF-02 | C7: Verificar sesión persistente | D7: Validar el token almacenado contra GET /auth/me; si responde 200, redirigir a la pantalla principal del rol (CAN-01 o REC-02); si responde 401, redirigir a MOV-01. | E7: Alta | F7: 0
B10: Requerimientos No Funcionales
B11: Interfaz : MOV-00 — Splash · Accesibilidad, Pantallas móviles
B12: ID | C12: Nombre | D12: Descripción | E12: Prioridad | F12: Avance
B13: RNF-ACC-01 | C13: ='RNF Accesibilidad'!C6 -> Estándar de accesibilidad | D13: ='RNF Accesibilidad'!D6 -> Las interfaces cumplen las pautas WCAG 2.1 nivel AA. | E13: ='RNF Accesibilidad'!E6 -> Alta | F13: ='RNF Accesibilidad'!F6 -> 0
B14: RNF-ACC-02 | C14: ='RNF Accesibilidad'!C7 -> Lectores de pantalla | D14: ='RNF Accesibilidad'!D7 -> Todos los elementos interactivos tienen etiqueta, rol y estado accesibles (accessibilityLabel/Role/State en React Native; HTML semántico y ARIA en Laravel) y funcionan con TalkBack, VoiceOver y NVDA. | E14: ='RNF Accesibilidad'!E7 -> Alta | F14: ='RNF Accesibilidad'!F7 -> 0
B15: RNF-ACC-03 | C15: ='RNF Accesibilidad'!C8 -> Contraste | D15: ='RNF Accesibilidad'!D8 -> Contraste mínimo de 4.5:1 para texto normal y 3:1 para texto grande y componentes de interfaz. | E15: ='RNF Accesibilidad'!E8 -> Alta | F15: ='RNF Accesibilidad'!F8 -> 0
B16: RNF-ACC-04 | C16: ='RNF Accesibilidad'!C9 -> Texto escalable | D16: ='RNF Accesibilidad'!D9 -> La interfaz respeta el tamaño de fuente del sistema y admite hasta 200 % de ampliación sin pérdida de contenido ni funcionalidad. | E16: ='RNF Accesibilidad'!E9 -> Alta | F16: ='RNF Accesibilidad'!F9 -> 0
B17: RNF-ACC-05 | C17: ='RNF Accesibilidad'!C10 -> Áreas táctiles | D17: ='RNF Accesibilidad'!D10 -> Los componentes táctiles tienen un área mínima de 48 × 48 dp en Android y 44 × 44 pt en iOS. | E17: ='RNF Accesibilidad'!E10 -> Alta | F17: ='RNF Accesibilidad'!F10 -> 0
B18: RNF-ACC-06 | C18: ='RNF Accesibilidad'!C11 -> Información no dependiente del color | D18: ='RNF Accesibilidad'!D11 -> Estados, errores y porcentajes se comunican con texto o ícono además del color. | E18: ='RNF Accesibilidad'!E11 -> Alta | F18: ='RNF Accesibilidad'!F11 -> 0
B19: RNF-ACC-07 | C19: ='RNF Accesibilidad'!C12 -> Navegación por teclado | D19: ='RNF Accesibilidad'!D12 -> El panel web puede operarse completamente con teclado y la app admite teclado externo y control por interruptores (Switch Access / Control por botón), con foco visible y orden lógico. | E19: ='RNF Accesibilidad'!E12 -> Alta | F19: ='RNF Accesibilidad'!F12 -> 0
B20: RNF-ACC-08 | C20: ='RNF Accesibilidad'!C13 -> Lenguaje claro | D20: ='RNF Accesibilidad'!D13 -> Textos en lenguaje claro y sin tecnicismos; los errores de formulario indican qué campo falla y cómo corregirlo. | E20: ='RNF Accesibilidad'!E13 -> Media | F20: ='RNF Accesibilidad'!F13 -> 0
B21: RNF-ACC-09 | C21: ='RNF Accesibilidad'!C14 -> Movimiento reducido | D21: ='RNF Accesibilidad'!D14 -> Se respeta la preferencia de «reducir movimiento» del sistema y no hay contenido parpadeante. | E21: ='RNF Accesibilidad'!E14 -> Baja | F21: ='RNF Accesibilidad'!F14 -> 0
B22: RNF-MOV-01 | C22: ='RNF Operativas Móvil'!C6 -> Desempeño | D22: ='RNF Operativas Móvil'!D6 -> Tiempo de respuesta de las pantallas ≤ 2 s en el percentil 95 sobre red 4G. | E22: ='RNF Operativas Móvil'!E6 -> Alta | F22: ='RNF Operativas Móvil'!F6 -> 0
B23: RNF-MOV-02 | C23: ='RNF Operativas Móvil'!C7 -> Compatibilidad | D23: ='RNF Operativas Móvil'!D7 -> Ejecutable en Android 8+ e iOS 15+ con un solo código base (React Native + Expo). | E23: ='RNF Operativas Móvil'!E7 -> Alta | F23: ='RNF Operativas Móvil'!F7 -> 0
B24: RNF-MOV-03 | C24: ='RNF Operativas Móvil'!C8 -> Retroalimentación | D24: ='RNF Operativas Móvil'!D8 -> Toda acción que tarde más de 300 ms muestra un indicador de carga anunciado al lector de pantalla. | E24: ='RNF Operativas Móvil'!E8 -> Media | F24: ='RNF Operativas Móvil'!F8 -> 0
B25: RNF-MOV-04 | C25: ='RNF Operativas Móvil'!C9 -> Tolerancia a fallas de red | D25: ='RNF Operativas Móvil'!D9 -> La app conserva en caché el último listado de vacantes y postulaciones y avisa cuando no hay conexión; los formularios no pierden lo capturado. | E25: ='RNF Operativas Móvil'!E9 -> Media | F25: ='RNF Operativas Móvil'!F9 -> 0
B26: RNF-MOV-05 | C26: ='RNF Operativas Móvil'!C10 -> Orientación | D26: ='RNF Operativas Móvil'!D10 -> Las pantallas funcionan en orientación vertical y horizontal. | E26: ='RNF Operativas Móvil'!E10 -> Baja | F26: ='RNF Operativas Móvil'!F10 -> 0
B27: Los RNF provienen de las hojas generales «RNF …» y se actualizan automáticamente; edita el texto y el avance en su hoja general.
B30: Elaborado por: | C30: Alan David Santiago de Vicente, Ricardo Méndez Rodríguez, Eduardo Daniel Licea González
B31: Responsable: | C31: Equipo IncluTec — Ingeniería en Sistemas Computacionales
B32: Dependencias: | C32: API REST (FastAPI), Base de datos PostgreSQL
B33: Entrega: | C33: 28 de octubre de 2026
B36: Acotaciones de Avance
B37: 100% | C37: Completada
B38: 50% | C38: En proceso
B39: 0% | C39: No Iniciada
B42: Autorizado:

Sheet MOV-01 Login móvil
B1: ← Índice
B3: Requerimientos Funcionales
B4: Interfaz : MOV-01 — Inicio de sesión (móvil)
B5: ID | C5: Requerimiento | D5: Descripción | E5: Prioridad | F5: Avance
B6: RF-01 | C6: Captura de credenciales | D6: Capturar correo (formato RFC 5322) y contraseña (≥ 8 caracteres); el botón «Iniciar sesión» se habilita solo si ambos campos son válidos. Opción para mostrar u ocultar la contraseña. | E6: Alta | F6: 0
B7: RF-02 | C7: Autenticación contra API | D7: Enviar las credenciales a POST /auth/login; al recibir 200, almacenar el JWT en expo-secure-store. | E7: Alta | F7: 0
B8: RF-03 | C8: Manejo de errores | D8: Mostrar un mensaje específico ante 401 («Correo o contraseña incorrectos»), 423 («Cuenta suspendida») o 5xx («Servicio no disponible»), sin exponer detalles técnicos y anunciándolo al lector de pantalla. | E8: Alta | F8: 0
B9: RF-04 | C9: Redirección por rol | D9: Leer el rol del JWT y navegar a CAN-01 (candidato) o REC-02 (reclutador). Si el rol es «administrador», informar que debe usar el panel web y cerrar la sesión. | E9: Alta | F9: 0
B10: RF-05 | C10: Accesos secundarios | D10: Mostrar enlaces a MOV-02 (crear cuenta) y MOV-03 (recuperar contraseña). | E10: Media | F10: 0
B13: Requerimientos No Funcionales
B14: Interfaz : MOV-01 — Inicio de sesión (móvil) · Accesibilidad, Inicio de sesión, registro y recuperación, Pantallas móviles
B15: ID | C15: Nombre | D15: Descripción | E15: Prioridad | F15: Avance
B16: RNF-ACC-01 | C16: ='RNF Accesibilidad'!C6 -> Estándar de accesibilidad | D16: ='RNF Accesibilidad'!D6 -> Las interfaces cumplen las pautas WCAG 2.1 nivel AA. | E16: ='RNF Accesibilidad'!E6 -> Alta | F16: ='RNF Accesibilidad'!F6 -> 0
B17: RNF-ACC-02 | C17: ='RNF Accesibilidad'!C7 -> Lectores de pantalla | D17: ='RNF Accesibilidad'!D7 -> Todos los elementos interactivos tienen etiqueta, rol y estado accesibles (accessibilityLabel/Role/State en React Native; HTML semántico y ARIA en Laravel) y funcionan con TalkBack, VoiceOver y NVDA. | E17: ='RNF Accesibilidad'!E7 -> Alta | F17: ='RNF Accesibilidad'!F7 -> 0
B18: RNF-ACC-03 | C18: ='RNF Accesibilidad'!C8 -> Contraste | D18: ='RNF Accesibilidad'!D8 -> Contraste mínimo de 4.5:1 para texto normal y 3:1 para texto grande y componentes de interfaz. | E18: ='RNF Accesibilidad'!E8 -> Alta | F18: ='RNF Accesibilidad'!F8 -> 0
B19: RNF-ACC-04 | C19: ='RNF Accesibilidad'!C9 -> Texto escalable | D19: ='RNF Accesibilidad'!D9 -> La interfaz respeta el tamaño de fuente del sistema y admite hasta 200 % de ampliación sin pérdida de contenido ni funcionalidad. | E19: ='RNF Accesibilidad'!E9 -> Alta | F19: ='RNF Accesibilidad'!F9 -> 0
B20: RNF-ACC-05 | C20: ='RNF Accesibilidad'!C10 -> Áreas táctiles | D20: ='RNF Accesibilidad'!D10 -> Los componentes táctiles tienen un área mínima de 48 × 48 dp en Android y 44 × 44 pt en iOS. | E20: ='RNF Accesibilidad'!E10 -> Alta | F20: ='RNF Accesibilidad'!F10 -> 0
B21: RNF-ACC-06 | C21: ='RNF Accesibilidad'!C11 -> Información no dependiente del color | D21: ='RNF Accesibilidad'!D11 -> Estados, errores y porcentajes se comunican con texto o ícono además del color. | E21: ='RNF Accesibilidad'!E11 -> Alta | F21: ='RNF Accesibilidad'!F11 -> 0
B22: RNF-ACC-07 | C22: ='RNF Accesibilidad'!C12 -> Navegación por teclado | D22: ='RNF Accesibilidad'!D12 -> El panel web puede operarse completamente con teclado y la app admite teclado externo y control por interruptores (Switch Access / Control por botón), con foco visible y orden lógico. | E22: ='RNF Accesibilidad'!E12 -> Alta | F22: ='RNF Accesibilidad'!F12 -> 0
B23: RNF-ACC-08 | C23: ='RNF Accesibilidad'!C13 -> Lenguaje claro | D23: ='RNF Accesibilidad'!D13 -> Textos en lenguaje claro y sin tecnicismos; los errores de formulario indican qué campo falla y cómo corregirlo. | E23: ='RNF Accesibilidad'!E13 -> Media | F23: ='RNF Accesibilidad'!F13 -> 0
B24: RNF-ACC-09 | C24: ='RNF Accesibilidad'!C14 -> Movimiento reducido | D24: ='RNF Accesibilidad'!D14 -> Se respeta la preferencia de «reducir movimiento» del sistema y no hay contenido parpadeante. | E24: ='RNF Accesibilidad'!E14 -> Baja | F24: ='RNF Accesibilidad'!F14 -> 0
B25: RNF-AUT-01 | C25: ='RNF Autenticación'!C6 -> Seguridad — contraseñas | D25: ='RNF Autenticación'!D6 -> Las contraseñas se almacenan únicamente como hash bcrypt (cost ≥ 10); nunca en texto plano ni en registros. | E25: ='RNF Autenticación'!E6 -> Alta | F25: ='RNF Autenticación'!F6 -> 0
B26: RNF-AUT-02 | C26: ='RNF Autenticación'!C7 -> Seguridad — tokens | D26: ='RNF Autenticación'!D7 -> JWT firmado HS256 con expiración de 8 h; transporte HTTPS obligatorio; almacenamiento en expo-secure-store (móvil) y en la sesión del servidor Laravel (web). | E26: ='RNF Autenticación'!E7 -> Alta | F26: ='RNF Autenticación'!F7 -> 0
B27: RNF-AUT-03 | C27: ='RNF Autenticación'!C8 -> Protección contra fuerza bruta | D27: ='RNF Autenticación'!D8 -> Bloqueo temporal de 15 minutos tras 5 intentos fallidos consecutivos por cuenta o por IP. | E27: ='RNF Autenticación'!E8 -> Alta | F27: ='RNF Autenticación'!F8 -> 0
B28: RNF-AUT-04 | C28: ='RNF Autenticación'!C9 -> Mensajes neutros | D28: ='RNF Autenticación'!D9 -> Los mensajes de error no revelan si un correo existe en el sistema. | E28: ='RNF Autenticación'!E9 -> Media | F28: ='RNF Autenticación'!F9 -> 0
B29: RNF-AUT-05 | C29: ='RNF Autenticación'!C10 -> Desempeño | D29: ='RNF Autenticación'!D10 -> El inicio de sesión responde en ≤ 1.5 s en el percentil 95. | E29: ='RNF Autenticación'!E10 -> Media | F29: ='RNF Autenticación'!F10 -> 0
B30: RNF-MOV-01 | C30: ='RNF Operativas Móvil'!C6 -> Desempeño | D30: ='RNF Operativas Móvil'!D6 -> Tiempo de respuesta de las pantallas ≤ 2 s en el percentil 95 sobre red 4G. | E30: ='RNF Operativas Móvil'!E6 -> Alta | F30: ='RNF Operativas Móvil'!F6 -> 0
B31: RNF-MOV-02 | C31: ='RNF Operativas Móvil'!C7 -> Compatibilidad | D31: ='RNF Operativas Móvil'!D7 -> Ejecutable en Android 8+ e iOS 15+ con un solo código base (React Native + Expo). | E31: ='RNF Operativas Móvil'!E7 -> Alta | F31: ='RNF Operativas Móvil'!F7 -> 0
B32: RNF-MOV-03 | C32: ='RNF Operativas Móvil'!C8 -> Retroalimentación | D32: ='RNF Operativas Móvil'!D8 -> Toda acción que tarde más de 300 ms muestra un indicador de carga anunciado al lector de pantalla. | E32: ='RNF Operativas Móvil'!E8 -> Media | F32: ='RNF Operativas Móvil'!F8 -> 0
B33: RNF-MOV-04 | C33: ='RNF Operativas Móvil'!C9 -> Tolerancia a fallas de red | D33: ='RNF Operativas Móvil'!D9 -> La app conserva en caché el último listado de vacantes y postulaciones y avisa cuando no hay conexión; los formularios no pierden lo capturado. | E33: ='RNF Operativas Móvil'!E9 -> Media | F33: ='RNF Operativas Móvil'!F9 -> 0
B34: RNF-MOV-05 | C34: ='RNF Operativas Móvil'!C10 -> Orientación | D34: ='RNF Operativas Móvil'!D10 -> Las pantallas funcionan en orientación vertical y horizontal. | E34: ='RNF Operativas Móvil'!E10 -> Baja | F34: ='RNF Operativas Móvil'!F10 -> 0
B35: Los RNF provienen de las hojas generales «RNF …» y se actualizan automáticamente; edita el texto y el avance en su hoja general.
B38: Elaborado por: | C38: Alan David Santiago de Vicente, Ricardo Méndez Rodríguez, Eduardo Daniel Licea González
B39: Responsable: | C39: Equipo IncluTec — Ingeniería en Sistemas Computacionales
B40: Dependencias: | C40: API REST (FastAPI), Base de datos PostgreSQL
B41: Entrega: | C41: 28 de octubre de 2026
B44: Acotaciones de Avance
B45: 100% | C45: Completada
B46: 50% | C46: En proceso
B47: 0% | C47: No Iniciada
B50: Autorizado:

Sheet MOV-02 Registro
B1: ← Índice
B3: Requerimientos Funcionales
B4: Interfaz : MOV-02 — Registro de cuenta
B5: ID | C5: Requerimiento | D5: Descripción | E5: Prioridad | F5: Avance
B6: RF-01 | C6: Selección de tipo de cuenta | D6: Permitir elegir entre «Busco empleo» (candidato) y «Represento a una empresa» (reclutador) antes de mostrar el formulario correspondiente. | E6: Alta | F6: 0
B7: RF-02 | C7: Registro de candidato | D7: Capturar nombre(s), apellidos, correo, teléfono (10 dígitos), municipio/estado y contraseña; enviar a POST /auth/registro/candidato. | E7: Alta | F7: 0
B8: RF-03 | C8: Registro de reclutador y empresa | D8: Capturar datos del reclutador (nombre, puesto, correo, teléfono, contraseña) y de la empresa (razón social, nombre comercial, RFC de 12 o 13 caracteres, sector, tamaño, municipio/estado); enviar a POST /auth/registro/reclutador. La empresa se crea en estado «pendiente de validación». | E8: Alta | F8: 0
B9: RF-04 | C9: Política de contraseña | D9: Validar contraseña de 8 a 64 caracteres con al menos una letra y un número, y confirmar que ambas capturas coincidan. | E9: Alta | F9: 0
B10: RF-05 | C10: Aviso de privacidad y consentimiento | D10: Mostrar el aviso de privacidad y exigir su aceptación. Para candidatos, solicitar además el consentimiento expreso para el tratamiento de datos sobre necesidades de ajuste (dato personal sensible, LFPDPPP); sin él, la cuenta se crea pero esa sección queda deshabilitada. | E10: Alta | F10: 0
B11: RF-06 | C11: Unicidad de correo | D11: Si el API responde 409, indicar que el correo ya está registrado y ofrecer ir a MOV-01 o MOV-03. | E11: Media | F11: 0
B12: RF-07 | C12: Inicio tras registro | D12: Al recibir 201, iniciar sesión automáticamente y dirigir al candidato a CAN-03 (completar perfil) y al reclutador a REC-01 (perfil de la organización). | E12: Media | F12: 0
B15: Requerimientos No Funcionales
B16: Interfaz : MOV-02 — Registro de cuenta · Accesibilidad, Inicio de sesión, registro y recuperación, Privacidad y datos sensibles, Pantallas móviles
B17: ID | C17: Nombre | D17: Descripción | E17: Prioridad | F17: Avance
B18: RNF-ACC-01 | C18: ='RNF Accesibilidad'!C6 -> Estándar de accesibilidad | D18: ='RNF Accesibilidad'!D6 -> Las interfaces cumplen las pautas WCAG 2.1 nivel AA. | E18: ='RNF Accesibilidad'!E6 -> Alta | F18: ='RNF Accesibilidad'!F6 -> 0
B19: RNF-ACC-02 | C19: ='RNF Accesibilidad'!C7 -> Lectores de pantalla | D19: ='RNF Accesibilidad'!D7 -> Todos los elementos interactivos tienen etiqueta, rol y estado accesibles (accessibilityLabel/Role/State en React Native; HTML semántico y ARIA en Laravel) y funcionan con TalkBack, VoiceOver y NVDA. | E19: ='RNF Accesibilidad'!E7 -> Alta | F19: ='RNF Accesibilidad'!F7 -> 0
B20: RNF-ACC-03 | C20: ='RNF Accesibilidad'!C8 -> Contraste | D20: ='RNF Accesibilidad'!D8 -> Contraste mínimo de 4.5:1 para texto normal y 3:1 para texto grande y componentes de interfaz. | E20: ='RNF Accesibilidad'!E8 -> Alta | F20: ='RNF Accesibilidad'!F8 -> 0
B21: RNF-ACC-04 | C21: ='RNF Accesibilidad'!C9 -> Texto escalable | D21: ='RNF Accesibilidad'!D9 -> La interfaz respeta el tamaño de fuente del sistema y admite hasta 200 % de ampliación sin pérdida de contenido ni funcionalidad. | E21: ='RNF Accesibilidad'!E9 -> Alta | F21: ='RNF Accesibilidad'!F9 -> 0
B22: RNF-ACC-05 | C22: ='RNF Accesibilidad'!C10 -> Áreas táctiles | D22: ='RNF Accesibilidad'!D10 -> Los componentes táctiles tienen un área mínima de 48 × 48 dp en Android y 44 × 44 pt en iOS. | E22: ='RNF Accesibilidad'!E10 -> Alta | F22: ='RNF Accesibilidad'!F10 -> 0
B23: RNF-ACC-06 | C23: ='RNF Accesibilidad'!C11 -> Información no dependiente del color | D23: ='RNF Accesibilidad'!D11 -> Estados, errores y porcentajes se comunican con texto o ícono además del color. | E23: ='RNF Accesibilidad'!E11 -> Alta | F23: ='RNF Accesibilidad'!F11 -> 0
B24: RNF-ACC-07 | C24: ='RNF Accesibilidad'!C12 -> Navegación por teclado | D24: ='RNF Accesibilidad'!D12 -> El panel web puede operarse completamente con teclado y la app admite teclado externo y control por interruptores (Switch Access / Control por botón), con foco visible y orden lógico. | E24: ='RNF Accesibilidad'!E12 -> Alta | F24: ='RNF Accesibilidad'!F12 -> 0
B25: RNF-ACC-08 | C25: ='RNF Accesibilidad'!C13 -> Lenguaje claro | D25: ='RNF Accesibilidad'!D13 -> Textos en lenguaje claro y sin tecnicismos; los errores de formulario indican qué campo falla y cómo corregirlo. | E25: ='RNF Accesibilidad'!E13 -> Media | F25: ='RNF Accesibilidad'!F13 -> 0
B26: RNF-ACC-09 | C26: ='RNF Accesibilidad'!C14 -> Movimiento reducido | D26: ='RNF Accesibilidad'!D14 -> Se respeta la preferencia de «reducir movimiento» del sistema y no hay contenido parpadeante. | E26: ='RNF Accesibilidad'!E14 -> Baja | F26: ='RNF Accesibilidad'!F14 -> 0
B27: RNF-AUT-01 | C27: ='RNF Autenticación'!C6 -> Seguridad — contraseñas | D27: ='RNF Autenticación'!D6 -> Las contraseñas se almacenan únicamente como hash bcrypt (cost ≥ 10); nunca en texto plano ni en registros. | E27: ='RNF Autenticación'!E6 -> Alta | F27: ='RNF Autenticación'!F6 -> 0
B28: RNF-AUT-02 | C28: ='RNF Autenticación'!C7 -> Seguridad — tokens | D28: ='RNF Autenticación'!D7 -> JWT firmado HS256 con expiración de 8 h; transporte HTTPS obligatorio; almacenamiento en expo-secure-store (móvil) y en la sesión del servidor Laravel (web). | E28: ='RNF Autenticación'!E7 -> Alta | F28: ='RNF Autenticación'!F7 -> 0
B29: RNF-AUT-03 | C29: ='RNF Autenticación'!C8 -> Protección contra fuerza bruta | D29: ='RNF Autenticación'!D8 -> Bloqueo temporal de 15 minutos tras 5 intentos fallidos consecutivos por cuenta o por IP. | E29: ='RNF Autenticación'!E8 -> Alta | F29: ='RNF Autenticación'!F8 -> 0
B30: RNF-AUT-04 | C30: ='RNF Autenticación'!C9 -> Mensajes neutros | D30: ='RNF Autenticación'!D9 -> Los mensajes de error no revelan si un correo existe en el sistema. | E30: ='RNF Autenticación'!E9 -> Media | F30: ='RNF Autenticación'!F9 -> 0
B31: RNF-AUT-05 | C31: ='RNF Autenticación'!C10 -> Desempeño | D31: ='RNF Autenticación'!D10 -> El inicio de sesión responde en ≤ 1.5 s en el percentil 95. | E31: ='RNF Autenticación'!E10 -> Media | F31: ='RNF Autenticación'!F10 -> 0
B32: RNF-PRV-01 | C32: ='RNF Privacidad'!C6 -> Cumplimiento legal | D32: ='RNF Privacidad'!D6 -> El tratamiento de datos personales cumple la Ley Federal de Protección de Datos Personales en Posesión de los Particulares, con aviso de privacidad y consentimiento expreso para datos sensibles. | E32: ='RNF Privacidad'!E6 -> Alta | F32: ='RNF Privacidad'!F6 -> 0
B33: RNF-PRV-02 | C33: ='RNF Privacidad'!C7 -> Minimización de datos | D33: ='RNF Privacidad'!D7 -> El sistema registra necesidades de ajuste y no diagnósticos, tipos de discapacidad ni documentos médicos. | E33: ='RNF Privacidad'!E7 -> Alta | F33: ='RNF Privacidad'!F7 -> 0
B34: RNF-PRV-03 | C34: ='RNF Privacidad'!C8 -> Control del candidato | D34: ='RNF Privacidad'!D8 -> Las necesidades de ajuste solo son visibles para el candidato y para las empresas a cuyas vacantes se postuló con consentimiento; el administrador solo ve datos agregados. | E34: ='RNF Privacidad'!E8 -> Alta | F34: ='RNF Privacidad'!F8 -> 0
B35: RNF-PRV-04 | C35: ='RNF Privacidad'!C9 -> Derechos ARCO | D35: ='RNF Privacidad'!D9 -> El candidato puede consultar, corregir y eliminar sus datos; la eliminación anonimiza sus postulaciones históricas en un plazo máximo de 30 días. | E35: ='RNF Privacidad'!E9 -> Alta | F35: ='RNF Privacidad'!F9 -> 0
B36: RNF-PRV-05 | C36: ='RNF Privacidad'!C10 -> Registros sin datos sensibles | D36: ='RNF Privacidad'!D10 -> Los logs del servidor y los mensajes push no incluyen necesidades de ajuste ni datos de contacto. | E36: ='RNF Privacidad'!E10 -> Alta | F36: ='RNF Privacidad'!F10 -> 0
B37: RNF-MOV-01 | C37: ='RNF Operativas Móvil'!C6 -> Desempeño | D37: ='RNF Operativas Móvil'!D6 -> Tiempo de respuesta de las pantallas ≤ 2 s en el percentil 95 sobre red 4G. | E37: ='RNF Operativas Móvil'!E6 -> Alta | F37: ='RNF Operativas Móvil'!F6 -> 0
B38: RNF-MOV-02 | C38: ='RNF Operativas Móvil'!C7 -> Compatibilidad | D38: ='RNF Operativas Móvil'!D7 -> Ejecutable en Android 8+ e iOS 15+ con un solo código base (React Native + Expo). | E38: ='RNF Operativas Móvil'!E7 -> Alta | F38: ='RNF Operativas Móvil'!F7 -> 0
B39: RNF-MOV-03 | C39: ='RNF Operativas Móvil'!C8 -> Retroalimentación | D39: ='RNF Operativas Móvil'!D8 -> Toda acción que tarde más de 300 ms muestra un indicador de carga anunciado al lector de pantalla. | E39: ='RNF Operativas Móvil'!E8 -> Media | F39: ='RNF Operativas Móvil'!F8 -> 0
B40: RNF-MOV-04 | C40: ='RNF Operativas Móvil'!C9 -> Tolerancia a fallas de red | D40: ='RNF Operativas Móvil'!D9 -> La app conserva en caché el último listado de vacantes y postulaciones y avisa cuando no hay conexión; los formularios no pierden lo capturado. | E40: ='RNF Operativas Móvil'!E9 -> Media | F40: ='RNF Operativas Móvil'!F9 -> 0
B41: RNF-MOV-05 | C41: ='RNF Operativas Móvil'!C10 -> Orientación | D41: ='RNF Operativas Móvil'!D10 -> Las pantallas funcionan en orientación vertical y horizontal. | E41: ='RNF Operativas Móvil'!E10 -> Baja | F41: ='RNF Operativas Móvil'!F10 -> 0
B42: Los RNF provienen de las hojas generales «RNF …» y se actualizan automáticamente; edita el texto y el avance en su hoja general.
B45: Elaborado por: | C45: Alan David Santiago de Vicente, Ricardo Méndez Rodríguez, Eduardo Daniel Licea González
B46: Responsable: | C46: Equipo IncluTec — Ingeniería en Sistemas Computacionales
B47: Dependencias: | C47: API REST (FastAPI), Base de datos PostgreSQL; catálogos de sector y tamaño de empresa
B48: Entrega: | C48: 28 de octubre de 2026
B51: Acotaciones de Avance
B52: 100% | C52: Completada
B53: 50% | C53: En proceso
B54: 0% | C54: No Iniciada
B57: Autorizado:

Sheet MOV-03 Recuperar contraseña
B1: ← Índice
B3: Requerimientos Funcionales
B4: Interfaz : MOV-03 — Recuperar contraseña
B5: ID | C5: Requerimiento | D5: Descripción | E5: Prioridad | F5: Avance
B6: RF-01 | C6: Solicitud de código | D6: Capturar el correo y enviarlo a POST /auth/password/solicitar; mostrar siempre el mismo mensaje de confirmación, exista o no la cuenta. | E6: Alta | F6: 0
B7: RF-02 | C7: Validación de código | D7: Capturar el código de 6 dígitos recibido por correo; el código vence a los 15 minutos y admite máximo 5 intentos. | E7: Alta | F7: 0
B8: RF-03 | C8: Nueva contraseña | D8: Capturar y confirmar la nueva contraseña (misma política que MOV-02) y enviarla a POST /auth/password/restablecer; al recibir 200, regresar a MOV-01 con mensaje de éxito. | E8: Alta | F8: 0
B9: RF-04 | C9: Reenvío de código | D9: Permitir reenviar el código una vez transcurridos 60 s desde el envío anterior. | E9: Baja | F9: 0
B12: Requerimientos No Funcionales
B13: Interfaz : MOV-03 — Recuperar contraseña · Accesibilidad, Inicio de sesión, registro y recuperación, Pantallas móviles
B14: ID | C14: Nombre | D14: Descripción | E14: Prioridad | F14: Avance
B15: RNF-ACC-01 | C15: ='RNF Accesibilidad'!C6 -> Estándar de accesibilidad | D15: ='RNF Accesibilidad'!D6 -> Las interfaces cumplen las pautas WCAG 2.1 nivel AA. | E15: ='RNF Accesibilidad'!E6 -> Alta | F15: ='RNF Accesibilidad'!F6 -> 0
B16: RNF-ACC-02 | C16: ='RNF Accesibilidad'!C7 -> Lectores de pantalla | D16: ='RNF Accesibilidad'!D7 -> Todos los elementos interactivos tienen etiqueta, rol y estado accesibles (accessibilityLabel/Role/State en React Native; HTML semántico y ARIA en Laravel) y funcionan con TalkBack, VoiceOver y NVDA. | E16: ='RNF Accesibilidad'!E7 -> Alta | F16: ='RNF Accesibilidad'!F7 -> 0
B17: RNF-ACC-03 | C17: ='RNF Accesibilidad'!C8 -> Contraste | D17: ='RNF Accesibilidad'!D8 -> Contraste mínimo de 4.5:1 para texto normal y 3:1 para texto grande y componentes de interfaz. | E17: ='RNF Accesibilidad'!E8 -> Alta | F17: ='RNF Accesibilidad'!F8 -> 0
B18: RNF-ACC-04 | C18: ='RNF Accesibilidad'!C9 -> Texto escalable | D18: ='RNF Accesibilidad'!D9 -> La interfaz respeta el tamaño de fuente del sistema y admite hasta 200 % de ampliación sin pérdida de contenido ni funcionalidad. | E18: ='RNF Accesibilidad'!E9 -> Alta | F18: ='RNF Accesibilidad'!F9 -> 0
B19: RNF-ACC-05 | C19: ='RNF Accesibilidad'!C10 -> Áreas táctiles | D19: ='RNF Accesibilidad'!D10 -> Los componentes táctiles tienen un área mínima de 48 × 48 dp en Android y 44 × 44 pt en iOS. | E19: ='RNF Accesibilidad'!E10 -> Alta | F19: ='RNF Accesibilidad'!F10 -> 0
B20: RNF-ACC-06 | C20: ='RNF Accesibilidad'!C11 -> Información no dependiente del color | D20: ='RNF Accesibilidad'!D11 -> Estados, errores y porcentajes se comunican con texto o ícono además del color. | E20: ='RNF Accesibilidad'!E11 -> Alta | F20: ='RNF Accesibilidad'!F11 -> 0
B21: RNF-ACC-07 | C21: ='RNF Accesibilidad'!C12 -> Navegación por teclado | D21: ='RNF Accesibilidad'!D12 -> El panel web puede operarse completamente con teclado y la app admite teclado externo y control por interruptores (Switch Access / Control por botón), con foco visible y orden lógico. | E21: ='RNF Accesibilidad'!E12 -> Alta | F21: ='RNF Accesibilidad'!F12 -> 0
B22: RNF-ACC-08 | C22: ='RNF Accesibilidad'!C13 -> Lenguaje claro | D22: ='RNF Accesibilidad'!D13 -> Textos en lenguaje claro y sin tecnicismos; los errores de formulario indican qué campo falla y cómo corregirlo. | E22: ='RNF Accesibilidad'!E13 -> Media | F22: ='RNF Accesibilidad'!F13 -> 0
B23: RNF-ACC-09 | C23: ='RNF Accesibilidad'!C14 -> Movimiento reducido | D23: ='RNF Accesibilidad'!D14 -> Se respeta la preferencia de «reducir movimiento» del sistema y no hay contenido parpadeante. | E23: ='RNF Accesibilidad'!E14 -> Baja | F23: ='RNF Accesibilidad'!F14 -> 0
B24: RNF-AUT-01 | C24: ='RNF Autenticación'!C6 -> Seguridad — contraseñas | D24: ='RNF Autenticación'!D6 -> Las contraseñas se almacenan únicamente como hash bcrypt (cost ≥ 10); nunca en texto plano ni en registros. | E24: ='RNF Autenticación'!E6 -> Alta | F24: ='RNF Autenticación'!F6 -> 0
B25: RNF-AUT-02 | C25: ='RNF Autenticación'!C7 -> Seguridad — tokens | D25: ='RNF Autenticación'!D7 -> JWT firmado HS256 con expiración de 8 h; transporte HTTPS obligatorio; almacenamiento en expo-secure-store (móvil) y en la sesión del servidor Laravel (web). | E25: ='RNF Autenticación'!E7 -> Alta | F25: ='RNF Autenticación'!F7 -> 0
B26: RNF-AUT-03 | C26: ='RNF Autenticación'!C8 -> Protección contra fuerza bruta | D26: ='RNF Autenticación'!D8 -> Bloqueo temporal de 15 minutos tras 5 intentos fallidos consecutivos por cuenta o por IP. | E26: ='RNF Autenticación'!E8 -> Alta | F26: ='RNF Autenticación'!F8 -> 0
B27: RNF-AUT-04 | C27: ='RNF Autenticación'!C9 -> Mensajes neutros | D27: ='RNF Autenticación'!D9 -> Los mensajes de error no revelan si un correo existe en el sistema. | E27: ='RNF Autenticación'!E9 -> Media | F27: ='RNF Autenticación'!F9 -> 0
B28: RNF-AUT-05 | C28: ='RNF Autenticación'!C10 -> Desempeño | D28: ='RNF Autenticación'!D10 -> El inicio de sesión responde en ≤ 1.5 s en el percentil 95. | E28: ='RNF Autenticación'!E10 -> Media | F28: ='RNF Autenticación'!F10 -> 0
B29: RNF-MOV-01 | C29: ='RNF Operativas Móvil'!C6 -> Desempeño | D29: ='RNF Operativas Móvil'!D6 -> Tiempo de respuesta de las pantallas ≤ 2 s en el percentil 95 sobre red 4G. | E29: ='RNF Operativas Móvil'!E6 -> Alta | F29: ='RNF Operativas Móvil'!F6 -> 0
B30: RNF-MOV-02 | C30: ='RNF Operativas Móvil'!C7 -> Compatibilidad | D30: ='RNF Operativas Móvil'!D7 -> Ejecutable en Android 8+ e iOS 15+ con un solo código base (React Native + Expo). | E30: ='RNF Operativas Móvil'!E7 -> Alta | F30: ='RNF Operativas Móvil'!F7 -> 0
B31: RNF-MOV-03 | C31: ='RNF Operativas Móvil'!C8 -> Retroalimentación | D31: ='RNF Operativas Móvil'!D8 -> Toda acción que tarde más de 300 ms muestra un indicador de carga anunciado al lector de pantalla. | E31: ='RNF Operativas Móvil'!E8 -> Media | F31: ='RNF Operativas Móvil'!F8 -> 0
B32: RNF-MOV-04 | C32: ='RNF Operativas Móvil'!C9 -> Tolerancia a fallas de red | D32: ='RNF Operativas Móvil'!D9 -> La app conserva en caché el último listado de vacantes y postulaciones y avisa cuando no hay conexión; los formularios no pierden lo capturado. | E32: ='RNF Operativas Móvil'!E9 -> Media | F32: ='RNF Operativas Móvil'!F9 -> 0
B33: RNF-MOV-05 | C33: ='RNF Operativas Móvil'!C10 -> Orientación | D33: ='RNF Operativas Móvil'!D10 -> Las pantallas funcionan en orientación vertical y horizontal. | E33: ='RNF Operativas Móvil'!E10 -> Baja | F33: ='RNF Operativas Móvil'!F10 -> 0
B34: Los RNF provienen de las hojas generales «RNF …» y se actualizan automáticamente; edita el texto y el avance en su hoja general.
B37: Elaborado por: | C37: Alan David Santiago de Vicente, Ricardo Méndez Rodríguez, Eduardo Daniel Licea González
B38: Responsable: | C38: Equipo IncluTec — Ingeniería en Sistemas Computacionales
B39: Dependencias: | C39: API REST (FastAPI), Base de datos PostgreSQL; servicio de correo (SMTP)
B40: Entrega: | C40: 28 de octubre de 2026
B43: Acotaciones de Avance
B44: 100% | C44: Completada
B45: 50% | C45: En proceso
B46: 0% | C46: No Iniciada
B49: Autorizado:

Sheet MOV-04 Notificaciones
B1: ← Índice
B3: Requerimientos Funcionales
B4: Interfaz : MOV-04 — Notificaciones
B5: ID | C5: Requerimiento | D5: Descripción | E5: Prioridad | F5: Avance
B6: RF-01 | C6: Registro del dispositivo | D6: Al iniciar sesión, solicitar permiso de notificaciones y registrar el token con POST /dispositivos. | E6: Alta | F6: 0
B7: RF-02 | C7: Listado de notificaciones | D7: Listar las notificaciones del usuario vía GET /notificaciones (paginado de 20, más recientes primero) con título, mensaje, fecha y estado leída/no leída. | E7: Alta | F7: 0
B8: RF-03 | C8: Indicador de no leídas | D8: Mostrar en la barra de navegación un contador de notificaciones no leídas, anunciado por el lector de pantalla (p. ej. «Notificaciones, 3 sin leer»). | E8: Media | F8: 0
B9: RF-04 | C9: Marcar como leída | D9: Marcar una notificación como leída al abrirla (PATCH /notificaciones/{id}/leida) y permitir marcar todas (PATCH /notificaciones/leidas). | E9: Media | F9: 0
B10: RF-05 | C10: Navegación al origen | D10: Al tocar una notificación, abrir la pantalla relacionada (CAN-06, REC-05, REC-06 o REC-01) con el identificador correspondiente. | E10: Media | F10: 0
B11: RF-06 | C11: Preferencias de canal | D11: Permitir activar o desactivar el aviso por push y por correo para cada tipo de evento vía PUT /notificaciones/preferencias. | E11: Baja | F11: 0
B14: Requerimientos No Funcionales
B15: Interfaz : MOV-04 — Notificaciones · Accesibilidad, Pantallas móviles, Notificaciones
B16: ID | C16: Nombre | D16: Descripción | E16: Prioridad | F16: Avance
B17: RNF-ACC-01 | C17: ='RNF Accesibilidad'!C6 -> Estándar de accesibilidad | D17: ='RNF Accesibilidad'!D6 -> Las interfaces cumplen las pautas WCAG 2.1 nivel AA. | E17: ='RNF Accesibilidad'!E6 -> Alta | F17: ='RNF Accesibilidad'!F6 -> 0
B18: RNF-ACC-02 | C18: ='RNF Accesibilidad'!C7 -> Lectores de pantalla | D18: ='RNF Accesibilidad'!D7 -> Todos los elementos interactivos tienen etiqueta, rol y estado accesibles (accessibilityLabel/Role/State en React Native; HTML semántico y ARIA en Laravel) y funcionan con TalkBack, VoiceOver y NVDA. | E18: ='RNF Accesibilidad'!E7 -> Alta | F18: ='RNF Accesibilidad'!F7 -> 0
B19: RNF-ACC-03 | C19: ='RNF Accesibilidad'!C8 -> Contraste | D19: ='RNF Accesibilidad'!D8 -> Contraste mínimo de 4.5:1 para texto normal y 3:1 para texto grande y componentes de interfaz. | E19: ='RNF Accesibilidad'!E8 -> Alta | F19: ='RNF Accesibilidad'!F8 -> 0
B20: RNF-ACC-04 | C20: ='RNF Accesibilidad'!C9 -> Texto escalable | D20: ='RNF Accesibilidad'!D9 -> La interfaz respeta el tamaño de fuente del sistema y admite hasta 200 % de ampliación sin pérdida de contenido ni funcionalidad. | E20: ='RNF Accesibilidad'!E9 -> Alta | F20: ='RNF Accesibilidad'!F9 -> 0
B21: RNF-ACC-05 | C21: ='RNF Accesibilidad'!C10 -> Áreas táctiles | D21: ='RNF Accesibilidad'!D10 -> Los componentes táctiles tienen un área mínima de 48 × 48 dp en Android y 44 × 44 pt en iOS. | E21: ='RNF Accesibilidad'!E10 -> Alta | F21: ='RNF Accesibilidad'!F10 -> 0
B22: RNF-ACC-06 | C22: ='RNF Accesibilidad'!C11 -> Información no dependiente del color | D22: ='RNF Accesibilidad'!D11 -> Estados, errores y porcentajes se comunican con texto o ícono además del color. | E22: ='RNF Accesibilidad'!E11 -> Alta | F22: ='RNF Accesibilidad'!F11 -> 0
B23: RNF-ACC-07 | C23: ='RNF Accesibilidad'!C12 -> Navegación por teclado | D23: ='RNF Accesibilidad'!D12 -> El panel web puede operarse completamente con teclado y la app admite teclado externo y control por interruptores (Switch Access / Control por botón), con foco visible y orden lógico. | E23: ='RNF Accesibilidad'!E12 -> Alta | F23: ='RNF Accesibilidad'!F12 -> 0
B24: RNF-ACC-08 | C24: ='RNF Accesibilidad'!C13 -> Lenguaje claro | D24: ='RNF Accesibilidad'!D13 -> Textos en lenguaje claro y sin tecnicismos; los errores de formulario indican qué campo falla y cómo corregirlo. | E24: ='RNF Accesibilidad'!E13 -> Media | F24: ='RNF Accesibilidad'!F13 -> 0
B25: RNF-ACC-09 | C25: ='RNF Accesibilidad'!C14 -> Movimiento reducido | D25: ='RNF Accesibilidad'!D14 -> Se respeta la preferencia de «reducir movimiento» del sistema y no hay contenido parpadeante. | E25: ='RNF Accesibilidad'!E14 -> Baja | F25: ='RNF Accesibilidad'!F14 -> 0
B26: RNF-MOV-01 | C26: ='RNF Operativas Móvil'!C6 -> Desempeño | D26: ='RNF Operativas Móvil'!D6 -> Tiempo de respuesta de las pantallas ≤ 2 s en el percentil 95 sobre red 4G. | E26: ='RNF Operativas Móvil'!E6 -> Alta | F26: ='RNF Operativas Móvil'!F6 -> 0
B27: RNF-MOV-02 | C27: ='RNF Operativas Móvil'!C7 -> Compatibilidad | D27: ='RNF Operativas Móvil'!D7 -> Ejecutable en Android 8+ e iOS 15+ con un solo código base (React Native + Expo). | E27: ='RNF Operativas Móvil'!E7 -> Alta | F27: ='RNF Operativas Móvil'!F7 -> 0
B28: RNF-MOV-03 | C28: ='RNF Operativas Móvil'!C8 -> Retroalimentación | D28: ='RNF Operativas Móvil'!D8 -> Toda acción que tarde más de 300 ms muestra un indicador de carga anunciado al lector de pantalla. | E28: ='RNF Operativas Móvil'!E8 -> Media | F28: ='RNF Operativas Móvil'!F8 -> 0
B29: RNF-MOV-04 | C29: ='RNF Operativas Móvil'!C9 -> Tolerancia a fallas de red | D29: ='RNF Operativas Móvil'!D9 -> La app conserva en caché el último listado de vacantes y postulaciones y avisa cuando no hay conexión; los formularios no pierden lo capturado. | E29: ='RNF Operativas Móvil'!E9 -> Media | F29: ='RNF Operativas Móvil'!F9 -> 0
B30: RNF-MOV-05 | C30: ='RNF Operativas Móvil'!C10 -> Orientación | D30: ='RNF Operativas Móvil'!D10 -> Las pantallas funcionan en orientación vertical y horizontal. | E30: ='RNF Operativas Móvil'!E10 -> Baja | F30: ='RNF Operativas Móvil'!F10 -> 0
B31: RNF-NOT-01 | C31: ='RNF Notificaciones'!C6 -> Tiempo de entrega | D31: ='RNF Notificaciones'!D6 -> Las notificaciones push se envían en ≤ 1 min y los correos en ≤ 5 min tras el evento. | E31: ='RNF Notificaciones'!E6 -> Media | F31: ='RNF Notificaciones'!F6 -> 0
B32: RNF-NOT-02 | C32: ='RNF Notificaciones'!C7 -> Confiabilidad | D32: ='RNF Notificaciones'!D7 -> Los envíos fallidos se reintentan hasta 3 veces; el fallo de un canal no bloquea la operación que lo generó. | E32: ='RNF Notificaciones'!E7 -> Alta | F32: ='RNF Notificaciones'!F7 -> 0
B33: RNF-NOT-03 | C33: ='RNF Notificaciones'!C8 -> Correos accesibles | D33: ='RNF Notificaciones'!D8 -> Los correos incluyen versión en texto plano, estructura semántica y enlaces descriptivos. | E33: ='RNF Notificaciones'!E8 -> Media | F33: ='RNF Notificaciones'!F8 -> 0
B34: RNF-NOT-04 | C34: ='RNF Notificaciones'!C9 -> Contenido mínimo | D34: ='RNF Notificaciones'!D9 -> Las notificaciones push no incluyen datos personales sensibles; el detalle se consulta dentro de la app. | E34: ='RNF Notificaciones'!E9 -> Alta | F34: ='RNF Notificaciones'!F9 -> 0
B35: Los RNF provienen de las hojas generales «RNF …» y se actualizan automáticamente; edita el texto y el avance en su hoja general.
B38: Elaborado por: | C38: Alan David Santiago de Vicente, Ricardo Méndez Rodríguez, Eduardo Daniel Licea González
B39: Responsable: | C39: Equipo IncluTec — Ingeniería en Sistemas Computacionales
B40: Dependencias: | C40: API REST (FastAPI), Base de datos PostgreSQL; Expo Push Notifications
B41: Entrega: | C41: 28 de octubre de 2026
B44: Acotaciones de Avance
B45: 100% | C45: Completada
B46: 50% | C46: En proceso
B47: 0% | C47: No Iniciada
B50: Autorizado:

Sheet CAN-01 Vacantes
B1: ← Índice
B3: Requerimientos Funcionales
B4: Interfaz : CAN-01 — Vacantes (inicio del candidato)
B5: ID | C5: Requerimiento | D5: Descripción | E5: Prioridad | F5: Avance
B6: RF-01 | C6: Vacantes recomendadas | D6: Mostrar por defecto las vacantes publicadas ordenadas por compatibilidad descendente vía GET /vacantes/recomendadas (paginado de 20 con desplazamiento infinito). | E6: Alta | F6: 0
B7: RF-02 | C7: Búsqueda por texto | D7: Buscar por puesto, empresa o palabra clave (mínimo 3 caracteres) vía GET /vacantes?q=. | E7: Alta | F7: 0
B8: RF-03 | C8: Filtros | D8: Filtrar por modalidad, categoría, municipio/estado, jornada, salario mínimo, compatibilidad mínima y ajustes o condiciones de accesibilidad específicas (p. ej. «intérprete de LSM», «acceso con rampa»). | E8: Alta | F8: 0
B9: RF-04 | C9: Filtro «cubre mis necesidades» | D9: Opción para mostrar solo las vacantes que cubren todas las necesidades de ajuste registradas por el candidato. | E9: Alta | F9: 0
B10: RF-05 | C10: Tarjeta de vacante | D10: Cada tarjeta muestra puesto, empresa (con distintivo de empresa validada), modalidad, ubicación, porcentaje de compatibilidad e íconos de accesibilidad acompañados de texto. | E10: Media | F10: 0
B11: RF-06 | C11: Estado vacío y perfil incompleto | D11: Si no hay resultados, sugerir quitar filtros. Si el perfil está incompleto, mostrar un aviso con acceso a CAN-03 y CAN-04 explicando que las recomendaciones mejoran al completarlo. | E11: Media | F11: 0
B14: Requerimientos No Funcionales
B15: Interfaz : CAN-01 — Vacantes (inicio del candidato) · Accesibilidad, Pantallas móviles
B16: ID | C16: Nombre | D16: Descripción | E16: Prioridad | F16: Avance
B17: RNF-ACC-01 | C17: ='RNF Accesibilidad'!C6 -> Estándar de accesibilidad | D17: ='RNF Accesibilidad'!D6 -> Las interfaces cumplen las pautas WCAG 2.1 nivel AA. | E17: ='RNF Accesibilidad'!E6 -> Alta | F17: ='RNF Accesibilidad'!F6 -> 0
B18: RNF-ACC-02 | C18: ='RNF Accesibilidad'!C7 -> Lectores de pantalla | D18: ='RNF Accesibilidad'!D7 -> Todos los elementos interactivos tienen etiqueta, rol y estado accesibles (accessibilityLabel/Role/State en React Native; HTML semántico y ARIA en Laravel) y funcionan con TalkBack, VoiceOver y NVDA. | E18: ='RNF Accesibilidad'!E7 -> Alta | F18: ='RNF Accesibilidad'!F7 -> 0
B19: RNF-ACC-03 | C19: ='RNF Accesibilidad'!C8 -> Contraste | D19: ='RNF Accesibilidad'!D8 -> Contraste mínimo de 4.5:1 para texto normal y 3:1 para texto grande y componentes de interfaz. | E19: ='RNF Accesibilidad'!E8 -> Alta | F19: ='RNF Accesibilidad'!F8 -> 0
B20: RNF-ACC-04 | C20: ='RNF Accesibilidad'!C9 -> Texto escalable | D20: ='RNF Accesibilidad'!D9 -> La interfaz respeta el tamaño de fuente del sistema y admite hasta 200 % de ampliación sin pérdida de contenido ni funcionalidad. | E20: ='RNF Accesibilidad'!E9 -> Alta | F20: ='RNF Accesibilidad'!F9 -> 0
B21: RNF-ACC-05 | C21: ='RNF Accesibilidad'!C10 -> Áreas táctiles | D21: ='RNF Accesibilidad'!D10 -> Los componentes táctiles tienen un área mínima de 48 × 48 dp en Android y 44 × 44 pt en iOS. | E21: ='RNF Accesibilidad'!E10 -> Alta | F21: ='RNF Accesibilidad'!F10 -> 0
B22: RNF-ACC-06 | C22: ='RNF Accesibilidad'!C11 -> Información no dependiente del color | D22: ='RNF Accesibilidad'!D11 -> Estados, errores y porcentajes se comunican con texto o ícono además del color. | E22: ='RNF Accesibilidad'!E11 -> Alta | F22: ='RNF Accesibilidad'!F11 -> 0
B23: RNF-ACC-07 | C23: ='RNF Accesibilidad'!C12 -> Navegación por teclado | D23: ='RNF Accesibilidad'!D12 -> El panel web puede operarse completamente con teclado y la app admite teclado externo y control por interruptores (Switch Access / Control por botón), con foco visible y orden lógico. | E23: ='RNF Accesibilidad'!E12 -> Alta | F23: ='RNF Accesibilidad'!F12 -> 0
B24: RNF-ACC-08 | C24: ='RNF Accesibilidad'!C13 -> Lenguaje claro | D24: ='RNF Accesibilidad'!D13 -> Textos en lenguaje claro y sin tecnicismos; los errores de formulario indican qué campo falla y cómo corregirlo. | E24: ='RNF Accesibilidad'!E13 -> Media | F24: ='RNF Accesibilidad'!F13 -> 0
B25: RNF-ACC-09 | C25: ='RNF Accesibilidad'!C14 -> Movimiento reducido | D25: ='RNF Accesibilidad'!D14 -> Se respeta la preferencia de «reducir movimiento» del sistema y no hay contenido parpadeante. | E25: ='RNF Accesibilidad'!E14 -> Baja | F25: ='RNF Accesibilidad'!F14 -> 0
B26: RNF-MOV-01 | C26: ='RNF Operativas Móvil'!C6 -> Desempeño | D26: ='RNF Operativas Móvil'!D6 -> Tiempo de respuesta de las pantallas ≤ 2 s en el percentil 95 sobre red 4G. | E26: ='RNF Operativas Móvil'!E6 -> Alta | F26: ='RNF Operativas Móvil'!F6 -> 0
B27: RNF-MOV-02 | C27: ='RNF Operativas Móvil'!C7 -> Compatibilidad | D27: ='RNF Operativas Móvil'!D7 -> Ejecutable en Android 8+ e iOS 15+ con un solo código base (React Native + Expo). | E27: ='RNF Operativas Móvil'!E7 -> Alta | F27: ='RNF Operativas Móvil'!F7 -> 0
B28: RNF-MOV-03 | C28: ='RNF Operativas Móvil'!C8 -> Retroalimentación | D28: ='RNF Operativas Móvil'!D8 -> Toda acción que tarde más de 300 ms muestra un indicador de carga anunciado al lector de pantalla. | E28: ='RNF Operativas Móvil'!E8 -> Media | F28: ='RNF Operativas Móvil'!F8 -> 0
B29: RNF-MOV-04 | C29: ='RNF Operativas Móvil'!C9 -> Tolerancia a fallas de red | D29: ='RNF Operativas Móvil'!D9 -> La app conserva en caché el último listado de vacantes y postulaciones y avisa cuando no hay conexión; los formularios no pierden lo capturado. | E29: ='RNF Operativas Móvil'!E9 -> Media | F29: ='RNF Operativas Móvil'!F9 -> 0
B30: RNF-MOV-05 | C30: ='RNF Operativas Móvil'!C10 -> Orientación | D30: ='RNF Operativas Móvil'!D10 -> Las pantallas funcionan en orientación vertical y horizontal. | E30: ='RNF Operativas Móvil'!E10 -> Baja | F30: ='RNF Operativas Móvil'!F10 -> 0
B31: Los RNF provienen de las hojas generales «RNF …» y se actualizan automáticamente; edita el texto y el avance en su hoja general.
B34: Elaborado por: | C34: Alan David Santiago de Vicente, Ricardo Méndez Rodríguez, Eduardo Daniel Licea González
B35: Responsable: | C35: Equipo IncluTec — Ingeniería en Sistemas Computacionales
B36: Dependencias: | C36: API REST (FastAPI), Base de datos PostgreSQL; motor de compatibilidad
B37: Entrega: | C37: 28 de octubre de 2026
B40: Acotaciones de Avance
B41: 100% | C41: Completada
B42: 50% | C42: En proceso
B43: 0% | C43: No Iniciada
B46: Autorizado:

Sheet CAN-02 Detalle vacante
B1: ← Índice
B3: Requerimientos Funcionales
B4: Interfaz : CAN-02 — Detalle de vacante
B5: ID | C5: Requerimiento | D5: Descripción | E5: Prioridad | F5: Avance
B6: RF-01 | C6: Información de la vacante | D6: Obtener GET /vacantes/{id} y mostrar puesto, empresa, descripción, categoría, jornada, tipo de contrato, salario (si la empresa lo publica), ubicación y fecha de publicación. | E6: Alta | F6: 0
B7: RF-02 | C7: Requisitos | D7: Mostrar habilidades obligatorias y deseables, formación mínima y años de experiencia solicitados. | E7: Alta | F7: 0
B8: RF-03 | C8: Accesibilidad y ajustes | D8: Mostrar la modalidad, las condiciones de accesibilidad con las que ya cuenta el lugar de trabajo y los ajustes razonables que la empresa puede ofrecer bajo solicitud. | E8: Alta | F8: 0
B9: RF-04 | C9: Desglose de compatibilidad | D9: Obtener GET /vacantes/{id}/compatibilidad y mostrar el porcentaje con su detalle: habilidades que cumple y que le faltan, necesidades de ajuste cubiertas y no cubiertas, modalidad y formación. | E9: Alta | F9: 0
B10: RF-05 | C10: Postularse | D10: Enviar POST /postulaciones con {vacante_id, mensaje (opcional, ≤ 500 caracteres), compartir_ajustes}; confirmar antes de enviar. Si el API responde 409, indicar que ya existe una postulación a esa vacante. | E10: Alta | F10: 0
B11: RF-06 | C11: Requisito de perfil mínimo | D11: Deshabilitar «Postularme» y explicar el motivo si el perfil no tiene nombre, municipio, al menos una habilidad y al menos una formación académica. | E11: Media | F11: 0
B12: RF-07 | C12: Consentimiento de ajustes | D12: Antes de postularse, preguntar si desea compartir sus necesidades de ajuste con la empresa; por defecto se toma su preferencia de CAN-03. | E12: Alta | F12: 0
B13: RF-08 | C13: Reportar vacante | D13: Permitir reportar la vacante (POST /reportes) eligiendo un motivo del catálogo y una descripción opcional (≤ 500 caracteres). | E13: Media | F13: 0
B14: RF-09 | C14: Ver empresa | D14: Enlazar a la ficha de la empresa en CAN-07. | E14: Baja | F14: 0
B17: Requerimientos No Funcionales
B18: Interfaz : CAN-02 — Detalle de vacante · Accesibilidad, Privacidad y datos sensibles, Pantallas móviles
B19: ID | C19: Nombre | D19: Descripción | E19: Prioridad | F19: Avance
B20: RNF-ACC-01 | C20: ='RNF Accesibilidad'!C6 -> Estándar de accesibilidad | D20: ='RNF Accesibilidad'!D6 -> Las interfaces cumplen las pautas WCAG 2.1 nivel AA. | E20: ='RNF Accesibilidad'!E6 -> Alta | F20: ='RNF Accesibilidad'!F6 -> 0
B21: RNF-ACC-02 | C21: ='RNF Accesibilidad'!C7 -> Lectores de pantalla | D21: ='RNF Accesibilidad'!D7 -> Todos los elementos interactivos tienen etiqueta, rol y estado accesibles (accessibilityLabel/Role/State en React Native; HTML semántico y ARIA en Laravel) y funcionan con TalkBack, VoiceOver y NVDA. | E21: ='RNF Accesibilidad'!E7 -> Alta | F21: ='RNF Accesibilidad'!F7 -> 0
B22: RNF-ACC-03 | C22: ='RNF Accesibilidad'!C8 -> Contraste | D22: ='RNF Accesibilidad'!D8 -> Contraste mínimo de 4.5:1 para texto normal y 3:1 para texto grande y componentes de interfaz. | E22: ='RNF Accesibilidad'!E8 -> Alta | F22: ='RNF Accesibilidad'!F8 -> 0
B23: RNF-ACC-04 | C23: ='RNF Accesibilidad'!C9 -> Texto escalable | D23: ='RNF Accesibilidad'!D9 -> La interfaz respeta el tamaño de fuente del sistema y admite hasta 200 % de ampliación sin pérdida de contenido ni funcionalidad. | E23: ='RNF Accesibilidad'!E9 -> Alta | F23: ='RNF Accesibilidad'!F9 -> 0
B24: RNF-ACC-05 | C24: ='RNF Accesibilidad'!C10 -> Áreas táctiles | D24: ='RNF Accesibilidad'!D10 -> Los componentes táctiles tienen un área mínima de 48 × 48 dp en Android y 44 × 44 pt en iOS. | E24: ='RNF Accesibilidad'!E10 -> Alta | F24: ='RNF Accesibilidad'!F10 -> 0
B25: RNF-ACC-06 | C25: ='RNF Accesibilidad'!C11 -> Información no dependiente del color | D25: ='RNF Accesibilidad'!D11 -> Estados, errores y porcentajes se comunican con texto o ícono además del color. | E25: ='RNF Accesibilidad'!E11 -> Alta | F25: ='RNF Accesibilidad'!F11 -> 0
B26: RNF-ACC-07 | C26: ='RNF Accesibilidad'!C12 -> Navegación por teclado | D26: ='RNF Accesibilidad'!D12 -> El panel web puede operarse completamente con teclado y la app admite teclado externo y control por interruptores (Switch Access / Control por botón), con foco visible y orden lógico. | E26: ='RNF Accesibilidad'!E12 -> Alta | F26: ='RNF Accesibilidad'!F12 -> 0
B27: RNF-ACC-08 | C27: ='RNF Accesibilidad'!C13 -> Lenguaje claro | D27: ='RNF Accesibilidad'!D13 -> Textos en lenguaje claro y sin tecnicismos; los errores de formulario indican qué campo falla y cómo corregirlo. | E27: ='RNF Accesibilidad'!E13 -> Media | F27: ='RNF Accesibilidad'!F13 -> 0
B28: RNF-ACC-09 | C28: ='RNF Accesibilidad'!C14 -> Movimiento reducido | D28: ='RNF Accesibilidad'!D14 -> Se respeta la preferencia de «reducir movimiento» del sistema y no hay contenido parpadeante. | E28: ='RNF Accesibilidad'!E14 -> Baja | F28: ='RNF Accesibilidad'!F14 -> 0
B29: RNF-PRV-01 | C29: ='RNF Privacidad'!C6 -> Cumplimiento legal | D29: ='RNF Privacidad'!D6 -> El tratamiento de datos personales cumple la Ley Federal de Protección de Datos Personales en Posesión de los Particulares, con aviso de privacidad y consentimiento expreso para datos sensibles. | E29: ='RNF Privacidad'!E6 -> Alta | F29: ='RNF Privacidad'!F6 -> 0
B30: RNF-PRV-02 | C30: ='RNF Privacidad'!C7 -> Minimización de datos | D30: ='RNF Privacidad'!D7 -> El sistema registra necesidades de ajuste y no diagnósticos, tipos de discapacidad ni documentos médicos. | E30: ='RNF Privacidad'!E7 -> Alta | F30: ='RNF Privacidad'!F7 -> 0
B31: RNF-PRV-03 | C31: ='RNF Privacidad'!C8 -> Control del candidato | D31: ='RNF Privacidad'!D8 -> Las necesidades de ajuste solo son visibles para el candidato y para las empresas a cuyas vacantes se postuló con consentimiento; el administrador solo ve datos agregados. | E31: ='RNF Privacidad'!E8 -> Alta | F31: ='RNF Privacidad'!F8 -> 0
B32: RNF-PRV-04 | C32: ='RNF Privacidad'!C9 -> Derechos ARCO | D32: ='RNF Privacidad'!D9 -> El candidato puede consultar, corregir y eliminar sus datos; la eliminación anonimiza sus postulaciones históricas en un plazo máximo de 30 días. | E32: ='RNF Privacidad'!E9 -> Alta | F32: ='RNF Privacidad'!F9 -> 0
B33: RNF-PRV-05 | C33: ='RNF Privacidad'!C10 -> Registros sin datos sensibles | D33: ='RNF Privacidad'!D10 -> Los logs del servidor y los mensajes push no incluyen necesidades de ajuste ni datos de contacto. | E33: ='RNF Privacidad'!E10 -> Alta | F33: ='RNF Privacidad'!F10 -> 0
B34: RNF-MOV-01 | C34: ='RNF Operativas Móvil'!C6 -> Desempeño | D34: ='RNF Operativas Móvil'!D6 -> Tiempo de respuesta de las pantallas ≤ 2 s en el percentil 95 sobre red 4G. | E34: ='RNF Operativas Móvil'!E6 -> Alta | F34: ='RNF Operativas Móvil'!F6 -> 0
B35: RNF-MOV-02 | C35: ='RNF Operativas Móvil'!C7 -> Compatibilidad | D35: ='RNF Operativas Móvil'!D7 -> Ejecutable en Android 8+ e iOS 15+ con un solo código base (React Native + Expo). | E35: ='RNF Operativas Móvil'!E7 -> Alta | F35: ='RNF Operativas Móvil'!F7 -> 0
B36: RNF-MOV-03 | C36: ='RNF Operativas Móvil'!C8 -> Retroalimentación | D36: ='RNF Operativas Móvil'!D8 -> Toda acción que tarde más de 300 ms muestra un indicador de carga anunciado al lector de pantalla. | E36: ='RNF Operativas Móvil'!E8 -> Media | F36: ='RNF Operativas Móvil'!F8 -> 0
B37: RNF-MOV-04 | C37: ='RNF Operativas Móvil'!C9 -> Tolerancia a fallas de red | D37: ='RNF Operativas Móvil'!D9 -> La app conserva en caché el último listado de vacantes y postulaciones y avisa cuando no hay conexión; los formularios no pierden lo capturado. | E37: ='RNF Operativas Móvil'!E9 -> Media | F37: ='RNF Operativas Móvil'!F9 -> 0
B38: RNF-MOV-05 | C38: ='RNF Operativas Móvil'!C10 -> Orientación | D38: ='RNF Operativas Móvil'!D10 -> Las pantallas funcionan en orientación vertical y horizontal. | E38: ='RNF Operativas Móvil'!E10 -> Baja | F38: ='RNF Operativas Móvil'!F10 -> 0
B39: Los RNF provienen de las hojas generales «RNF …» y se actualizan automáticamente; edita el texto y el avance en su hoja general.
B42: Elaborado por: | C42: Alan David Santiago de Vicente, Ricardo Méndez Rodríguez, Eduardo Daniel Licea González
B43: Responsable: | C43: Equipo IncluTec — Ingeniería en Sistemas Computacionales
B44: Dependencias: | C44: API REST (FastAPI), Base de datos PostgreSQL; motor de compatibilidad; CAN-03/CAN-04
B45: Entrega: | C45: 28 de octubre de 2026
B48: Acotaciones de Avance
B49: 100% | C49: Completada
B50: 50% | C50: En proceso
B51: 0% | C51: No Iniciada
B54: Autorizado:

Sheet CAN-03 Mi perfil
B1: ← Índice
B3: Requerimientos Funcionales
B4: Interfaz : CAN-03 — Mi perfil
B5: ID | C5: Requerimiento | D5: Descripción | E5: Prioridad | F5: Avance
B6: RF-01 | C6: Datos personales | D6: Consultar y editar nombre, apellidos, teléfono, municipio/estado, foto (opcional, JPG/PNG ≤ 2 MB) y resumen profesional (≤ 500 caracteres) vía GET/PUT /candidatos/me. | E6: Alta | F6: 0
B7: RF-02 | C7: Preferencias laborales | D7: Registrar modalidades de interés (presencial, remoto, híbrido), categorías de interés, jornada deseada y disponibilidad para reubicarse. | E7: Alta | F7: 0
B8: RF-03 | C8: Necesidades de ajuste | D8: Seleccionar del catálogo, agrupado por categoría (movilidad, visual, auditiva, comunicación, cognitiva/psicosocial, general), los ajustes que necesita, más una nota libre opcional (≤ 300 caracteres), vía PUT /candidatos/me/necesidades. No se solicita ni almacena diagnóstico ni tipo de discapacidad. | E8: Alta | F8: 0
B9: RF-04 | C9: Visibilidad de ajustes | D9: Interruptor «Compartir mis necesidades de ajuste con las empresas a las que me postule» (por defecto: preguntar en cada postulación). | E9: Alta | F9: 0
B10: RF-05 | C10: Completitud del perfil | D10: Mostrar el porcentaje de completitud del perfil y la lista de secciones pendientes. | E10: Media | F10: 0
B11: RF-06 | C11: Seguridad de la cuenta | D11: Permitir cambiar la contraseña (PUT /auth/password) y cerrar sesión (POST /auth/logout y borrado del token local). | E11: Alta | F11: 0
B12: RF-07 | C12: Eliminar cuenta | D12: Permitir la cancelación de la cuenta y de los datos personales (derecho ARCO) vía DELETE /candidatos/me, con doble confirmación. | E12: Media | F12: 0
B15: Requerimientos No Funcionales
B16: Interfaz : CAN-03 — Mi perfil · Accesibilidad, Privacidad y datos sensibles, Pantallas móviles
B17: ID | C17: Nombre | D17: Descripción | E17: Prioridad | F17: Avance
B18: RNF-ACC-01 | C18: ='RNF Accesibilidad'!C6 -> Estándar de accesibilidad | D18: ='RNF Accesibilidad'!D6 -> Las interfaces cumplen las pautas WCAG 2.1 nivel AA. | E18: ='RNF Accesibilidad'!E6 -> Alta | F18: ='RNF Accesibilidad'!F6 -> 0
B19: RNF-ACC-02 | C19: ='RNF Accesibilidad'!C7 -> Lectores de pantalla | D19: ='RNF Accesibilidad'!D7 -> Todos los elementos interactivos tienen etiqueta, rol y estado accesibles (accessibilityLabel/Role/State en React Native; HTML semántico y ARIA en Laravel) y funcionan con TalkBack, VoiceOver y NVDA. | E19: ='RNF Accesibilidad'!E7 -> Alta | F19: ='RNF Accesibilidad'!F7 -> 0
B20: RNF-ACC-03 | C20: ='RNF Accesibilidad'!C8 -> Contraste | D20: ='RNF Accesibilidad'!D8 -> Contraste mínimo de 4.5:1 para texto normal y 3:1 para texto grande y componentes de interfaz. | E20: ='RNF Accesibilidad'!E8 -> Alta | F20: ='RNF Accesibilidad'!F8 -> 0
B21: RNF-ACC-04 | C21: ='RNF Accesibilidad'!C9 -> Texto escalable | D21: ='RNF Accesibilidad'!D9 -> La interfaz respeta el tamaño de fuente del sistema y admite hasta 200 % de ampliación sin pérdida de contenido ni funcionalidad. | E21: ='RNF Accesibilidad'!E9 -> Alta | F21: ='RNF Accesibilidad'!F9 -> 0
B22: RNF-ACC-05 | C22: ='RNF Accesibilidad'!C10 -> Áreas táctiles | D22: ='RNF Accesibilidad'!D10 -> Los componentes táctiles tienen un área mínima de 48 × 48 dp en Android y 44 × 44 pt en iOS. | E22: ='RNF Accesibilidad'!E10 -> Alta | F22: ='RNF Accesibilidad'!F10 -> 0
B23: RNF-ACC-06 | C23: ='RNF Accesibilidad'!C11 -> Información no dependiente del color | D23: ='RNF Accesibilidad'!D11 -> Estados, errores y porcentajes se comunican con texto o ícono además del color. | E23: ='RNF Accesibilidad'!E11 -> Alta | F23: ='RNF Accesibilidad'!F11 -> 0
B24: RNF-ACC-07 | C24: ='RNF Accesibilidad'!C12 -> Navegación por teclado | D24: ='RNF Accesibilidad'!D12 -> El panel web puede operarse completamente con teclado y la app admite teclado externo y control por interruptores (Switch Access / Control por botón), con foco visible y orden lógico. | E24: ='RNF Accesibilidad'!E12 -> Alta | F24: ='RNF Accesibilidad'!F12 -> 0
B25: RNF-ACC-08 | C25: ='RNF Accesibilidad'!C13 -> Lenguaje claro | D25: ='RNF Accesibilidad'!D13 -> Textos en lenguaje claro y sin tecnicismos; los errores de formulario indican qué campo falla y cómo corregirlo. | E25: ='RNF Accesibilidad'!E13 -> Media | F25: ='RNF Accesibilidad'!F13 -> 0
B26: RNF-ACC-09 | C26: ='RNF Accesibilidad'!C14 -> Movimiento reducido | D26: ='RNF Accesibilidad'!D14 -> Se respeta la preferencia de «reducir movimiento» del sistema y no hay contenido parpadeante. | E26: ='RNF Accesibilidad'!E14 -> Baja | F26: ='RNF Accesibilidad'!F14 -> 0
B27: RNF-PRV-01 | C27: ='RNF Privacidad'!C6 -> Cumplimiento legal | D27: ='RNF Privacidad'!D6 -> El tratamiento de datos personales cumple la Ley Federal de Protección de Datos Personales en Posesión de los Particulares, con aviso de privacidad y consentimiento expreso para datos sensibles. | E27: ='RNF Privacidad'!E6 -> Alta | F27: ='RNF Privacidad'!F6 -> 0
B28: RNF-PRV-02 | C28: ='RNF Privacidad'!C7 -> Minimización de datos | D28: ='RNF Privacidad'!D7 -> El sistema registra necesidades de ajuste y no diagnósticos, tipos de discapacidad ni documentos médicos. | E28: ='RNF Privacidad'!E7 -> Alta | F28: ='RNF Privacidad'!F7 -> 0
B29: RNF-PRV-03 | C29: ='RNF Privacidad'!C8 -> Control del candidato | D29: ='RNF Privacidad'!D8 -> Las necesidades de ajuste solo son visibles para el candidato y para las empresas a cuyas vacantes se postuló con consentimiento; el administrador solo ve datos agregados. | E29: ='RNF Privacidad'!E8 -> Alta | F29: ='RNF Privacidad'!F8 -> 0
B30: RNF-PRV-04 | C30: ='RNF Privacidad'!C9 -> Derechos ARCO | D30: ='RNF Privacidad'!D9 -> El candidato puede consultar, corregir y eliminar sus datos; la eliminación anonimiza sus postulaciones históricas en un plazo máximo de 30 días. | E30: ='RNF Privacidad'!E9 -> Alta | F30: ='RNF Privacidad'!F9 -> 0
B31: RNF-PRV-05 | C31: ='RNF Privacidad'!C10 -> Registros sin datos sensibles | D31: ='RNF Privacidad'!D10 -> Los logs del servidor y los mensajes push no incluyen necesidades de ajuste ni datos de contacto. | E31: ='RNF Privacidad'!E10 -> Alta | F31: ='RNF Privacidad'!F10 -> 0
B32: RNF-MOV-01 | C32: ='RNF Operativas Móvil'!C6 -> Desempeño | D32: ='RNF Operativas Móvil'!D6 -> Tiempo de respuesta de las pantallas ≤ 2 s en el percentil 95 sobre red 4G. | E32: ='RNF Operativas Móvil'!E6 -> Alta | F32: ='RNF Operativas Móvil'!F6 -> 0
B33: RNF-MOV-02 | C33: ='RNF Operativas Móvil'!C7 -> Compatibilidad | D33: ='RNF Operativas Móvil'!D7 -> Ejecutable en Android 8+ e iOS 15+ con un solo código base (React Native + Expo). | E33: ='RNF Operativas Móvil'!E7 -> Alta | F33: ='RNF Operativas Móvil'!F7 -> 0
B34: RNF-MOV-03 | C34: ='RNF Operativas Móvil'!C8 -> Retroalimentación | D34: ='RNF Operativas Móvil'!D8 -> Toda acción que tarde más de 300 ms muestra un indicador de carga anunciado al lector de pantalla. | E34: ='RNF Operativas Móvil'!E8 -> Media | F34: ='RNF Operativas Móvil'!F8 -> 0
B35: RNF-MOV-04 | C35: ='RNF Operativas Móvil'!C9 -> Tolerancia a fallas de red | D35: ='RNF Operativas Móvil'!D9 -> La app conserva en caché el último listado de vacantes y postulaciones y avisa cuando no hay conexión; los formularios no pierden lo capturado. | E35: ='RNF Operativas Móvil'!E9 -> Media | F35: ='RNF Operativas Móvil'!F9 -> 0
B36: RNF-MOV-05 | C36: ='RNF Operativas Móvil'!C10 -> Orientación | D36: ='RNF Operativas Móvil'!D10 -> Las pantallas funcionan en orientación vertical y horizontal. | E36: ='RNF Operativas Móvil'!E10 -> Baja | F36: ='RNF Operativas Móvil'!F10 -> 0
B37: Los RNF provienen de las hojas generales «RNF …» y se actualizan automáticamente; edita el texto y el avance en su hoja general.
B40: Elaborado por: | C40: Alan David Santiago de Vicente, Ricardo Méndez Rodríguez, Eduardo Daniel Licea González
B41: Responsable: | C41: Equipo IncluTec — Ingeniería en Sistemas Computacionales
B42: Dependencias: | C42: API REST (FastAPI), Base de datos PostgreSQL; catálogo de ajustes y condiciones de accesibilidad
B43: Entrega: | C43: 28 de octubre de 2026
B46: Acotaciones de Avance
B47: 100% | C47: Completada
B48: 50% | C48: En proceso
B49: 0% | C49: No Iniciada
B52: Autorizado:

Sheet CAN-04 Mi CV
B1: ← Índice
B3: Requerimientos Funcionales
B4: Interfaz : CAN-04 — Mi CV
B5: ID | C5: Requerimiento | D5: Descripción | E5: Prioridad | F5: Avance
B6: RF-01 | C6: Organización en pestañas | D6: Presentar tres pestañas: Experiencia, Formación y Habilidades, navegables con lector de pantalla y teclado externo. | E6: Media | F6: 0
B7: RF-02 | C7: Experiencia laboral | D7: Listar, crear, editar y eliminar experiencias (puesto, empresa, fecha de inicio, fecha de fin o «actual», descripción ≤ 500 caracteres) vía /candidatos/me/experiencias; validar que la fecha de fin sea posterior a la de inicio. | E7: Alta | F7: 0
B8: RF-03 | C8: Formación académica | D8: Listar, crear, editar y eliminar formaciones (nivel educativo del catálogo, institución, carrera, estado: concluida / en curso / trunca, fechas) vía /candidatos/me/formaciones. | E8: Alta | F8: 0
B9: RF-04 | C9: Habilidades | D9: Agregar habilidades con autocompletado contra GET /catalogos/habilidades?q=, con nivel (básico, intermedio, avanzado); máximo 30 y sin duplicados, vía /candidatos/me/habilidades. | E9: Alta | F9: 0
B10: RF-05 | C10: Recalcular compatibilidad | D10: Al guardar cambios en el CV, el API recalcula la compatibilidad del candidato con las vacantes publicadas. | E10: Media | F10: 0
B11: RF-06 | C11: Vista previa | D11: Mostrar el CV tal como lo verá una empresa, respetando la configuración de visibilidad de ajustes. | E11: Baja | F11: 0
B14: Requerimientos No Funcionales
B15: Interfaz : CAN-04 — Mi CV · Accesibilidad, Privacidad y datos sensibles, Pantallas móviles
B16: ID | C16: Nombre | D16: Descripción | E16: Prioridad | F16: Avance
B17: RNF-ACC-01 | C17: ='RNF Accesibilidad'!C6 -> Estándar de accesibilidad | D17: ='RNF Accesibilidad'!D6 -> Las interfaces cumplen las pautas WCAG 2.1 nivel AA. | E17: ='RNF Accesibilidad'!E6 -> Alta | F17: ='RNF Accesibilidad'!F6 -> 0
B18: RNF-ACC-02 | C18: ='RNF Accesibilidad'!C7 -> Lectores de pantalla | D18: ='RNF Accesibilidad'!D7 -> Todos los elementos interactivos tienen etiqueta, rol y estado accesibles (accessibilityLabel/Role/State en React Native; HTML semántico y ARIA en Laravel) y funcionan con TalkBack, VoiceOver y NVDA. | E18: ='RNF Accesibilidad'!E7 -> Alta | F18: ='RNF Accesibilidad'!F7 -> 0
B19: RNF-ACC-03 | C19: ='RNF Accesibilidad'!C8 -> Contraste | D19: ='RNF Accesibilidad'!D8 -> Contraste mínimo de 4.5:1 para texto normal y 3:1 para texto grande y componentes de interfaz. | E19: ='RNF Accesibilidad'!E8 -> Alta | F19: ='RNF Accesibilidad'!F8 -> 0
B20: RNF-ACC-04 | C20: ='RNF Accesibilidad'!C9 -> Texto escalable | D20: ='RNF Accesibilidad'!D9 -> La interfaz respeta el tamaño de fuente del sistema y admite hasta 200 % de ampliación sin pérdida de contenido ni funcionalidad. | E20: ='RNF Accesibilidad'!E9 -> Alta | F20: ='RNF Accesibilidad'!F9 -> 0
B21: RNF-ACC-05 | C21: ='RNF Accesibilidad'!C10 -> Áreas táctiles | D21: ='RNF Accesibilidad'!D10 -> Los componentes táctiles tienen un área mínima de 48 × 48 dp en Android y 44 × 44 pt en iOS. | E21: ='RNF Accesibilidad'!E10 -> Alta | F21: ='RNF Accesibilidad'!F10 -> 0
B22: RNF-ACC-06 | C22: ='RNF Accesibilidad'!C11 -> Información no dependiente del color | D22: ='RNF Accesibilidad'!D11 -> Estados, errores y porcentajes se comunican con texto o ícono además del color. | E22: ='RNF Accesibilidad'!E11 -> Alta | F22: ='RNF Accesibilidad'!F11 -> 0
B23: RNF-ACC-07 | C23: ='RNF Accesibilidad'!C12 -> Navegación por teclado | D23: ='RNF Accesibilidad'!D12 -> El panel web puede operarse completamente con teclado y la app admite teclado externo y control por interruptores (Switch Access / Control por botón), con foco visible y orden lógico. | E23: ='RNF Accesibilidad'!E12 -> Alta | F23: ='RNF Accesibilidad'!F12 -> 0
B24: RNF-ACC-08 | C24: ='RNF Accesibilidad'!C13 -> Lenguaje claro | D24: ='RNF Accesibilidad'!D13 -> Textos en lenguaje claro y sin tecnicismos; los errores de formulario indican qué campo falla y cómo corregirlo. | E24: ='RNF Accesibilidad'!E13 -> Media | F24: ='RNF Accesibilidad'!F13 -> 0
B25: RNF-ACC-09 | C25: ='RNF Accesibilidad'!C14 -> Movimiento reducido | D25: ='RNF Accesibilidad'!D14 -> Se respeta la preferencia de «reducir movimiento» del sistema y no hay contenido parpadeante. | E25: ='RNF Accesibilidad'!E14 -> Baja | F25: ='RNF Accesibilidad'!F14 -> 0
B26: RNF-PRV-01 | C26: ='RNF Privacidad'!C6 -> Cumplimiento legal | D26: ='RNF Privacidad'!D6 -> El tratamiento de datos personales cumple la Ley Federal de Protección de Datos Personales en Posesión de los Particulares, con aviso de privacidad y consentimiento expreso para datos sensibles. | E26: ='RNF Privacidad'!E6 -> Alta | F26: ='RNF Privacidad'!F6 -> 0
B27: RNF-PRV-02 | C27: ='RNF Privacidad'!C7 -> Minimización de datos | D27: ='RNF Privacidad'!D7 -> El sistema registra necesidades de ajuste y no diagnósticos, tipos de discapacidad ni documentos médicos. | E27: ='RNF Privacidad'!E7 -> Alta | F27: ='RNF Privacidad'!F7 -> 0
B28: RNF-PRV-03 | C28: ='RNF Privacidad'!C8 -> Control del candidato | D28: ='RNF Privacidad'!D8 -> Las necesidades de ajuste solo son visibles para el candidato y para las empresas a cuyas vacantes se postuló con consentimiento; el administrador solo ve datos agregados. | E28: ='RNF Privacidad'!E8 -> Alta | F28: ='RNF Privacidad'!F8 -> 0
B29: RNF-PRV-04 | C29: ='RNF Privacidad'!C9 -> Derechos ARCO | D29: ='RNF Privacidad'!D9 -> El candidato puede consultar, corregir y eliminar sus datos; la eliminación anonimiza sus postulaciones históricas en un plazo máximo de 30 días. | E29: ='RNF Privacidad'!E9 -> Alta | F29: ='RNF Privacidad'!F9 -> 0
B30: RNF-PRV-05 | C30: ='RNF Privacidad'!C10 -> Registros sin datos sensibles | D30: ='RNF Privacidad'!D10 -> Los logs del servidor y los mensajes push no incluyen necesidades de ajuste ni datos de contacto. | E30: ='RNF Privacidad'!E10 -> Alta | F30: ='RNF Privacidad'!F10 -> 0
B31: RNF-MOV-01 | C31: ='RNF Operativas Móvil'!C6 -> Desempeño | D31: ='RNF Operativas Móvil'!D6 -> Tiempo de respuesta de las pantallas ≤ 2 s en el percentil 95 sobre red 4G. | E31: ='RNF Operativas Móvil'!E6 -> Alta | F31: ='RNF Operativas Móvil'!F6 -> 0
B32: RNF-MOV-02 | C32: ='RNF Operativas Móvil'!C7 -> Compatibilidad | D32: ='RNF Operativas Móvil'!D7 -> Ejecutable en Android 8+ e iOS 15+ con un solo código base (React Native + Expo). | E32: ='RNF Operativas Móvil'!E7 -> Alta | F32: ='RNF Operativas Móvil'!F7 -> 0
B33: RNF-MOV-03 | C33: ='RNF Operativas Móvil'!C8 -> Retroalimentación | D33: ='RNF Operativas Móvil'!D8 -> Toda acción que tarde más de 300 ms muestra un indicador de carga anunciado al lector de pantalla. | E33: ='RNF Operativas Móvil'!E8 -> Media | F33: ='RNF Operativas Móvil'!F8 -> 0
B34: RNF-MOV-04 | C34: ='RNF Operativas Móvil'!C9 -> Tolerancia a fallas de red | D34: ='RNF Operativas Móvil'!D9 -> La app conserva en caché el último listado de vacantes y postulaciones y avisa cuando no hay conexión; los formularios no pierden lo capturado. | E34: ='RNF Operativas Móvil'!E9 -> Media | F34: ='RNF Operativas Móvil'!F9 -> 0
B35: RNF-MOV-05 | C35: ='RNF Operativas Móvil'!C10 -> Orientación | D35: ='RNF Operativas Móvil'!D10 -> Las pantallas funcionan en orientación vertical y horizontal. | E35: ='RNF Operativas Móvil'!E10 -> Baja | F35: ='RNF Operativas Móvil'!F10 -> 0
B36: Los RNF provienen de las hojas generales «RNF …» y se actualizan automáticamente; edita el texto y el avance en su hoja general.
B39: Elaborado por: | C39: Alan David Santiago de Vicente, Ricardo Méndez Rodríguez, Eduardo Daniel Licea González
B40: Responsable: | C40: Equipo IncluTec — Ingeniería en Sistemas Computacionales
B41: Dependencias: | C41: API REST (FastAPI), Base de datos PostgreSQL; catálogos de habilidades y niveles educativos
B42: Entrega: | C42: 28 de octubre de 2026
B45: Acotaciones de Avance
B46: 100% | C46: Completada
B47: 50% | C47: En proceso
B48: 0% | C48: No Iniciada
B51: Autorizado:

Sheet CAN-05 Postulaciones
B1: ← Índice
B3: Requerimientos Funcionales
B4: Interfaz : CAN-05 — Mis postulaciones
B5: ID | C5: Requerimiento | D5: Descripción | E5: Prioridad | F5: Avance
B6: RF-01 | C6: Listado de postulaciones | D6: Listar las postulaciones del candidato vía GET /postulaciones/me con puesto, empresa, fecha y estado (postulada, en revisión, entrevista, aceptada, no seleccionada, retirada). | E6: Alta | F6: 0
B7: RF-02 | C7: Filtro por estado | D7: Filtrar por estado y separar las postulaciones activas de las finalizadas. | E7: Media | F7: 0
B8: RF-03 | C8: Estado accesible | D8: Mostrar cada estado con texto e ícono, no solo con color. | E8: Alta | F8: 0
B9: RF-04 | C9: Actualización | D9: Actualizar el listado al deslizar hacia abajo y al volver a la pantalla. | E9: Media | F9: 0
B10: RF-05 | C10: Navegación al detalle | D10: Al seleccionar una postulación, navegar a CAN-06 con su identificador. | E10: Media | F10: 0
B13: Requerimientos No Funcionales
B14: Interfaz : CAN-05 — Mis postulaciones · Accesibilidad, Pantallas móviles
B15: ID | C15: Nombre | D15: Descripción | E15: Prioridad | F15: Avance
B16: RNF-ACC-01 | C16: ='RNF Accesibilidad'!C6 -> Estándar de accesibilidad | D16: ='RNF Accesibilidad'!D6 -> Las interfaces cumplen las pautas WCAG 2.1 nivel AA. | E16: ='RNF Accesibilidad'!E6 -> Alta | F16: ='RNF Accesibilidad'!F6 -> 0
B17: RNF-ACC-02 | C17: ='RNF Accesibilidad'!C7 -> Lectores de pantalla | D17: ='RNF Accesibilidad'!D7 -> Todos los elementos interactivos tienen etiqueta, rol y estado accesibles (accessibilityLabel/Role/State en React Native; HTML semántico y ARIA en Laravel) y funcionan con TalkBack, VoiceOver y NVDA. | E17: ='RNF Accesibilidad'!E7 -> Alta | F17: ='RNF Accesibilidad'!F7 -> 0
B18: RNF-ACC-03 | C18: ='RNF Accesibilidad'!C8 -> Contraste | D18: ='RNF Accesibilidad'!D8 -> Contraste mínimo de 4.5:1 para texto normal y 3:1 para texto grande y componentes de interfaz. | E18: ='RNF Accesibilidad'!E8 -> Alta | F18: ='RNF Accesibilidad'!F8 -> 0
B19: RNF-ACC-04 | C19: ='RNF Accesibilidad'!C9 -> Texto escalable | D19: ='RNF Accesibilidad'!D9 -> La interfaz respeta el tamaño de fuente del sistema y admite hasta 200 % de ampliación sin pérdida de contenido ni funcionalidad. | E19: ='RNF Accesibilidad'!E9 -> Alta | F19: ='RNF Accesibilidad'!F9 -> 0
B20: RNF-ACC-05 | C20: ='RNF Accesibilidad'!C10 -> Áreas táctiles | D20: ='RNF Accesibilidad'!D10 -> Los componentes táctiles tienen un área mínima de 48 × 48 dp en Android y 44 × 44 pt en iOS. | E20: ='RNF Accesibilidad'!E10 -> Alta | F20: ='RNF Accesibilidad'!F10 -> 0
B21: RNF-ACC-06 | C21: ='RNF Accesibilidad'!C11 -> Información no dependiente del color | D21: ='RNF Accesibilidad'!D11 -> Estados, errores y porcentajes se comunican con texto o ícono además del color. | E21: ='RNF Accesibilidad'!E11 -> Alta | F21: ='RNF Accesibilidad'!F11 -> 0
B22: RNF-ACC-07 | C22: ='RNF Accesibilidad'!C12 -> Navegación por teclado | D22: ='RNF Accesibilidad'!D12 -> El panel web puede operarse completamente con teclado y la app admite teclado externo y control por interruptores (Switch Access / Control por botón), con foco visible y orden lógico. | E22: ='RNF Accesibilidad'!E12 -> Alta | F22: ='RNF Accesibilidad'!F12 -> 0
B23: RNF-ACC-08 | C23: ='RNF Accesibilidad'!C13 -> Lenguaje claro | D23: ='RNF Accesibilidad'!D13 -> Textos en lenguaje claro y sin tecnicismos; los errores de formulario indican qué campo falla y cómo corregirlo. | E23: ='RNF Accesibilidad'!E13 -> Media | F23: ='RNF Accesibilidad'!F13 -> 0
B24: RNF-ACC-09 | C24: ='RNF Accesibilidad'!C14 -> Movimiento reducido | D24: ='RNF Accesibilidad'!D14 -> Se respeta la preferencia de «reducir movimiento» del sistema y no hay contenido parpadeante. | E24: ='RNF Accesibilidad'!E14 -> Baja | F24: ='RNF Accesibilidad'!F14 -> 0
B25: RNF-MOV-01 | C25: ='RNF Operativas Móvil'!C6 -> Desempeño | D25: ='RNF Operativas Móvil'!D6 -> Tiempo de respuesta de las pantallas ≤ 2 s en el percentil 95 sobre red 4G. | E25: ='RNF Operativas Móvil'!E6 -> Alta | F25: ='RNF Operativas Móvil'!F6 -> 0
B26: RNF-MOV-02 | C26: ='RNF Operativas Móvil'!C7 -> Compatibilidad | D26: ='RNF Operativas Móvil'!D7 -> Ejecutable en Android 8+ e iOS 15+ con un solo código base (React Native + Expo). | E26: ='RNF Operativas Móvil'!E7 -> Alta | F26: ='RNF Operativas Móvil'!F7 -> 0
B27: RNF-MOV-03 | C27: ='RNF Operativas Móvil'!C8 -> Retroalimentación | D27: ='RNF Operativas Móvil'!D8 -> Toda acción que tarde más de 300 ms muestra un indicador de carga anunciado al lector de pantalla. | E27: ='RNF Operativas Móvil'!E8 -> Media | F27: ='RNF Operativas Móvil'!F8 -> 0
B28: RNF-MOV-04 | C28: ='RNF Operativas Móvil'!C9 -> Tolerancia a fallas de red | D28: ='RNF Operativas Móvil'!D9 -> La app conserva en caché el último listado de vacantes y postulaciones y avisa cuando no hay conexión; los formularios no pierden lo capturado. | E28: ='RNF Operativas Móvil'!E9 -> Media | F28: ='RNF Operativas Móvil'!F9 -> 0
B29: RNF-MOV-05 | C29: ='RNF Operativas Móvil'!C10 -> Orientación | D29: ='RNF Operativas Móvil'!D10 -> Las pantallas funcionan en orientación vertical y horizontal. | E29: ='RNF Operativas Móvil'!E10 -> Baja | F29: ='RNF Operativas Móvil'!F10 -> 0
B30: Los RNF provienen de las hojas generales «RNF …» y se actualizan automáticamente; edita el texto y el avance en su hoja general.
B33: Elaborado por: | C33: Alan David Santiago de Vicente, Ricardo Méndez Rodríguez, Eduardo Daniel Licea González
B34: Responsable: | C34: Equipo IncluTec — Ingeniería en Sistemas Computacionales
B35: Dependencias: | C35: API REST (FastAPI), Base de datos PostgreSQL
B36: Entrega: | C36: 28 de octubre de 2026
B39: Acotaciones de Avance
B40: 100% | C40: Completada
B41: 50% | C41: En proceso
B42: 0% | C42: No Iniciada
B45: Autorizado:

Sheet CAN-06 Detalle postulación
B1: ← Índice
B3: Requerimientos Funcionales
B4: Interfaz : CAN-06 — Detalle de postulación y entrevista
B5: ID | C5: Requerimiento | D5: Descripción | E5: Prioridad | F5: Avance
B6: RF-01 | C6: Historial de la postulación | D6: Obtener GET /postulaciones/{id} y mostrar la línea de tiempo de estados con fecha y el mensaje que el reclutador haya dejado en cada cambio. | E6: Alta | F6: 0
B7: RF-02 | C7: Horarios disponibles | D7: Si el estado es «entrevista», mostrar los horarios libres de la vacante vía GET /horarios-entrevista?vacante_id={id}&disponible=true. | E7: Alta | F7: 0
B8: RF-03 | C8: Agendar entrevista | D8: Permitir elegir un horario y confirmarlo con POST /postulaciones/{id}/entrevista {horario_id}. Si el API responde 409 (horario ya tomado), refrescar la lista y avisar. | E8: Alta | F8: 0
B9: RF-04 | C9: Datos de la entrevista | D9: Una vez agendada, mostrar fecha, hora, duración y la liga de Google Meet o Microsoft Teams, con opción para abrirla o copiarla. | E9: Alta | F9: 0
B10: RF-05 | C10: Cancelar entrevista | D10: Permitir cancelar la entrevista con al menos 24 h de anticipación (DELETE /entrevistas/{id}); el horario vuelve a quedar disponible y se notifica al reclutador. | E10: Media | F10: 0
B11: RF-06 | C11: Retirar postulación | D11: Permitir retirar la postulación mientras no esté finalizada (PATCH /postulaciones/{id}/retirar), con confirmación. | E11: Media | F11: 0
B14: Requerimientos No Funcionales
B15: Interfaz : CAN-06 — Detalle de postulación y entrevista · Accesibilidad, Pantallas móviles, Notificaciones
B16: ID | C16: Nombre | D16: Descripción | E16: Prioridad | F16: Avance
B17: RNF-ACC-01 | C17: ='RNF Accesibilidad'!C6 -> Estándar de accesibilidad | D17: ='RNF Accesibilidad'!D6 -> Las interfaces cumplen las pautas WCAG 2.1 nivel AA. | E17: ='RNF Accesibilidad'!E6 -> Alta | F17: ='RNF Accesibilidad'!F6 -> 0
B18: RNF-ACC-02 | C18: ='RNF Accesibilidad'!C7 -> Lectores de pantalla | D18: ='RNF Accesibilidad'!D7 -> Todos los elementos interactivos tienen etiqueta, rol y estado accesibles (accessibilityLabel/Role/State en React Native; HTML semántico y ARIA en Laravel) y funcionan con TalkBack, VoiceOver y NVDA. | E18: ='RNF Accesibilidad'!E7 -> Alta | F18: ='RNF Accesibilidad'!F7 -> 0
B19: RNF-ACC-03 | C19: ='RNF Accesibilidad'!C8 -> Contraste | D19: ='RNF Accesibilidad'!D8 -> Contraste mínimo de 4.5:1 para texto normal y 3:1 para texto grande y componentes de interfaz. | E19: ='RNF Accesibilidad'!E8 -> Alta | F19: ='RNF Accesibilidad'!F8 -> 0
B20: RNF-ACC-04 | C20: ='RNF Accesibilidad'!C9 -> Texto escalable | D20: ='RNF Accesibilidad'!D9 -> La interfaz respeta el tamaño de fuente del sistema y admite hasta 200 % de ampliación sin pérdida de contenido ni funcionalidad. | E20: ='RNF Accesibilidad'!E9 -> Alta | F20: ='RNF Accesibilidad'!F9 -> 0
B21: RNF-ACC-05 | C21: ='RNF Accesibilidad'!C10 -> Áreas táctiles | D21: ='RNF Accesibilidad'!D10 -> Los componentes táctiles tienen un área mínima de 48 × 48 dp en Android y 44 × 44 pt en iOS. | E21: ='RNF Accesibilidad'!E10 -> Alta | F21: ='RNF Accesibilidad'!F10 -> 0
B22: RNF-ACC-06 | C22: ='RNF Accesibilidad'!C11 -> Información no dependiente del color | D22: ='RNF Accesibilidad'!D11 -> Estados, errores y porcentajes se comunican con texto o ícono además del color. | E22: ='RNF Accesibilidad'!E11 -> Alta | F22: ='RNF Accesibilidad'!F11 -> 0
B23: RNF-ACC-07 | C23: ='RNF Accesibilidad'!C12 -> Navegación por teclado | D23: ='RNF Accesibilidad'!D12 -> El panel web puede operarse completamente con teclado y la app admite teclado externo y control por interruptores (Switch Access / Control por botón), con foco visible y orden lógico. | E23: ='RNF Accesibilidad'!E12 -> Alta | F23: ='RNF Accesibilidad'!F12 -> 0
B24: RNF-ACC-08 | C24: ='RNF Accesibilidad'!C13 -> Lenguaje claro | D24: ='RNF Accesibilidad'!D13 -> Textos en lenguaje claro y sin tecnicismos; los errores de formulario indican qué campo falla y cómo corregirlo. | E24: ='RNF Accesibilidad'!E13 -> Media | F24: ='RNF Accesibilidad'!F13 -> 0
B25: RNF-ACC-09 | C25: ='RNF Accesibilidad'!C14 -> Movimiento reducido | D25: ='RNF Accesibilidad'!D14 -> Se respeta la preferencia de «reducir movimiento» del sistema y no hay contenido parpadeante. | E25: ='RNF Accesibilidad'!E14 -> Baja | F25: ='RNF Accesibilidad'!F14 -> 0
B26: RNF-MOV-01 | C26: ='RNF Operativas Móvil'!C6 -> Desempeño | D26: ='RNF Operativas Móvil'!D6 -> Tiempo de respuesta de las pantallas ≤ 2 s en el percentil 95 sobre red 4G. | E26: ='RNF Operativas Móvil'!E6 -> Alta | F26: ='RNF Operativas Móvil'!F6 -> 0
B27: RNF-MOV-02 | C27: ='RNF Operativas Móvil'!C7 -> Compatibilidad | D27: ='RNF Operativas Móvil'!D7 -> Ejecutable en Android 8+ e iOS 15+ con un solo código base (React Native + Expo). | E27: ='RNF Operativas Móvil'!E7 -> Alta | F27: ='RNF Operativas Móvil'!F7 -> 0
B28: RNF-MOV-03 | C28: ='RNF Operativas Móvil'!C8 -> Retroalimentación | D28: ='RNF Operativas Móvil'!D8 -> Toda acción que tarde más de 300 ms muestra un indicador de carga anunciado al lector de pantalla. | E28: ='RNF Operativas Móvil'!E8 -> Media | F28: ='RNF Operativas Móvil'!F8 -> 0
B29: RNF-MOV-04 | C29: ='RNF Operativas Móvil'!C9 -> Tolerancia a fallas de red | D29: ='RNF Operativas Móvil'!D9 -> La app conserva en caché el último listado de vacantes y postulaciones y avisa cuando no hay conexión; los formularios no pierden lo capturado. | E29: ='RNF Operativas Móvil'!E9 -> Media | F29: ='RNF Operativas Móvil'!F9 -> 0
B30: RNF-MOV-05 | C30: ='RNF Operativas Móvil'!C10 -> Orientación | D30: ='RNF Operativas Móvil'!D10 -> Las pantallas funcionan en orientación vertical y horizontal. | E30: ='RNF Operativas Móvil'!E10 -> Baja | F30: ='RNF Operativas Móvil'!F10 -> 0
B31: RNF-NOT-01 | C31: ='RNF Notificaciones'!C6 -> Tiempo de entrega | D31: ='RNF Notificaciones'!D6 -> Las notificaciones push se envían en ≤ 1 min y los correos en ≤ 5 min tras el evento. | E31: ='RNF Notificaciones'!E6 -> Media | F31: ='RNF Notificaciones'!F6 -> 0
B32: RNF-NOT-02 | C32: ='RNF Notificaciones'!C7 -> Confiabilidad | D32: ='RNF Notificaciones'!D7 -> Los envíos fallidos se reintentan hasta 3 veces; el fallo de un canal no bloquea la operación que lo generó. | E32: ='RNF Notificaciones'!E7 -> Alta | F32: ='RNF Notificaciones'!F7 -> 0
B33: RNF-NOT-03 | C33: ='RNF Notificaciones'!C8 -> Correos accesibles | D33: ='RNF Notificaciones'!D8 -> Los correos incluyen versión en texto plano, estructura semántica y enlaces descriptivos. | E33: ='RNF Notificaciones'!E8 -> Media | F33: ='RNF Notificaciones'!F8 -> 0
B34: RNF-NOT-04 | C34: ='RNF Notificaciones'!C9 -> Contenido mínimo | D34: ='RNF Notificaciones'!D9 -> Las notificaciones push no incluyen datos personales sensibles; el detalle se consulta dentro de la app. | E34: ='RNF Notificaciones'!E9 -> Alta | F34: ='RNF Notificaciones'!F9 -> 0
B35: Los RNF provienen de las hojas generales «RNF …» y se actualizan automáticamente; edita el texto y el avance en su hoja general.
B38: Elaborado por: | C38: Alan David Santiago de Vicente, Ricardo Méndez Rodríguez, Eduardo Daniel Licea González
B39: Responsable: | C39: Equipo IncluTec — Ingeniería en Sistemas Computacionales
B40: Dependencias: | C40: API REST (FastAPI), Base de datos PostgreSQL; REC-06 (horarios de entrevista); servicio de correo
B41: Entrega: | C41: 28 de octubre de 2026
B44: Acotaciones de Avance
B45: 100% | C45: Completada
B46: 50% | C46: En proceso
B47: 0% | C47: No Iniciada
B50: Autorizado:

Sheet CAN-07 Empresas
B1: ← Índice
B3: Requerimientos Funcionales
B4: Interfaz : CAN-07 — Empresas
B5: ID | C5: Requerimiento | D5: Descripción | E5: Prioridad | F5: Avance
B6: RF-01 | C6: Directorio de empresas | D6: Listar las empresas validadas vía GET /empresas con búsqueda por nombre y filtro por sector. | E6: Alta | F6: 0
B7: RF-02 | C7: Ficha de empresa | D7: Mostrar nombre comercial, logotipo, sector, tamaño, ubicación, descripción y compromisos o prácticas de inclusión declarados. | E7: Alta | F7: 0
B8: RF-03 | C8: Vacantes de la empresa | D8: Listar las vacantes publicadas por la empresa con acceso a CAN-02. | E8: Media | F8: 0
B9: RF-04 | C9: Reportar empresa | D9: Permitir reportar la empresa (POST /reportes) con motivo y descripción. | E9: Media | F9: 0
B12: Requerimientos No Funcionales
B13: Interfaz : CAN-07 — Empresas · Accesibilidad, Pantallas móviles
B14: ID | C14: Nombre | D14: Descripción | E14: Prioridad | F14: Avance
B15: RNF-ACC-01 | C15: ='RNF Accesibilidad'!C6 -> Estándar de accesibilidad | D15: ='RNF Accesibilidad'!D6 -> Las interfaces cumplen las pautas WCAG 2.1 nivel AA. | E15: ='RNF Accesibilidad'!E6 -> Alta | F15: ='RNF Accesibilidad'!F6 -> 0
B16: RNF-ACC-02 | C16: ='RNF Accesibilidad'!C7 -> Lectores de pantalla | D16: ='RNF Accesibilidad'!D7 -> Todos los elementos interactivos tienen etiqueta, rol y estado accesibles (accessibilityLabel/Role/State en React Native; HTML semántico y ARIA en Laravel) y funcionan con TalkBack, VoiceOver y NVDA. | E16: ='RNF Accesibilidad'!E7 -> Alta | F16: ='RNF Accesibilidad'!F7 -> 0
B17: RNF-ACC-03 | C17: ='RNF Accesibilidad'!C8 -> Contraste | D17: ='RNF Accesibilidad'!D8 -> Contraste mínimo de 4.5:1 para texto normal y 3:1 para texto grande y componentes de interfaz. | E17: ='RNF Accesibilidad'!E8 -> Alta | F17: ='RNF Accesibilidad'!F8 -> 0
B18: RNF-ACC-04 | C18: ='RNF Accesibilidad'!C9 -> Texto escalable | D18: ='RNF Accesibilidad'!D9 -> La interfaz respeta el tamaño de fuente del sistema y admite hasta 200 % de ampliación sin pérdida de contenido ni funcionalidad. | E18: ='RNF Accesibilidad'!E9 -> Alta | F18: ='RNF Accesibilidad'!F9 -> 0
B19: RNF-ACC-05 | C19: ='RNF Accesibilidad'!C10 -> Áreas táctiles | D19: ='RNF Accesibilidad'!D10 -> Los componentes táctiles tienen un área mínima de 48 × 48 dp en Android y 44 × 44 pt en iOS. | E19: ='RNF Accesibilidad'!E10 -> Alta | F19: ='RNF Accesibilidad'!F10 -> 0
B20: RNF-ACC-06 | C20: ='RNF Accesibilidad'!C11 -> Información no dependiente del color | D20: ='RNF Accesibilidad'!D11 -> Estados, errores y porcentajes se comunican con texto o ícono además del color. | E20: ='RNF Accesibilidad'!E11 -> Alta | F20: ='RNF Accesibilidad'!F11 -> 0
B21: RNF-ACC-07 | C21: ='RNF Accesibilidad'!C12 -> Navegación por teclado | D21: ='RNF Accesibilidad'!D12 -> El panel web puede operarse completamente con teclado y la app admite teclado externo y control por interruptores (Switch Access / Control por botón), con foco visible y orden lógico. | E21: ='RNF Accesibilidad'!E12 -> Alta | F21: ='RNF Accesibilidad'!F12 -> 0
B22: RNF-ACC-08 | C22: ='RNF Accesibilidad'!C13 -> Lenguaje claro | D22: ='RNF Accesibilidad'!D13 -> Textos en lenguaje claro y sin tecnicismos; los errores de formulario indican qué campo falla y cómo corregirlo. | E22: ='RNF Accesibilidad'!E13 -> Media | F22: ='RNF Accesibilidad'!F13 -> 0
B23: RNF-ACC-09 | C23: ='RNF Accesibilidad'!C14 -> Movimiento reducido | D23: ='RNF Accesibilidad'!D14 -> Se respeta la preferencia de «reducir movimiento» del sistema y no hay contenido parpadeante. | E23: ='RNF Accesibilidad'!E14 -> Baja | F23: ='RNF Accesibilidad'!F14 -> 0
B24: RNF-MOV-01 | C24: ='RNF Operativas Móvil'!C6 -> Desempeño | D24: ='RNF Operativas Móvil'!D6 -> Tiempo de respuesta de las pantallas ≤ 2 s en el percentil 95 sobre red 4G. | E24: ='RNF Operativas Móvil'!E6 -> Alta | F24: ='RNF Operativas Móvil'!F6 -> 0
B25: RNF-MOV-02 | C25: ='RNF Operativas Móvil'!C7 -> Compatibilidad | D25: ='RNF Operativas Móvil'!D7 -> Ejecutable en Android 8+ e iOS 15+ con un solo código base (React Native + Expo). | E25: ='RNF Operativas Móvil'!E7 -> Alta | F25: ='RNF Operativas Móvil'!F7 -> 0
B26: RNF-MOV-03 | C26: ='RNF Operativas Móvil'!C8 -> Retroalimentación | D26: ='RNF Operativas Móvil'!D8 -> Toda acción que tarde más de 300 ms muestra un indicador de carga anunciado al lector de pantalla. | E26: ='RNF Operativas Móvil'!E8 -> Media | F26: ='RNF Operativas Móvil'!F8 -> 0
B27: RNF-MOV-04 | C27: ='RNF Operativas Móvil'!C9 -> Tolerancia a fallas de red | D27: ='RNF Operativas Móvil'!D9 -> La app conserva en caché el último listado de vacantes y postulaciones y avisa cuando no hay conexión; los formularios no pierden lo capturado. | E27: ='RNF Operativas Móvil'!E9 -> Media | F27: ='RNF Operativas Móvil'!F9 -> 0
B28: RNF-MOV-05 | C28: ='RNF Operativas Móvil'!C10 -> Orientación | D28: ='RNF Operativas Móvil'!D10 -> Las pantallas funcionan en orientación vertical y horizontal. | E28: ='RNF Operativas Móvil'!E10 -> Baja | F28: ='RNF Operativas Móvil'!F10 -> 0
B29: Los RNF provienen de las hojas generales «RNF …» y se actualizan automáticamente; edita el texto y el avance en su hoja general.
B32: Elaborado por: | C32: Alan David Santiago de Vicente, Ricardo Méndez Rodríguez, Eduardo Daniel Licea González
B33: Responsable: | C33: Equipo IncluTec — Ingeniería en Sistemas Computacionales
B34: Dependencias: | C34: API REST (FastAPI), Base de datos PostgreSQL
B35: Entrega: | C35: 28 de octubre de 2026
B38: Acotaciones de Avance
B39: 100% | C39: Completada
B40: 50% | C40: En proceso
B41: 0% | C41: No Iniciada
B44: Autorizado:

Sheet REC-01 Organización
B1: ← Índice
B3: Requerimientos Funcionales
B4: Interfaz : REC-01 — Perfil de la organización
B5: ID | C5: Requerimiento | D5: Descripción | E5: Prioridad | F5: Avance
B6: RF-01 | C6: Datos de la organización | D6: Consultar y editar nombre comercial, sector, tamaño, descripción (≤ 1000 caracteres), sitio web, ubicación, logotipo (JPG/PNG ≤ 2 MB) y prácticas de inclusión vía GET/PUT /empresas/me. | E6: Alta | F6: 0
B7: RF-02 | C7: Estado de validación | D7: Mostrar un aviso con el estado de la empresa (pendiente, validada, rechazada con motivo, suspendida) y lo que implica cada uno. | E7: Alta | F7: 0
B8: RF-03 | C8: Documento de validación | D8: Permitir subir la constancia de situación fiscal (PDF ≤ 5 MB) vía POST /empresas/me/documento para que el administrador valide la empresa. | E8: Media | F8: 0
B9: RF-04 | C9: Datos fiscales protegidos | D9: Una vez validada la empresa, la razón social y el RFC quedan en solo lectura; cualquier cambio se solicita al administrador. | E9: Media | F9: 0
B10: RF-05 | C10: Seguridad de la cuenta | D10: Permitir cambiar la contraseña y cerrar sesión. | E10: Alta | F10: 0
B13: Requerimientos No Funcionales
B14: Interfaz : REC-01 — Perfil de la organización · Accesibilidad, Pantallas móviles
B15: ID | C15: Nombre | D15: Descripción | E15: Prioridad | F15: Avance
B16: RNF-ACC-01 | C16: ='RNF Accesibilidad'!C6 -> Estándar de accesibilidad | D16: ='RNF Accesibilidad'!D6 -> Las interfaces cumplen las pautas WCAG 2.1 nivel AA. | E16: ='RNF Accesibilidad'!E6 -> Alta | F16: ='RNF Accesibilidad'!F6 -> 0
B17: RNF-ACC-02 | C17: ='RNF Accesibilidad'!C7 -> Lectores de pantalla | D17: ='RNF Accesibilidad'!D7 -> Todos los elementos interactivos tienen etiqueta, rol y estado accesibles (accessibilityLabel/Role/State en React Native; HTML semántico y ARIA en Laravel) y funcionan con TalkBack, VoiceOver y NVDA. | E17: ='RNF Accesibilidad'!E7 -> Alta | F17: ='RNF Accesibilidad'!F7 -> 0
B18: RNF-ACC-03 | C18: ='RNF Accesibilidad'!C8 -> Contraste | D18: ='RNF Accesibilidad'!D8 -> Contraste mínimo de 4.5:1 para texto normal y 3:1 para texto grande y componentes de interfaz. | E18: ='RNF Accesibilidad'!E8 -> Alta | F18: ='RNF Accesibilidad'!F8 -> 0
B19: RNF-ACC-04 | C19: ='RNF Accesibilidad'!C9 -> Texto escalable | D19: ='RNF Accesibilidad'!D9 -> La interfaz respeta el tamaño de fuente del sistema y admite hasta 200 % de ampliación sin pérdida de contenido ni funcionalidad. | E19: ='RNF Accesibilidad'!E9 -> Alta | F19: ='RNF Accesibilidad'!F9 -> 0
B20: RNF-ACC-05 | C20: ='RNF Accesibilidad'!C10 -> Áreas táctiles | D20: ='RNF Accesibilidad'!D10 -> Los componentes táctiles tienen un área mínima de 48 × 48 dp en Android y 44 × 44 pt en iOS. | E20: ='RNF Accesibilidad'!E10 -> Alta | F20: ='RNF Accesibilidad'!F10 -> 0
B21: RNF-ACC-06 | C21: ='RNF Accesibilidad'!C11 -> Información no dependiente del color | D21: ='RNF Accesibilidad'!D11 -> Estados, errores y porcentajes se comunican con texto o ícono además del color. | E21: ='RNF Accesibilidad'!E11 -> Alta | F21: ='RNF Accesibilidad'!F11 -> 0
B22: RNF-ACC-07 | C22: ='RNF Accesibilidad'!C12 -> Navegación por teclado | D22: ='RNF Accesibilidad'!D12 -> El panel web puede operarse completamente con teclado y la app admite teclado externo y control por interruptores (Switch Access / Control por botón), con foco visible y orden lógico. | E22: ='RNF Accesibilidad'!E12 -> Alta | F22: ='RNF Accesibilidad'!F12 -> 0
B23: RNF-ACC-08 | C23: ='RNF Accesibilidad'!C13 -> Lenguaje claro | D23: ='RNF Accesibilidad'!D13 -> Textos en lenguaje claro y sin tecnicismos; los errores de formulario indican qué campo falla y cómo corregirlo. | E23: ='RNF Accesibilidad'!E13 -> Media | F23: ='RNF Accesibilidad'!F13 -> 0
B24: RNF-ACC-09 | C24: ='RNF Accesibilidad'!C14 -> Movimiento reducido | D24: ='RNF Accesibilidad'!D14 -> Se respeta la preferencia de «reducir movimiento» del sistema y no hay contenido parpadeante. | E24: ='RNF Accesibilidad'!E14 -> Baja | F24: ='RNF Accesibilidad'!F14 -> 0
B25: RNF-MOV-01 | C25: ='RNF Operativas Móvil'!C6 -> Desempeño | D25: ='RNF Operativas Móvil'!D6 -> Tiempo de respuesta de las pantallas ≤ 2 s en el percentil 95 sobre red 4G. | E25: ='RNF Operativas Móvil'!E6 -> Alta | F25: ='RNF Operativas Móvil'!F6 -> 0
B26: RNF-MOV-02 | C26: ='RNF Operativas Móvil'!C7 -> Compatibilidad | D26: ='RNF Operativas Móvil'!D7 -> Ejecutable en Android 8+ e iOS 15+ con un solo código base (React Native + Expo). | E26: ='RNF Operativas Móvil'!E7 -> Alta | F26: ='RNF Operativas Móvil'!F7 -> 0
B27: RNF-MOV-03 | C27: ='RNF Operativas Móvil'!C8 -> Retroalimentación | D27: ='RNF Operativas Móvil'!D8 -> Toda acción que tarde más de 300 ms muestra un indicador de carga anunciado al lector de pantalla. | E27: ='RNF Operativas Móvil'!E8 -> Media | F27: ='RNF Operativas Móvil'!F8 -> 0
B28: RNF-MOV-04 | C28: ='RNF Operativas Móvil'!C9 -> Tolerancia a fallas de red | D28: ='RNF Operativas Móvil'!D9 -> La app conserva en caché el último listado de vacantes y postulaciones y avisa cuando no hay conexión; los formularios no pierden lo capturado. | E28: ='RNF Operativas Móvil'!E9 -> Media | F28: ='RNF Operativas Móvil'!F9 -> 0
B29: RNF-MOV-05 | C29: ='RNF Operativas Móvil'!C10 -> Orientación | D29: ='RNF Operativas Móvil'!D10 -> Las pantallas funcionan en orientación vertical y horizontal. | E29: ='RNF Operativas Móvil'!E10 -> Baja | F29: ='RNF Operativas Móvil'!F10 -> 0
B30: Los RNF provienen de las hojas generales «RNF …» y se actualizan automáticamente; edita el texto y el avance en su hoja general.
B33: Elaborado por: | C33: Alan David Santiago de Vicente, Ricardo Méndez Rodríguez, Eduardo Daniel Licea González
B34: Responsable: | C34: Equipo IncluTec — Ingeniería en Sistemas Computacionales
B35: Dependencias: | C35: API REST (FastAPI), Base de datos PostgreSQL; catálogos de sector y tamaño
B36: Entrega: | C36: 28 de octubre de 2026
B39: Acotaciones de Avance
B40: 100% | C40: Completada
B41: 50% | C41: En proceso
B42: 0% | C42: No Iniciada
B45: Autorizado:

Sheet REC-02 Mis vacantes
B1: ← Índice
B3: Requerimientos Funcionales
B4: Interfaz : REC-02 — Mis vacantes
B5: ID | C5: Requerimiento | D5: Descripción | E5: Prioridad | F5: Avance
B6: RF-01 | C6: Listado de vacantes | D6: Listar las vacantes de la empresa vía GET /empresas/me/vacantes con título, estado (borrador, publicada, pausada, cerrada, suspendida), número de postulados y postulaciones nuevas. | E6: Alta | F6: 0
B7: RF-02 | C7: Filtro por estado | D7: Filtrar el listado por estado de la vacante. | E7: Media | F7: 0
B8: RF-03 | C8: Cambio de estado | D8: Permitir pausar, reanudar y cerrar una vacante vía PATCH /vacantes/{id}/estado, con confirmación. | E8: Alta | F8: 0
B9: RF-04 | C9: Crear y duplicar | D9: Botón para crear una vacante (REC-03) y opción para duplicar una existente como borrador (POST /vacantes/{id}/duplicar). | E9: Media | F9: 0
B10: RF-05 | C10: Restricción por validación | D10: Si la empresa no está validada, permitir crear borradores pero no publicar, e indicarlo en pantalla. | E10: Alta | F10: 0
B11: RF-06 | C11: Navegación | D11: Al seleccionar una vacante, ir a REC-04 (postulados); desde el menú de la tarjeta, ir a REC-03 (editar). | E11: Media | F11: 0
B14: Requerimientos No Funcionales
B15: Interfaz : REC-02 — Mis vacantes · Accesibilidad, Pantallas móviles
B16: ID | C16: Nombre | D16: Descripción | E16: Prioridad | F16: Avance
B17: RNF-ACC-01 | C17: ='RNF Accesibilidad'!C6 -> Estándar de accesibilidad | D17: ='RNF Accesibilidad'!D6 -> Las interfaces cumplen las pautas WCAG 2.1 nivel AA. | E17: ='RNF Accesibilidad'!E6 -> Alta | F17: ='RNF Accesibilidad'!F6 -> 0
B18: RNF-ACC-02 | C18: ='RNF Accesibilidad'!C7 -> Lectores de pantalla | D18: ='RNF Accesibilidad'!D7 -> Todos los elementos interactivos tienen etiqueta, rol y estado accesibles (accessibilityLabel/Role/State en React Native; HTML semántico y ARIA en Laravel) y funcionan con TalkBack, VoiceOver y NVDA. | E18: ='RNF Accesibilidad'!E7 -> Alta | F18: ='RNF Accesibilidad'!F7 -> 0
B19: RNF-ACC-03 | C19: ='RNF Accesibilidad'!C8 -> Contraste | D19: ='RNF Accesibilidad'!D8 -> Contraste mínimo de 4.5:1 para texto normal y 3:1 para texto grande y componentes de interfaz. | E19: ='RNF Accesibilidad'!E8 -> Alta | F19: ='RNF Accesibilidad'!F8 -> 0
B20: RNF-ACC-04 | C20: ='RNF Accesibilidad'!C9 -> Texto escalable | D20: ='RNF Accesibilidad'!D9 -> La interfaz respeta el tamaño de fuente del sistema y admite hasta 200 % de ampliación sin pérdida de contenido ni funcionalidad. | E20: ='RNF Accesibilidad'!E9 -> Alta | F20: ='RNF Accesibilidad'!F9 -> 0
B21: RNF-ACC-05 | C21: ='RNF Accesibilidad'!C10 -> Áreas táctiles | D21: ='RNF Accesibilidad'!D10 -> Los componentes táctiles tienen un área mínima de 48 × 48 dp en Android y 44 × 44 pt en iOS. | E21: ='RNF Accesibilidad'!E10 -> Alta | F21: ='RNF Accesibilidad'!F10 -> 0
B22: RNF-ACC-06 | C22: ='RNF Accesibilidad'!C11 -> Información no dependiente del color | D22: ='RNF Accesibilidad'!D11 -> Estados, errores y porcentajes se comunican con texto o ícono además del color. | E22: ='RNF Accesibilidad'!E11 -> Alta | F22: ='RNF Accesibilidad'!F11 -> 0
B23: RNF-ACC-07 | C23: ='RNF Accesibilidad'!C12 -> Navegación por teclado | D23: ='RNF Accesibilidad'!D12 -> El panel web puede operarse completamente con teclado y la app admite teclado externo y control por interruptores (Switch Access / Control por botón), con foco visible y orden lógico. | E23: ='RNF Accesibilidad'!E12 -> Alta | F23: ='RNF Accesibilidad'!F12 -> 0
B24: RNF-ACC-08 | C24: ='RNF Accesibilidad'!C13 -> Lenguaje claro | D24: ='RNF Accesibilidad'!D13 -> Textos en lenguaje claro y sin tecnicismos; los errores de formulario indican qué campo falla y cómo corregirlo. | E24: ='RNF Accesibilidad'!E13 -> Media | F24: ='RNF Accesibilidad'!F13 -> 0
B25: RNF-ACC-09 | C25: ='RNF Accesibilidad'!C14 -> Movimiento reducido | D25: ='RNF Accesibilidad'!D14 -> Se respeta la preferencia de «reducir movimiento» del sistema y no hay contenido parpadeante. | E25: ='RNF Accesibilidad'!E14 -> Baja | F25: ='RNF Accesibilidad'!F14 -> 0
B26: RNF-MOV-01 | C26: ='RNF Operativas Móvil'!C6 -> Desempeño | D26: ='RNF Operativas Móvil'!D6 -> Tiempo de respuesta de las pantallas ≤ 2 s en el percentil 95 sobre red 4G. | E26: ='RNF Operativas Móvil'!E6 -> Alta | F26: ='RNF Operativas Móvil'!F6 -> 0
B27: RNF-MOV-02 | C27: ='RNF Operativas Móvil'!C7 -> Compatibilidad | D27: ='RNF Operativas Móvil'!D7 -> Ejecutable en Android 8+ e iOS 15+ con un solo código base (React Native + Expo). | E27: ='RNF Operativas Móvil'!E7 -> Alta | F27: ='RNF Operativas Móvil'!F7 -> 0
B28: RNF-MOV-03 | C28: ='RNF Operativas Móvil'!C8 -> Retroalimentación | D28: ='RNF Operativas Móvil'!D8 -> Toda acción que tarde más de 300 ms muestra un indicador de carga anunciado al lector de pantalla. | E28: ='RNF Operativas Móvil'!E8 -> Media | F28: ='RNF Operativas Móvil'!F8 -> 0
B29: RNF-MOV-04 | C29: ='RNF Operativas Móvil'!C9 -> Tolerancia a fallas de red | D29: ='RNF Operativas Móvil'!D9 -> La app conserva en caché el último listado de vacantes y postulaciones y avisa cuando no hay conexión; los formularios no pierden lo capturado. | E29: ='RNF Operativas Móvil'!E9 -> Media | F29: ='RNF Operativas Móvil'!F9 -> 0
B30: RNF-MOV-05 | C30: ='RNF Operativas Móvil'!C10 -> Orientación | D30: ='RNF Operativas Móvil'!D10 -> Las pantallas funcionan en orientación vertical y horizontal. | E30: ='RNF Operativas Móvil'!E10 -> Baja | F30: ='RNF Operativas Móvil'!F10 -> 0
B31: Los RNF provienen de las hojas generales «RNF …» y se actualizan automáticamente; edita el texto y el avance en su hoja general.
B34: Elaborado por: | C34: Alan David Santiago de Vicente, Ricardo Méndez Rodríguez, Eduardo Daniel Licea González
B35: Responsable: | C35: Equipo IncluTec — Ingeniería en Sistemas Computacionales
B36: Dependencias: | C36: API REST (FastAPI), Base de datos PostgreSQL
B37: Entrega: | C37: 28 de octubre de 2026
B40: Acotaciones de Avance
B41: 100% | C41: Completada
B42: 50% | C42: En proceso
B43: 0% | C43: No Iniciada
B46: Autorizado:

Sheet REC-03 Crear vacante
B1: ← Índice
B3: Requerimientos Funcionales
B4: Interfaz : REC-03 — Crear / editar vacante
B5: ID | C5: Requerimiento | D5: Descripción | E5: Prioridad | F5: Avance
B6: RF-01 | C6: Datos generales | D6: Capturar título, categoría, descripción (≤ 2000 caracteres), jornada, tipo de contrato, número de plazas, ubicación y rango salarial opcional con la opción «mostrar salario». | E6: Alta | F6: 0
B7: RF-02 | C7: Requisitos | D7: Seleccionar habilidades del catálogo marcadas como obligatorias o deseables (al menos una obligatoria), formación mínima y años de experiencia. | E7: Alta | F7: 0
B8: RF-03 | C8: Modalidad de trabajo | D8: Elegir la modalidad (presencial, remoto o híbrido); si es presencial o híbrida, la dirección es obligatoria. | E8: Alta | F8: 0
B9: RF-04 | C9: Accesibilidad obligatoria | D9: Declarar las condiciones de accesibilidad existentes y los ajustes razonables que la empresa puede ofrecer bajo solicitud, más notas (≤ 500 caracteres). La sección es obligatoria para publicar; si no hay condiciones, se debe declarar explícitamente. | E9: Alta | F9: 0
B10: RF-05 | C10: Guardar o publicar | D10: Guardar como borrador (POST/PUT /vacantes) o publicar (estado «publicada»). Publicar requiere que la empresa esté validada y que todos los campos obligatorios sean válidos. | E10: Alta | F10: 0
B11: RF-06 | C11: Edición con postulados | D11: Al modificar requisitos o accesibilidad de una vacante con postulaciones, advertir que la compatibilidad se recalculará y que se avisará a los postulados. | E11: Media | F11: 0
B14: Requerimientos No Funcionales
B15: Interfaz : REC-03 — Crear / editar vacante · Accesibilidad, Pantallas móviles
B16: ID | C16: Nombre | D16: Descripción | E16: Prioridad | F16: Avance
B17: RNF-ACC-01 | C17: ='RNF Accesibilidad'!C6 -> Estándar de accesibilidad | D17: ='RNF Accesibilidad'!D6 -> Las interfaces cumplen las pautas WCAG 2.1 nivel AA. | E17: ='RNF Accesibilidad'!E6 -> Alta | F17: ='RNF Accesibilidad'!F6 -> 0
B18: RNF-ACC-02 | C18: ='RNF Accesibilidad'!C7 -> Lectores de pantalla | D18: ='RNF Accesibilidad'!D7 -> Todos los elementos interactivos tienen etiqueta, rol y estado accesibles (accessibilityLabel/Role/State en React Native; HTML semántico y ARIA en Laravel) y funcionan con TalkBack, VoiceOver y NVDA. | E18: ='RNF Accesibilidad'!E7 -> Alta | F18: ='RNF Accesibilidad'!F7 -> 0
B19: RNF-ACC-03 | C19: ='RNF Accesibilidad'!C8 -> Contraste | D19: ='RNF Accesibilidad'!D8 -> Contraste mínimo de 4.5:1 para texto normal y 3:1 para texto grande y componentes de interfaz. | E19: ='RNF Accesibilidad'!E8 -> Alta | F19: ='RNF Accesibilidad'!F8 -> 0
B20: RNF-ACC-04 | C20: ='RNF Accesibilidad'!C9 -> Texto escalable | D20: ='RNF Accesibilidad'!D9 -> La interfaz respeta el tamaño de fuente del sistema y admite hasta 200 % de ampliación sin pérdida de contenido ni funcionalidad. | E20: ='RNF Accesibilidad'!E9 -> Alta | F20: ='RNF Accesibilidad'!F9 -> 0
B21: RNF-ACC-05 | C21: ='RNF Accesibilidad'!C10 -> Áreas táctiles | D21: ='RNF Accesibilidad'!D10 -> Los componentes táctiles tienen un área mínima de 48 × 48 dp en Android y 44 × 44 pt en iOS. | E21: ='RNF Accesibilidad'!E10 -> Alta | F21: ='RNF Accesibilidad'!F10 -> 0
B22: RNF-ACC-06 | C22: ='RNF Accesibilidad'!C11 -> Información no dependiente del color | D22: ='RNF Accesibilidad'!D11 -> Estados, errores y porcentajes se comunican con texto o ícono además del color. | E22: ='RNF Accesibilidad'!E11 -> Alta | F22: ='RNF Accesibilidad'!F11 -> 0
B23: RNF-ACC-07 | C23: ='RNF Accesibilidad'!C12 -> Navegación por teclado | D23: ='RNF Accesibilidad'!D12 -> El panel web puede operarse completamente con teclado y la app admite teclado externo y control por interruptores (Switch Access / Control por botón), con foco visible y orden lógico. | E23: ='RNF Accesibilidad'!E12 -> Alta | F23: ='RNF Accesibilidad'!F12 -> 0
B24: RNF-ACC-08 | C24: ='RNF Accesibilidad'!C13 -> Lenguaje claro | D24: ='RNF Accesibilidad'!D13 -> Textos en lenguaje claro y sin tecnicismos; los errores de formulario indican qué campo falla y cómo corregirlo. | E24: ='RNF Accesibilidad'!E13 -> Media | F24: ='RNF Accesibilidad'!F13 -> 0
B25: RNF-ACC-09 | C25: ='RNF Accesibilidad'!C14 -> Movimiento reducido | D25: ='RNF Accesibilidad'!D14 -> Se respeta la preferencia de «reducir movimiento» del sistema y no hay contenido parpadeante. | E25: ='RNF Accesibilidad'!E14 -> Baja | F25: ='RNF Accesibilidad'!F14 -> 0
B26: RNF-MOV-01 | C26: ='RNF Operativas Móvil'!C6 -> Desempeño | D26: ='RNF Operativas Móvil'!D6 -> Tiempo de respuesta de las pantallas ≤ 2 s en el percentil 95 sobre red 4G. | E26: ='RNF Operativas Móvil'!E6 -> Alta | F26: ='RNF Operativas Móvil'!F6 -> 0
B27: RNF-MOV-02 | C27: ='RNF Operativas Móvil'!C7 -> Compatibilidad | D27: ='RNF Operativas Móvil'!D7 -> Ejecutable en Android 8+ e iOS 15+ con un solo código base (React Native + Expo). | E27: ='RNF Operativas Móvil'!E7 -> Alta | F27: ='RNF Operativas Móvil'!F7 -> 0
B28: RNF-MOV-03 | C28: ='RNF Operativas Móvil'!C8 -> Retroalimentación | D28: ='RNF Operativas Móvil'!D8 -> Toda acción que tarde más de 300 ms muestra un indicador de carga anunciado al lector de pantalla. | E28: ='RNF Operativas Móvil'!E8 -> Media | F28: ='RNF Operativas Móvil'!F8 -> 0
B29: RNF-MOV-04 | C29: ='RNF Operativas Móvil'!C9 -> Tolerancia a fallas de red | D29: ='RNF Operativas Móvil'!D9 -> La app conserva en caché el último listado de vacantes y postulaciones y avisa cuando no hay conexión; los formularios no pierden lo capturado. | E29: ='RNF Operativas Móvil'!E9 -> Media | F29: ='RNF Operativas Móvil'!F9 -> 0
B30: RNF-MOV-05 | C30: ='RNF Operativas Móvil'!C10 -> Orientación | D30: ='RNF Operativas Móvil'!D10 -> Las pantallas funcionan en orientación vertical y horizontal. | E30: ='RNF Operativas Móvil'!E10 -> Baja | F30: ='RNF Operativas Móvil'!F10 -> 0
B31: Los RNF provienen de las hojas generales «RNF …» y se actualizan automáticamente; edita el texto y el avance en su hoja general.
B34: Elaborado por: | C34: Alan David Santiago de Vicente, Ricardo Méndez Rodríguez, Eduardo Daniel Licea González
B35: Responsable: | C35: Equipo IncluTec — Ingeniería en Sistemas Computacionales
B36: Dependencias: | C36: API REST (FastAPI), Base de datos PostgreSQL; catálogos (categorías, habilidades, modalidades, jornadas, niveles educativos, ajustes)
B37: Entrega: | C37: 28 de octubre de 2026
B40: Acotaciones de Avance
B41: 100% | C41: Completada
B42: 50% | C42: En proceso
B43: 0% | C43: No Iniciada
B46: Autorizado:

Sheet REC-04 Postulados
B1: ← Índice
B3: Requerimientos Funcionales
B4: Interfaz : REC-04 — Candidatos postulados
B5: ID | C5: Requerimiento | D5: Descripción | E5: Prioridad | F5: Avance
B6: RF-01 | C6: Listado por vacante | D6: Listar los postulados de una vacante vía GET /vacantes/{id}/postulaciones, ordenados por compatibilidad laboral descendente. | E6: Alta | F6: 0
B7: RF-02 | C7: Información por postulado | D7: Mostrar nombre, porcentaje de compatibilidad laboral, estado, fecha de postulación y el indicador «ajustes por confirmar» cuando corresponda. | E7: Alta | F7: 0
B8: RF-03 | C8: Compatibilidad sin sesgo | D8: La compatibilidad mostrada al reclutador considera solo habilidades, formación y modalidad; las necesidades de ajuste nunca reducen la posición del candidato en la lista. | E8: Alta | F8: 0
B9: RF-04 | C9: Filtros | D9: Filtrar por estado de la postulación y por compatibilidad mínima. | E9: Media | F9: 0
B10: RF-05 | C10: Navegación al detalle | D10: Al seleccionar un postulado, navegar a REC-05 con el id de la postulación. | E10: Media | F10: 0
B13: Requerimientos No Funcionales
B14: Interfaz : REC-04 — Candidatos postulados · Accesibilidad, Pantallas móviles
B15: ID | C15: Nombre | D15: Descripción | E15: Prioridad | F15: Avance
B16: RNF-ACC-01 | C16: ='RNF Accesibilidad'!C6 -> Estándar de accesibilidad | D16: ='RNF Accesibilidad'!D6 -> Las interfaces cumplen las pautas WCAG 2.1 nivel AA. | E16: ='RNF Accesibilidad'!E6 -> Alta | F16: ='RNF Accesibilidad'!F6 -> 0
B17: RNF-ACC-02 | C17: ='RNF Accesibilidad'!C7 -> Lectores de pantalla | D17: ='RNF Accesibilidad'!D7 -> Todos los elementos interactivos tienen etiqueta, rol y estado accesibles (accessibilityLabel/Role/State en React Native; HTML semántico y ARIA en Laravel) y funcionan con TalkBack, VoiceOver y NVDA. | E17: ='RNF Accesibilidad'!E7 -> Alta | F17: ='RNF Accesibilidad'!F7 -> 0
B18: RNF-ACC-03 | C18: ='RNF Accesibilidad'!C8 -> Contraste | D18: ='RNF Accesibilidad'!D8 -> Contraste mínimo de 4.5:1 para texto normal y 3:1 para texto grande y componentes de interfaz. | E18: ='RNF Accesibilidad'!E8 -> Alta | F18: ='RNF Accesibilidad'!F8 -> 0
B19: RNF-ACC-04 | C19: ='RNF Accesibilidad'!C9 -> Texto escalable | D19: ='RNF Accesibilidad'!D9 -> La interfaz respeta el tamaño de fuente del sistema y admite hasta 200 % de ampliación sin pérdida de contenido ni funcionalidad. | E19: ='RNF Accesibilidad'!E9 -> Alta | F19: ='RNF Accesibilidad'!F9 -> 0
B20: RNF-ACC-05 | C20: ='RNF Accesibilidad'!C10 -> Áreas táctiles | D20: ='RNF Accesibilidad'!D10 -> Los componentes táctiles tienen un área mínima de 48 × 48 dp en Android y 44 × 44 pt en iOS. | E20: ='RNF Accesibilidad'!E10 -> Alta | F20: ='RNF Accesibilidad'!F10 -> 0
B21: RNF-ACC-06 | C21: ='RNF Accesibilidad'!C11 -> Información no dependiente del color | D21: ='RNF Accesibilidad'!D11 -> Estados, errores y porcentajes se comunican con texto o ícono además del color. | E21: ='RNF Accesibilidad'!E11 -> Alta | F21: ='RNF Accesibilidad'!F11 -> 0
B22: RNF-ACC-07 | C22: ='RNF Accesibilidad'!C12 -> Navegación por teclado | D22: ='RNF Accesibilidad'!D12 -> El panel web puede operarse completamente con teclado y la app admite teclado externo y control por interruptores (Switch Access / Control por botón), con foco visible y orden lógico. | E22: ='RNF Accesibilidad'!E12 -> Alta | F22: ='RNF Accesibilidad'!F12 -> 0
B23: RNF-ACC-08 | C23: ='RNF Accesibilidad'!C13 -> Lenguaje claro | D23: ='RNF Accesibilidad'!D13 -> Textos en lenguaje claro y sin tecnicismos; los errores de formulario indican qué campo falla y cómo corregirlo. | E23: ='RNF Accesibilidad'!E13 -> Media | F23: ='RNF Accesibilidad'!F13 -> 0
B24: RNF-ACC-09 | C24: ='RNF Accesibilidad'!C14 -> Movimiento reducido | D24: ='RNF Accesibilidad'!D14 -> Se respeta la preferencia de «reducir movimiento» del sistema y no hay contenido parpadeante. | E24: ='RNF Accesibilidad'!E14 -> Baja | F24: ='RNF Accesibilidad'!F14 -> 0
B25: RNF-MOV-01 | C25: ='RNF Operativas Móvil'!C6 -> Desempeño | D25: ='RNF Operativas Móvil'!D6 -> Tiempo de respuesta de las pantallas ≤ 2 s en el percentil 95 sobre red 4G. | E25: ='RNF Operativas Móvil'!E6 -> Alta | F25: ='RNF Operativas Móvil'!F6 -> 0
B26: RNF-MOV-02 | C26: ='RNF Operativas Móvil'!C7 -> Compatibilidad | D26: ='RNF Operativas Móvil'!D7 -> Ejecutable en Android 8+ e iOS 15+ con un solo código base (React Native + Expo). | E26: ='RNF Operativas Móvil'!E7 -> Alta | F26: ='RNF Operativas Móvil'!F7 -> 0
B27: RNF-MOV-03 | C27: ='RNF Operativas Móvil'!C8 -> Retroalimentación | D27: ='RNF Operativas Móvil'!D8 -> Toda acción que tarde más de 300 ms muestra un indicador de carga anunciado al lector de pantalla. | E27: ='RNF Operativas Móvil'!E8 -> Media | F27: ='RNF Operativas Móvil'!F8 -> 0
B28: RNF-MOV-04 | C28: ='RNF Operativas Móvil'!C9 -> Tolerancia a fallas de red | D28: ='RNF Operativas Móvil'!D9 -> La app conserva en caché el último listado de vacantes y postulaciones y avisa cuando no hay conexión; los formularios no pierden lo capturado. | E28: ='RNF Operativas Móvil'!E9 -> Media | F28: ='RNF Operativas Móvil'!F9 -> 0
B29: RNF-MOV-05 | C29: ='RNF Operativas Móvil'!C10 -> Orientación | D29: ='RNF Operativas Móvil'!D10 -> Las pantallas funcionan en orientación vertical y horizontal. | E29: ='RNF Operativas Móvil'!E10 -> Baja | F29: ='RNF Operativas Móvil'!F10 -> 0
B30: Los RNF provienen de las hojas generales «RNF …» y se actualizan automáticamente; edita el texto y el avance en su hoja general.
B33: Elaborado por: | C33: Alan David Santiago de Vicente, Ricardo Méndez Rodríguez, Eduardo Daniel Licea González
B34: Responsable: | C34: Equipo IncluTec — Ingeniería en Sistemas Computacionales
B35: Dependencias: | C35: API REST (FastAPI), Base de datos PostgreSQL; motor de compatibilidad
B36: Entrega: | C36: 28 de octubre de 2026
B39: Acotaciones de Avance
B40: 100% | C40: Completada
B41: 50% | C41: En proceso
B42: 0% | C42: No Iniciada
B45: Autorizado:

Sheet REC-05 Detalle postulado
B1: ← Índice
B3: Requerimientos Funcionales
B4: Interfaz : REC-05 — Detalle del postulado
B5: ID | C5: Requerimiento | D5: Descripción | E5: Prioridad | F5: Avance
B6: RF-01 | C6: CV del candidato | D6: Obtener GET /postulaciones/{id}/candidato y mostrar resumen, experiencia, formación, habilidades y mensaje de postulación. | E6: Alta | F6: 0
B7: RF-02 | C7: Desglose de compatibilidad | D7: Mostrar las habilidades obligatorias y deseables que cumple y las que no, la formación y la modalidad. | E7: Alta | F7: 0
B8: RF-03 | C8: Necesidades de ajuste | D8: Si el candidato dio su consentimiento, mostrar sus necesidades de ajuste indicando cuáles ya están cubiertas por la vacante y cuáles requieren confirmación de la empresa. | E8: Alta | F8: 0
B9: RF-04 | C9: Cambio de estado | D9: Cambiar el estado vía PATCH /postulaciones/{id}/estado solo con transiciones válidas (postulada → en revisión → entrevista → aceptada / no seleccionada), con mensaje opcional para el candidato; el cambio genera notificación. | E9: Alta | F9: 0
B10: RF-05 | C10: Observaciones del proceso | D10: Registrar y consultar observaciones internas con fecha y autor (POST/GET /postulaciones/{id}/observaciones); no son visibles para el candidato. | E10: Alta | F10: 0
B11: RF-06 | C11: Datos de contacto | D11: Mostrar el correo y el teléfono del candidato a partir del estado «entrevista». | E11: Media | F11: 0
B12: RF-07 | C12: Reportar candidato | D12: Permitir reportar el perfil (POST /reportes) con motivo y descripción. | E12: Baja | F12: 0
B15: Requerimientos No Funcionales
B16: Interfaz : REC-05 — Detalle del postulado · Accesibilidad, Privacidad y datos sensibles, Pantallas móviles, Notificaciones
B17: ID | C17: Nombre | D17: Descripción | E17: Prioridad | F17: Avance
B18: RNF-ACC-01 | C18: ='RNF Accesibilidad'!C6 -> Estándar de accesibilidad | D18: ='RNF Accesibilidad'!D6 -> Las interfaces cumplen las pautas WCAG 2.1 nivel AA. | E18: ='RNF Accesibilidad'!E6 -> Alta | F18: ='RNF Accesibilidad'!F6 -> 0
B19: RNF-ACC-02 | C19: ='RNF Accesibilidad'!C7 -> Lectores de pantalla | D19: ='RNF Accesibilidad'!D7 -> Todos los elementos interactivos tienen etiqueta, rol y estado accesibles (accessibilityLabel/Role/State en React Native; HTML semántico y ARIA en Laravel) y funcionan con TalkBack, VoiceOver y NVDA. | E19: ='RNF Accesibilidad'!E7 -> Alta | F19: ='RNF Accesibilidad'!F7 -> 0
B20: RNF-ACC-03 | C20: ='RNF Accesibilidad'!C8 -> Contraste | D20: ='RNF Accesibilidad'!D8 -> Contraste mínimo de 4.5:1 para texto normal y 3:1 para texto grande y componentes de interfaz. | E20: ='RNF Accesibilidad'!E8 -> Alta | F20: ='RNF Accesibilidad'!F8 -> 0
B21: RNF-ACC-04 | C21: ='RNF Accesibilidad'!C9 -> Texto escalable | D21: ='RNF Accesibilidad'!D9 -> La interfaz respeta el tamaño de fuente del sistema y admite hasta 200 % de ampliación sin pérdida de contenido ni funcionalidad. | E21: ='RNF Accesibilidad'!E9 -> Alta | F21: ='RNF Accesibilidad'!F9 -> 0
B22: RNF-ACC-05 | C22: ='RNF Accesibilidad'!C10 -> Áreas táctiles | D22: ='RNF Accesibilidad'!D10 -> Los componentes táctiles tienen un área mínima de 48 × 48 dp en Android y 44 × 44 pt en iOS. | E22: ='RNF Accesibilidad'!E10 -> Alta | F22: ='RNF Accesibilidad'!F10 -> 0
B23: RNF-ACC-06 | C23: ='RNF Accesibilidad'!C11 -> Información no dependiente del color | D23: ='RNF Accesibilidad'!D11 -> Estados, errores y porcentajes se comunican con texto o ícono además del color. | E23: ='RNF Accesibilidad'!E11 -> Alta | F23: ='RNF Accesibilidad'!F11 -> 0
B24: RNF-ACC-07 | C24: ='RNF Accesibilidad'!C12 -> Navegación por teclado | D24: ='RNF Accesibilidad'!D12 -> El panel web puede operarse completamente con teclado y la app admite teclado externo y control por interruptores (Switch Access / Control por botón), con foco visible y orden lógico. | E24: ='RNF Accesibilidad'!E12 -> Alta | F24: ='RNF Accesibilidad'!F12 -> 0
B25: RNF-ACC-08 | C25: ='RNF Accesibilidad'!C13 -> Lenguaje claro | D25: ='RNF Accesibilidad'!D13 -> Textos en lenguaje claro y sin tecnicismos; los errores de formulario indican qué campo falla y cómo corregirlo. | E25: ='RNF Accesibilidad'!E13 -> Media | F25: ='RNF Accesibilidad'!F13 -> 0
B26: RNF-ACC-09 | C26: ='RNF Accesibilidad'!C14 -> Movimiento reducido | D26: ='RNF Accesibilidad'!D14 -> Se respeta la preferencia de «reducir movimiento» del sistema y no hay contenido parpadeante. | E26: ='RNF Accesibilidad'!E14 -> Baja | F26: ='RNF Accesibilidad'!F14 -> 0
B27: RNF-PRV-01 | C27: ='RNF Privacidad'!C6 -> Cumplimiento legal | D27: ='RNF Privacidad'!D6 -> El tratamiento de datos personales cumple la Ley Federal de Protección de Datos Personales en Posesión de los Particulares, con aviso de privacidad y consentimiento expreso para datos sensibles. | E27: ='RNF Privacidad'!E6 -> Alta | F27: ='RNF Privacidad'!F6 -> 0
B28: RNF-PRV-02 | C28: ='RNF Privacidad'!C7 -> Minimización de datos | D28: ='RNF Privacidad'!D7 -> El sistema registra necesidades de ajuste y no diagnósticos, tipos de discapacidad ni documentos médicos. | E28: ='RNF Privacidad'!E7 -> Alta | F28: ='RNF Privacidad'!F7 -> 0
B29: RNF-PRV-03 | C29: ='RNF Privacidad'!C8 -> Control del candidato | D29: ='RNF Privacidad'!D8 -> Las necesidades de ajuste solo son visibles para el candidato y para las empresas a cuyas vacantes se postuló con consentimiento; el administrador solo ve datos agregados. | E29: ='RNF Privacidad'!E8 -> Alta | F29: ='RNF Privacidad'!F8 -> 0
B30: RNF-PRV-04 | C30: ='RNF Privacidad'!C9 -> Derechos ARCO | D30: ='RNF Privacidad'!D9 -> El candidato puede consultar, corregir y eliminar sus datos; la eliminación anonimiza sus postulaciones históricas en un plazo máximo de 30 días. | E30: ='RNF Privacidad'!E9 -> Alta | F30: ='RNF Privacidad'!F9 -> 0
B31: RNF-PRV-05 | C31: ='RNF Privacidad'!C10 -> Registros sin datos sensibles | D31: ='RNF Privacidad'!D10 -> Los logs del servidor y los mensajes push no incluyen necesidades de ajuste ni datos de contacto. | E31: ='RNF Privacidad'!E10 -> Alta | F31: ='RNF Privacidad'!F10 -> 0
B32: RNF-MOV-01 | C32: ='RNF Operativas Móvil'!C6 -> Desempeño | D32: ='RNF Operativas Móvil'!D6 -> Tiempo de respuesta de las pantallas ≤ 2 s en el percentil 95 sobre red 4G. | E32: ='RNF Operativas Móvil'!E6 -> Alta | F32: ='RNF Operativas Móvil'!F6 -> 0
B33: RNF-MOV-02 | C33: ='RNF Operativas Móvil'!C7 -> Compatibilidad | D33: ='RNF Operativas Móvil'!D7 -> Ejecutable en Android 8+ e iOS 15+ con un solo código base (React Native + Expo). | E33: ='RNF Operativas Móvil'!E7 -> Alta | F33: ='RNF Operativas Móvil'!F7 -> 0
B34: RNF-MOV-03 | C34: ='RNF Operativas Móvil'!C8 -> Retroalimentación | D34: ='RNF Operativas Móvil'!D8 -> Toda acción que tarde más de 300 ms muestra un indicador de carga anunciado al lector de pantalla. | E34: ='RNF Operativas Móvil'!E8 -> Media | F34: ='RNF Operativas Móvil'!F8 -> 0
B35: RNF-MOV-04 | C35: ='RNF Operativas Móvil'!C9 -> Tolerancia a fallas de red | D35: ='RNF Operativas Móvil'!D9 -> La app conserva en caché el último listado de vacantes y postulaciones y avisa cuando no hay conexión; los formularios no pierden lo capturado. | E35: ='RNF Operativas Móvil'!E9 -> Media | F35: ='RNF Operativas Móvil'!F9 -> 0
B36: RNF-MOV-05 | C36: ='RNF Operativas Móvil'!C10 -> Orientación | D36: ='RNF Operativas Móvil'!D10 -> Las pantallas funcionan en orientación vertical y horizontal. | E36: ='RNF Operativas Móvil'!E10 -> Baja | F36: ='RNF Operativas Móvil'!F10 -> 0
B37: RNF-NOT-01 | C37: ='RNF Notificaciones'!C6 -> Tiempo de entrega | D37: ='RNF Notificaciones'!D6 -> Las notificaciones push se envían en ≤ 1 min y los correos en ≤ 5 min tras el evento. | E37: ='RNF Notificaciones'!E6 -> Media | F37: ='RNF Notificaciones'!F6 -> 0
B38: RNF-NOT-02 | C38: ='RNF Notificaciones'!C7 -> Confiabilidad | D38: ='RNF Notificaciones'!D7 -> Los envíos fallidos se reintentan hasta 3 veces; el fallo de un canal no bloquea la operación que lo generó. | E38: ='RNF Notificaciones'!E7 -> Alta | F38: ='RNF Notificaciones'!F7 -> 0
B39: RNF-NOT-03 | C39: ='RNF Notificaciones'!C8 -> Correos accesibles | D39: ='RNF Notificaciones'!D8 -> Los correos incluyen versión en texto plano, estructura semántica y enlaces descriptivos. | E39: ='RNF Notificaciones'!E8 -> Media | F39: ='RNF Notificaciones'!F8 -> 0
B40: RNF-NOT-04 | C40: ='RNF Notificaciones'!C9 -> Contenido mínimo | D40: ='RNF Notificaciones'!D9 -> Las notificaciones push no incluyen datos personales sensibles; el detalle se consulta dentro de la app. | E40: ='RNF Notificaciones'!E9 -> Alta | F40: ='RNF Notificaciones'!F9 -> 0
B41: Los RNF provienen de las hojas generales «RNF …» y se actualizan automáticamente; edita el texto y el avance en su hoja general.
B44: Elaborado por: | C44: Alan David Santiago de Vicente, Ricardo Méndez Rodríguez, Eduardo Daniel Licea González
B45: Responsable: | C45: Equipo IncluTec — Ingeniería en Sistemas Computacionales
B46: Dependencias: | C46: API REST (FastAPI), Base de datos PostgreSQL; servicio de notificaciones
B47: Entrega: | C47: 28 de octubre de 2026
B50: Acotaciones de Avance
B51: 100% | C51: Completada
B52: 50% | C52: En proceso
B53: 0% | C53: No Iniciada
B56: Autorizado:

Sheet REC-06 Agenda
B1: ← Índice
B3: Requerimientos Funcionales
B4: Interfaz : REC-06 — Agenda de entrevistas
B5: ID | C5: Requerimiento | D5: Descripción | E5: Prioridad | F5: Avance
B6: RF-01 | C6: Publicar horarios | D6: Crear horarios de entrevista por vacante con fecha, hora de inicio, duración (30, 45 o 60 min) y liga genérica de Google Meet o Microsoft Teams vía POST /horarios-entrevista; validar que la fecha sea futura y que no se traslapen. | E6: Alta | F6: 0
B7: RF-02 | C7: Agenda | D7: Listar los horarios propios, libres y agendados, agrupados por día (GET /entrevistas/me), mostrando candidato y vacante en los ocupados. | E7: Alta | F7: 0
B8: RF-03 | C8: Cancelar horario | D8: Eliminar un horario libre o cancelar uno agendado (con motivo); si estaba agendado, notificar al candidato por app y correo. | E8: Alta | F8: 0
B9: RF-04 | C9: Resultado de la entrevista | D9: Marcar una entrevista como realizada o «no asistió» (PATCH /entrevistas/{id}). | E9: Media | F9: 0
B10: RF-05 | C10: Recordatorio | D10: El sistema envía un recordatorio 24 h antes de la entrevista a ambas partes. | E10: Media | F10: 0
B13: Requerimientos No Funcionales
B14: Interfaz : REC-06 — Agenda de entrevistas · Accesibilidad, Pantallas móviles, Notificaciones
B15: ID | C15: Nombre | D15: Descripción | E15: Prioridad | F15: Avance
B16: RNF-ACC-01 | C16: ='RNF Accesibilidad'!C6 -> Estándar de accesibilidad | D16: ='RNF Accesibilidad'!D6 -> Las interfaces cumplen las pautas WCAG 2.1 nivel AA. | E16: ='RNF Accesibilidad'!E6 -> Alta | F16: ='RNF Accesibilidad'!F6 -> 0
B17: RNF-ACC-02 | C17: ='RNF Accesibilidad'!C7 -> Lectores de pantalla | D17: ='RNF Accesibilidad'!D7 -> Todos los elementos interactivos tienen etiqueta, rol y estado accesibles (accessibilityLabel/Role/State en React Native; HTML semántico y ARIA en Laravel) y funcionan con TalkBack, VoiceOver y NVDA. | E17: ='RNF Accesibilidad'!E7 -> Alta | F17: ='RNF Accesibilidad'!F7 -> 0
B18: RNF-ACC-03 | C18: ='RNF Accesibilidad'!C8 -> Contraste | D18: ='RNF Accesibilidad'!D8 -> Contraste mínimo de 4.5:1 para texto normal y 3:1 para texto grande y componentes de interfaz. | E18: ='RNF Accesibilidad'!E8 -> Alta | F18: ='RNF Accesibilidad'!F8 -> 0
B19: RNF-ACC-04 | C19: ='RNF Accesibilidad'!C9 -> Texto escalable | D19: ='RNF Accesibilidad'!D9 -> La interfaz respeta el tamaño de fuente del sistema y admite hasta 200 % de ampliación sin pérdida de contenido ni funcionalidad. | E19: ='RNF Accesibilidad'!E9 -> Alta | F19: ='RNF Accesibilidad'!F9 -> 0
B20: RNF-ACC-05 | C20: ='RNF Accesibilidad'!C10 -> Áreas táctiles | D20: ='RNF Accesibilidad'!D10 -> Los componentes táctiles tienen un área mínima de 48 × 48 dp en Android y 44 × 44 pt en iOS. | E20: ='RNF Accesibilidad'!E10 -> Alta | F20: ='RNF Accesibilidad'!F10 -> 0
B21: RNF-ACC-06 | C21: ='RNF Accesibilidad'!C11 -> Información no dependiente del color | D21: ='RNF Accesibilidad'!D11 -> Estados, errores y porcentajes se comunican con texto o ícono además del color. | E21: ='RNF Accesibilidad'!E11 -> Alta | F21: ='RNF Accesibilidad'!F11 -> 0
B22: RNF-ACC-07 | C22: ='RNF Accesibilidad'!C12 -> Navegación por teclado | D22: ='RNF Accesibilidad'!D12 -> El panel web puede operarse completamente con teclado y la app admite teclado externo y control por interruptores (Switch Access / Control por botón), con foco visible y orden lógico. | E22: ='RNF Accesibilidad'!E12 -> Alta | F22: ='RNF Accesibilidad'!F12 -> 0
B23: RNF-ACC-08 | C23: ='RNF Accesibilidad'!C13 -> Lenguaje claro | D23: ='RNF Accesibilidad'!D13 -> Textos en lenguaje claro y sin tecnicismos; los errores de formulario indican qué campo falla y cómo corregirlo. | E23: ='RNF Accesibilidad'!E13 -> Media | F23: ='RNF Accesibilidad'!F13 -> 0
B24: RNF-ACC-09 | C24: ='RNF Accesibilidad'!C14 -> Movimiento reducido | D24: ='RNF Accesibilidad'!D14 -> Se respeta la preferencia de «reducir movimiento» del sistema y no hay contenido parpadeante. | E24: ='RNF Accesibilidad'!E14 -> Baja | F24: ='RNF Accesibilidad'!F14 -> 0
B25: RNF-MOV-01 | C25: ='RNF Operativas Móvil'!C6 -> Desempeño | D25: ='RNF Operativas Móvil'!D6 -> Tiempo de respuesta de las pantallas ≤ 2 s en el percentil 95 sobre red 4G. | E25: ='RNF Operativas Móvil'!E6 -> Alta | F25: ='RNF Operativas Móvil'!F6 -> 0
B26: RNF-MOV-02 | C26: ='RNF Operativas Móvil'!C7 -> Compatibilidad | D26: ='RNF Operativas Móvil'!D7 -> Ejecutable en Android 8+ e iOS 15+ con un solo código base (React Native + Expo). | E26: ='RNF Operativas Móvil'!E7 -> Alta | F26: ='RNF Operativas Móvil'!F7 -> 0
B27: RNF-MOV-03 | C27: ='RNF Operativas Móvil'!C8 -> Retroalimentación | D27: ='RNF Operativas Móvil'!D8 -> Toda acción que tarde más de 300 ms muestra un indicador de carga anunciado al lector de pantalla. | E27: ='RNF Operativas Móvil'!E8 -> Media | F27: ='RNF Operativas Móvil'!F8 -> 0
B28: RNF-MOV-04 | C28: ='RNF Operativas Móvil'!C9 -> Tolerancia a fallas de red | D28: ='RNF Operativas Móvil'!D9 -> La app conserva en caché el último listado de vacantes y postulaciones y avisa cuando no hay conexión; los formularios no pierden lo capturado. | E28: ='RNF Operativas Móvil'!E9 -> Media | F28: ='RNF Operativas Móvil'!F9 -> 0
B29: RNF-MOV-05 | C29: ='RNF Operativas Móvil'!C10 -> Orientación | D29: ='RNF Operativas Móvil'!D10 -> Las pantallas funcionan en orientación vertical y horizontal. | E29: ='RNF Operativas Móvil'!E10 -> Baja | F29: ='RNF Operativas Móvil'!F10 -> 0
B30: RNF-NOT-01 | C30: ='RNF Notificaciones'!C6 -> Tiempo de entrega | D30: ='RNF Notificaciones'!D6 -> Las notificaciones push se envían en ≤ 1 min y los correos en ≤ 5 min tras el evento. | E30: ='RNF Notificaciones'!E6 -> Media | F30: ='RNF Notificaciones'!F6 -> 0
B31: RNF-NOT-02 | C31: ='RNF Notificaciones'!C7 -> Confiabilidad | D31: ='RNF Notificaciones'!D7 -> Los envíos fallidos se reintentan hasta 3 veces; el fallo de un canal no bloquea la operación que lo generó. | E31: ='RNF Notificaciones'!E7 -> Alta | F31: ='RNF Notificaciones'!F7 -> 0
B32: RNF-NOT-03 | C32: ='RNF Notificaciones'!C8 -> Correos accesibles | D32: ='RNF Notificaciones'!D8 -> Los correos incluyen versión en texto plano, estructura semántica y enlaces descriptivos. | E32: ='RNF Notificaciones'!E8 -> Media | F32: ='RNF Notificaciones'!F8 -> 0
B33: RNF-NOT-04 | C33: ='RNF Notificaciones'!C9 -> Contenido mínimo | D33: ='RNF Notificaciones'!D9 -> Las notificaciones push no incluyen datos personales sensibles; el detalle se consulta dentro de la app. | E33: ='RNF Notificaciones'!E9 -> Alta | F33: ='RNF Notificaciones'!F9 -> 0
B34: Los RNF provienen de las hojas generales «RNF …» y se actualizan automáticamente; edita el texto y el avance en su hoja general.
B37: Elaborado por: | C37: Alan David Santiago de Vicente, Ricardo Méndez Rodríguez, Eduardo Daniel Licea González
B38: Responsable: | C38: Equipo IncluTec — Ingeniería en Sistemas Computacionales
B39: Dependencias: | C39: API REST (FastAPI), Base de datos PostgreSQL; servicio de correo
B40: Entrega: | C40: 28 de octubre de 2026
B43: Acotaciones de Avance
B44: 100% | C44: Completada
B45: 50% | C45: En proceso
B46: 0% | C46: No Iniciada
B49: Autorizado:

Sheet WEB-01 Login web
B1: ← Índice
B3: Requerimientos Funcionales
B4: Interfaz : WEB-01 — Inicio de sesión (web)
B5: ID | C5: Requerimiento | D5: Descripción | E5: Prioridad | F5: Avance
B6: RF-01 | C6: Captura de credenciales | D6: Capturar correo (RFC 5322) y contraseña (≥ 8 caracteres); deshabilitar el envío hasta que ambos sean válidos. | E6: Alta | F6: 0
B7: RF-02 | C7: Autenticación contra API | D7: Laravel envía las credenciales a POST /auth/login y guarda el JWT en la sesión del servidor; el token nunca se expone al navegador. | E7: Alta | F7: 0
B8: RF-03 | C8: Restricción de rol | D8: Permitir el acceso solo si el rol es «administrador»; en otro caso, mostrar 403 y cerrar la sesión. | E8: Alta | F8: 0
B9: RF-04 | C9: Mensajes de error | D9: Manejar 401, 403, 423 y 5xx con mensajes claros sin exponer detalles técnicos. | E9: Media | F9: 0
B10: RF-05 | C10: Protección de rutas | D10: Proteger todas las rutas del panel con middleware; si el API responde 401 (token vencido), redirigir a WEB-01. | E10: Alta | F10: 0
B13: Requerimientos No Funcionales
B14: Interfaz : WEB-01 — Inicio de sesión (web) · Accesibilidad, Inicio de sesión, registro y recuperación
B15: ID | C15: Nombre | D15: Descripción | E15: Prioridad | F15: Avance
B16: RNF-ACC-01 | C16: ='RNF Accesibilidad'!C6 -> Estándar de accesibilidad | D16: ='RNF Accesibilidad'!D6 -> Las interfaces cumplen las pautas WCAG 2.1 nivel AA. | E16: ='RNF Accesibilidad'!E6 -> Alta | F16: ='RNF Accesibilidad'!F6 -> 0
B17: RNF-ACC-02 | C17: ='RNF Accesibilidad'!C7 -> Lectores de pantalla | D17: ='RNF Accesibilidad'!D7 -> Todos los elementos interactivos tienen etiqueta, rol y estado accesibles (accessibilityLabel/Role/State en React Native; HTML semántico y ARIA en Laravel) y funcionan con TalkBack, VoiceOver y NVDA. | E17: ='RNF Accesibilidad'!E7 -> Alta | F17: ='RNF Accesibilidad'!F7 -> 0
B18: RNF-ACC-03 | C18: ='RNF Accesibilidad'!C8 -> Contraste | D18: ='RNF Accesibilidad'!D8 -> Contraste mínimo de 4.5:1 para texto normal y 3:1 para texto grande y componentes de interfaz. | E18: ='RNF Accesibilidad'!E8 -> Alta | F18: ='RNF Accesibilidad'!F8 -> 0
B19: RNF-ACC-04 | C19: ='RNF Accesibilidad'!C9 -> Texto escalable | D19: ='RNF Accesibilidad'!D9 -> La interfaz respeta el tamaño de fuente del sistema y admite hasta 200 % de ampliación sin pérdida de contenido ni funcionalidad. | E19: ='RNF Accesibilidad'!E9 -> Alta | F19: ='RNF Accesibilidad'!F9 -> 0
B20: RNF-ACC-05 | C20: ='RNF Accesibilidad'!C10 -> Áreas táctiles | D20: ='RNF Accesibilidad'!D10 -> Los componentes táctiles tienen un área mínima de 48 × 48 dp en Android y 44 × 44 pt en iOS. | E20: ='RNF Accesibilidad'!E10 -> Alta | F20: ='RNF Accesibilidad'!F10 -> 0
B21: RNF-ACC-06 | C21: ='RNF Accesibilidad'!C11 -> Información no dependiente del color | D21: ='RNF Accesibilidad'!D11 -> Estados, errores y porcentajes se comunican con texto o ícono además del color. | E21: ='RNF Accesibilidad'!E11 -> Alta | F21: ='RNF Accesibilidad'!F11 -> 0
B22: RNF-ACC-07 | C22: ='RNF Accesibilidad'!C12 -> Navegación por teclado | D22: ='RNF Accesibilidad'!D12 -> El panel web puede operarse completamente con teclado y la app admite teclado externo y control por interruptores (Switch Access / Control por botón), con foco visible y orden lógico. | E22: ='RNF Accesibilidad'!E12 -> Alta | F22: ='RNF Accesibilidad'!F12 -> 0
B23: RNF-ACC-08 | C23: ='RNF Accesibilidad'!C13 -> Lenguaje claro | D23: ='RNF Accesibilidad'!D13 -> Textos en lenguaje claro y sin tecnicismos; los errores de formulario indican qué campo falla y cómo corregirlo. | E23: ='RNF Accesibilidad'!E13 -> Media | F23: ='RNF Accesibilidad'!F13 -> 0
B24: RNF-ACC-09 | C24: ='RNF Accesibilidad'!C14 -> Movimiento reducido | D24: ='RNF Accesibilidad'!D14 -> Se respeta la preferencia de «reducir movimiento» del sistema y no hay contenido parpadeante. | E24: ='RNF Accesibilidad'!E14 -> Baja | F24: ='RNF Accesibilidad'!F14 -> 0
B25: RNF-AUT-01 | C25: ='RNF Autenticación'!C6 -> Seguridad — contraseñas | D25: ='RNF Autenticación'!D6 -> Las contraseñas se almacenan únicamente como hash bcrypt (cost ≥ 10); nunca en texto plano ni en registros. | E25: ='RNF Autenticación'!E6 -> Alta | F25: ='RNF Autenticación'!F6 -> 0
B26: RNF-AUT-02 | C26: ='RNF Autenticación'!C7 -> Seguridad — tokens | D26: ='RNF Autenticación'!D7 -> JWT firmado HS256 con expiración de 8 h; transporte HTTPS obligatorio; almacenamiento en expo-secure-store (móvil) y en la sesión del servidor Laravel (web). | E26: ='RNF Autenticación'!E7 -> Alta | F26: ='RNF Autenticación'!F7 -> 0
B27: RNF-AUT-03 | C27: ='RNF Autenticación'!C8 -> Protección contra fuerza bruta | D27: ='RNF Autenticación'!D8 -> Bloqueo temporal de 15 minutos tras 5 intentos fallidos consecutivos por cuenta o por IP. | E27: ='RNF Autenticación'!E8 -> Alta | F27: ='RNF Autenticación'!F8 -> 0
B28: RNF-AUT-04 | C28: ='RNF Autenticación'!C9 -> Mensajes neutros | D28: ='RNF Autenticación'!D9 -> Los mensajes de error no revelan si un correo existe en el sistema. | E28: ='RNF Autenticación'!E9 -> Media | F28: ='RNF Autenticación'!F9 -> 0
B29: RNF-AUT-05 | C29: ='RNF Autenticación'!C10 -> Desempeño | D29: ='RNF Autenticación'!D10 -> El inicio de sesión responde en ≤ 1.5 s en el percentil 95. | E29: ='RNF Autenticación'!E10 -> Media | F29: ='RNF Autenticación'!F10 -> 0
B30: Los RNF provienen de las hojas generales «RNF …» y se actualizan automáticamente; edita el texto y el avance en su hoja general.
B33: Elaborado por: | C33: Alan David Santiago de Vicente, Ricardo Méndez Rodríguez, Eduardo Daniel Licea González
B34: Responsable: | C34: Equipo IncluTec — Ingeniería en Sistemas Computacionales
B35: Dependencias: | C35: API REST (FastAPI), Base de datos PostgreSQL; Laravel como cliente del API
B36: Entrega: | C36: 28 de octubre de 2026
B39: Acotaciones de Avance
B40: 100% | C40: Completada
B41: 50% | C41: En proceso
B42: 0% | C42: No Iniciada
B45: Autorizado:

Sheet WEB-02 Dashboard
B1: ← Índice
B3: Requerimientos Funcionales
B4: Interfaz : WEB-02 — Dashboard y estadísticas
B5: ID | C5: Requerimiento | D5: Descripción | E5: Prioridad | F5: Avance
B6: RF-01 | C6: Indicadores clave | D6: Mostrar candidatos activos, empresas validadas, vacantes publicadas, postulaciones del periodo, contrataciones (postulaciones aceptadas) y tasa de colocación, vía GET /admin/estadisticas/resumen. | E6: Alta | F6: 0
B7: RF-02 | C7: Pendientes de atención | D7: Mostrar el número de empresas pendientes de validar y de reportes abiertos, con acceso directo a WEB-04 y WEB-08. | E7: Alta | F7: 0
B8: RF-03 | C8: Gráficas de vinculación | D8: Graficar postulaciones por estado, vacantes por modalidad y categoría, y la evolución mensual de postulaciones y contrataciones. | E8: Alta | F8: 0
B9: RF-04 | C9: Brecha de accesibilidad | D9: Comparar los ajustes más solicitados por candidatos contra los más ofrecidos en vacantes, y las habilidades más demandadas contra las más registradas. | E9: Alta | F9: 0
B10: RF-05 | C10: Filtros de periodo | D10: Filtrar todas las métricas por rango de fechas (por defecto, últimos 30 días). | E10: Media | F10: 0
B11: RF-06 | C11: Exportación | D11: Exportar el reporte estadístico en PDF y XLSX vía GET /admin/estadisticas/exportar?formato=. | E11: Media | F11: 0
B12: RF-07 | C12: Datos agregados | D12: Las estadísticas se presentan solo de forma agregada; no permiten identificar a un candidato ni sus necesidades de ajuste. | E12: Alta | F12: 0
B15: Requerimientos No Funcionales
B16: Interfaz : WEB-02 — Dashboard y estadísticas · Accesibilidad, Dashboard y estadísticas
B17: ID | C17: Nombre | D17: Descripción | E17: Prioridad | F17: Avance
B18: RNF-ACC-01 | C18: ='RNF Accesibilidad'!C6 -> Estándar de accesibilidad | D18: ='RNF Accesibilidad'!D6 -> Las interfaces cumplen las pautas WCAG 2.1 nivel AA. | E18: ='RNF Accesibilidad'!E6 -> Alta | F18: ='RNF Accesibilidad'!F6 -> 0
B19: RNF-ACC-02 | C19: ='RNF Accesibilidad'!C7 -> Lectores de pantalla | D19: ='RNF Accesibilidad'!D7 -> Todos los elementos interactivos tienen etiqueta, rol y estado accesibles (accessibilityLabel/Role/State en React Native; HTML semántico y ARIA en Laravel) y funcionan con TalkBack, VoiceOver y NVDA. | E19: ='RNF Accesibilidad'!E7 -> Alta | F19: ='RNF Accesibilidad'!F7 -> 0
B20: RNF-ACC-03 | C20: ='RNF Accesibilidad'!C8 -> Contraste | D20: ='RNF Accesibilidad'!D8 -> Contraste mínimo de 4.5:1 para texto normal y 3:1 para texto grande y componentes de interfaz. | E20: ='RNF Accesibilidad'!E8 -> Alta | F20: ='RNF Accesibilidad'!F8 -> 0
B21: RNF-ACC-04 | C21: ='RNF Accesibilidad'!C9 -> Texto escalable | D21: ='RNF Accesibilidad'!D9 -> La interfaz respeta el tamaño de fuente del sistema y admite hasta 200 % de ampliación sin pérdida de contenido ni funcionalidad. | E21: ='RNF Accesibilidad'!E9 -> Alta | F21: ='RNF Accesibilidad'!F9 -> 0
B22: RNF-ACC-05 | C22: ='RNF Accesibilidad'!C10 -> Áreas táctiles | D22: ='RNF Accesibilidad'!D10 -> Los componentes táctiles tienen un área mínima de 48 × 48 dp en Android y 44 × 44 pt en iOS. | E22: ='RNF Accesibilidad'!E10 -> Alta | F22: ='RNF Accesibilidad'!F10 -> 0
B23: RNF-ACC-06 | C23: ='RNF Accesibilidad'!C11 -> Información no dependiente del color | D23: ='RNF Accesibilidad'!D11 -> Estados, errores y porcentajes se comunican con texto o ícono además del color. | E23: ='RNF Accesibilidad'!E11 -> Alta | F23: ='RNF Accesibilidad'!F11 -> 0
B24: RNF-ACC-07 | C24: ='RNF Accesibilidad'!C12 -> Navegación por teclado | D24: ='RNF Accesibilidad'!D12 -> El panel web puede operarse completamente con teclado y la app admite teclado externo y control por interruptores (Switch Access / Control por botón), con foco visible y orden lógico. | E24: ='RNF Accesibilidad'!E12 -> Alta | F24: ='RNF Accesibilidad'!F12 -> 0
B25: RNF-ACC-08 | C25: ='RNF Accesibilidad'!C13 -> Lenguaje claro | D25: ='RNF Accesibilidad'!D13 -> Textos en lenguaje claro y sin tecnicismos; los errores de formulario indican qué campo falla y cómo corregirlo. | E25: ='RNF Accesibilidad'!E13 -> Media | F25: ='RNF Accesibilidad'!F13 -> 0
B26: RNF-ACC-09 | C26: ='RNF Accesibilidad'!C14 -> Movimiento reducido | D26: ='RNF Accesibilidad'!D14 -> Se respeta la preferencia de «reducir movimiento» del sistema y no hay contenido parpadeante. | E26: ='RNF Accesibilidad'!E14 -> Baja | F26: ='RNF Accesibilidad'!F14 -> 0
B27: RNF-DSH-01 | C27: ='RNF Dashboard'!C6 -> Desempeño | D27: ='RNF Dashboard'!D6 -> Generación de estadísticas de hasta 12 meses de datos en ≤ 5 s. | E27: ='RNF Dashboard'!E6 -> Alta | F27: ='RNF Dashboard'!F6 -> 0
B28: RNF-DSH-02 | C28: ='RNF Dashboard'!C7 -> Exportación | D28: ='RNF Dashboard'!D7 -> La descarga en PDF o XLSX inicia en ≤ 3 s después de la solicitud. | E28: ='RNF Dashboard'!E7 -> Media | F28: ='RNF Dashboard'!F7 -> 0
B29: RNF-DSH-03 | C29: ='RNF Dashboard'!C8 -> Gráficas accesibles | D29: ='RNF Dashboard'!D8 -> Cada gráfica tiene título, leyenda, valores disponibles como tabla alternativa y colores distinguibles para personas con daltonismo. | E29: ='RNF Dashboard'!E8 -> Alta | F29: ='RNF Dashboard'!F8 -> 0
B30: RNF-DSH-04 | C30: ='RNF Dashboard'!C9 -> Anonimato | D30: ='RNF Dashboard'!D9 -> Los indicadores con menos de 5 registros se agrupan para evitar identificar a personas. | E30: ='RNF Dashboard'!E9 -> Media | F30: ='RNF Dashboard'!F9 -> 0
B31: Los RNF provienen de las hojas generales «RNF …» y se actualizan automáticamente; edita el texto y el avance en su hoja general.
B34: Elaborado por: | C34: Alan David Santiago de Vicente, Ricardo Méndez Rodríguez, Eduardo Daniel Licea González
B35: Responsable: | C35: Equipo IncluTec — Ingeniería en Sistemas Computacionales
B36: Dependencias: | C36: API REST (FastAPI), Base de datos PostgreSQL; librería de gráficas
B37: Entrega: | C37: 28 de octubre de 2026
B40: Acotaciones de Avance
B41: 100% | C41: Completada
B42: 50% | C42: En proceso
B43: 0% | C43: No Iniciada
B46: Autorizado:

Sheet WEB-03 Usuarios
B1: ← Índice
B3: Requerimientos Funcionales
B4: Interfaz : WEB-03 — Gestión de usuarios
B5: ID | C5: Requerimiento | D5: Descripción | E5: Prioridad | F5: Avance
B6: RF-01 | C6: Listado paginado | D6: Listar usuarios vía GET /admin/usuarios?page=&size=25 con nombre, correo, rol, empresa (si aplica), fecha de registro y estado. | E6: Alta | F6: 0
B7: RF-02 | C7: Búsqueda y filtros | D7: Buscar por nombre o correo y filtrar por rol y estado (activo, suspendido, eliminado). | E7: Media | F7: 0
B8: RF-03 | C8: Alta de usuario | D8: Crear usuarios de cualquier rol validando la unicidad del correo; la contraseña se guarda con hash bcrypt (cost ≥ 10). | E8: Alta | F8: 0
B9: RF-04 | C9: Edición | D9: Editar nombre, correo, teléfono y rol; el cambio de rol de un reclutador requiere desvincularlo de su empresa. | E9: Media | F9: 0
B10: RF-05 | C10: Suspensión y baja lógica | D10: Suspender, reactivar o dar de baja lógica un usuario (PATCH /admin/usuarios/{id}/estado) registrando el motivo; nunca se borra físicamente. | E10: Alta | F10: 0
B11: RF-06 | C11: Consulta de detalle | D11: Ver el detalle del usuario: datos generales, número de postulaciones o vacantes y reportes asociados. No se muestran las necesidades de ajuste del candidato. | E11: Media | F11: 0
B14: Requerimientos No Funcionales
B15: Interfaz : WEB-03 — Gestión de usuarios · Accesibilidad, Privacidad y datos sensibles, Pantallas de administración web
B16: ID | C16: Nombre | D16: Descripción | E16: Prioridad | F16: Avance
B17: RNF-ACC-01 | C17: ='RNF Accesibilidad'!C6 -> Estándar de accesibilidad | D17: ='RNF Accesibilidad'!D6 -> Las interfaces cumplen las pautas WCAG 2.1 nivel AA. | E17: ='RNF Accesibilidad'!E6 -> Alta | F17: ='RNF Accesibilidad'!F6 -> 0
B18: RNF-ACC-02 | C18: ='RNF Accesibilidad'!C7 -> Lectores de pantalla | D18: ='RNF Accesibilidad'!D7 -> Todos los elementos interactivos tienen etiqueta, rol y estado accesibles (accessibilityLabel/Role/State en React Native; HTML semántico y ARIA en Laravel) y funcionan con TalkBack, VoiceOver y NVDA. | E18: ='RNF Accesibilidad'!E7 -> Alta | F18: ='RNF Accesibilidad'!F7 -> 0
B19: RNF-ACC-03 | C19: ='RNF Accesibilidad'!C8 -> Contraste | D19: ='RNF Accesibilidad'!D8 -> Contraste mínimo de 4.5:1 para texto normal y 3:1 para texto grande y componentes de interfaz. | E19: ='RNF Accesibilidad'!E8 -> Alta | F19: ='RNF Accesibilidad'!F8 -> 0
B20: RNF-ACC-04 | C20: ='RNF Accesibilidad'!C9 -> Texto escalable | D20: ='RNF Accesibilidad'!D9 -> La interfaz respeta el tamaño de fuente del sistema y admite hasta 200 % de ampliación sin pérdida de contenido ni funcionalidad. | E20: ='RNF Accesibilidad'!E9 -> Alta | F20: ='RNF Accesibilidad'!F9 -> 0
B21: RNF-ACC-05 | C21: ='RNF Accesibilidad'!C10 -> Áreas táctiles | D21: ='RNF Accesibilidad'!D10 -> Los componentes táctiles tienen un área mínima de 48 × 48 dp en Android y 44 × 44 pt en iOS. | E21: ='RNF Accesibilidad'!E10 -> Alta | F21: ='RNF Accesibilidad'!F10 -> 0
B22: RNF-ACC-06 | C22: ='RNF Accesibilidad'!C11 -> Información no dependiente del color | D22: ='RNF Accesibilidad'!D11 -> Estados, errores y porcentajes se comunican con texto o ícono además del color. | E22: ='RNF Accesibilidad'!E11 -> Alta | F22: ='RNF Accesibilidad'!F11 -> 0
B23: RNF-ACC-07 | C23: ='RNF Accesibilidad'!C12 -> Navegación por teclado | D23: ='RNF Accesibilidad'!D12 -> El panel web puede operarse completamente con teclado y la app admite teclado externo y control por interruptores (Switch Access / Control por botón), con foco visible y orden lógico. | E23: ='RNF Accesibilidad'!E12 -> Alta | F23: ='RNF Accesibilidad'!F12 -> 0
B24: RNF-ACC-08 | C24: ='RNF Accesibilidad'!C13 -> Lenguaje claro | D24: ='RNF Accesibilidad'!D13 -> Textos en lenguaje claro y sin tecnicismos; los errores de formulario indican qué campo falla y cómo corregirlo. | E24: ='RNF Accesibilidad'!E13 -> Media | F24: ='RNF Accesibilidad'!F13 -> 0
B25: RNF-ACC-09 | C25: ='RNF Accesibilidad'!C14 -> Movimiento reducido | D25: ='RNF Accesibilidad'!D14 -> Se respeta la preferencia de «reducir movimiento» del sistema y no hay contenido parpadeante. | E25: ='RNF Accesibilidad'!E14 -> Baja | F25: ='RNF Accesibilidad'!F14 -> 0
B26: RNF-PRV-01 | C26: ='RNF Privacidad'!C6 -> Cumplimiento legal | D26: ='RNF Privacidad'!D6 -> El tratamiento de datos personales cumple la Ley Federal de Protección de Datos Personales en Posesión de los Particulares, con aviso de privacidad y consentimiento expreso para datos sensibles. | E26: ='RNF Privacidad'!E6 -> Alta | F26: ='RNF Privacidad'!F6 -> 0
B27: RNF-PRV-02 | C27: ='RNF Privacidad'!C7 -> Minimización de datos | D27: ='RNF Privacidad'!D7 -> El sistema registra necesidades de ajuste y no diagnósticos, tipos de discapacidad ni documentos médicos. | E27: ='RNF Privacidad'!E7 -> Alta | F27: ='RNF Privacidad'!F7 -> 0
B28: RNF-PRV-03 | C28: ='RNF Privacidad'!C8 -> Control del candidato | D28: ='RNF Privacidad'!D8 -> Las necesidades de ajuste solo son visibles para el candidato y para las empresas a cuyas vacantes se postuló con consentimiento; el administrador solo ve datos agregados. | E28: ='RNF Privacidad'!E8 -> Alta | F28: ='RNF Privacidad'!F8 -> 0
B29: RNF-PRV-04 | C29: ='RNF Privacidad'!C9 -> Derechos ARCO | D29: ='RNF Privacidad'!D9 -> El candidato puede consultar, corregir y eliminar sus datos; la eliminación anonimiza sus postulaciones históricas en un plazo máximo de 30 días. | E29: ='RNF Privacidad'!E9 -> Alta | F29: ='RNF Privacidad'!F9 -> 0
B30: RNF-PRV-05 | C30: ='RNF Privacidad'!C10 -> Registros sin datos sensibles | D30: ='RNF Privacidad'!D10 -> Los logs del servidor y los mensajes push no incluyen necesidades de ajuste ni datos de contacto. | E30: ='RNF Privacidad'!E10 -> Alta | F30: ='RNF Privacidad'!F10 -> 0
B31: RNF-WEB-01 | C31: ='RNF CRUD Web'!C6 -> Desempeño | D31: ='RNF CRUD Web'!D6 -> Listados paginados de 25 registros con tiempo de respuesta ≤ 1 s. | E31: ='RNF CRUD Web'!E6 -> Alta | F31: ='RNF CRUD Web'!F6 -> 0
B32: RNF-WEB-02 | C32: ='RNF CRUD Web'!C7 -> Validación | D32: ='RNF CRUD Web'!D7 -> Validación en cliente y servidor con mensajes específicos por campo. | E32: ='RNF CRUD Web'!E7 -> Alta | F32: ='RNF CRUD Web'!F7 -> 0
B33: RNF-WEB-03 | C33: ='RNF CRUD Web'!C8 -> Compatibilidad | D33: ='RNF CRUD Web'!D8 -> Funciona en Chrome, Firefox y Edge en sus dos versiones más recientes, en resoluciones desde 1280 px de ancho. | E33: ='RNF CRUD Web'!E8 -> Media | F33: ='RNF CRUD Web'!F8 -> 0
B34: RNF-WEB-04 | C34: ='RNF CRUD Web'!C9 -> Auditoría | D34: ='RNF CRUD Web'!D9 -> Toda creación, edición, validación, suspensión o cambio de estado queda registrado en bitácora con usuario, fecha y hora, valor anterior y valor nuevo. | E34: ='RNF CRUD Web'!E9 -> Alta | F34: ='RNF CRUD Web'!F9 -> 0
B35: RNF-WEB-05 | C35: ='RNF CRUD Web'!C10 -> Confirmación de acciones críticas | D35: ='RNF CRUD Web'!D10 -> Suspender, rechazar o dar de baja requiere confirmación y motivo. | E35: ='RNF CRUD Web'!E10 -> Media | F35: ='RNF CRUD Web'!F10 -> 0
B36: Los RNF provienen de las hojas generales «RNF …» y se actualizan automáticamente; edita el texto y el avance en su hoja general.
B39: Elaborado por: | C39: Alan David Santiago de Vicente, Ricardo Méndez Rodríguez, Eduardo Daniel Licea González
B40: Responsable: | C40: Equipo IncluTec — Ingeniería en Sistemas Computacionales
B41: Dependencias: | C41: API REST (FastAPI), Base de datos PostgreSQL
B42: Entrega: | C42: 28 de octubre de 2026
B45: Acotaciones de Avance
B46: 100% | C46: Completada
B47: 50% | C47: En proceso
B48: 0% | C48: No Iniciada
B51: Autorizado:

Sheet WEB-04 Empresas
B1: ← Índice
B3: Requerimientos Funcionales
B4: Interfaz : WEB-04 — Empresas y validación
B5: ID | C5: Requerimiento | D5: Descripción | E5: Prioridad | F5: Avance
B6: RF-01 | C6: Listado de empresas | D6: Listar empresas vía GET /admin/empresas con razón social, RFC, sector, reclutadores, vacantes activas y estado (pendiente, validada, rechazada, suspendida). | E6: Alta | F6: 0
B7: RF-02 | C7: Cola de validación | D7: Mostrar primero las empresas pendientes, ordenadas por antigüedad de la solicitud. | E7: Alta | F7: 0
B8: RF-03 | C8: Revisión y validación | D8: Mostrar los datos fiscales y el documento cargado; permitir validar o rechazar con motivo obligatorio (PATCH /admin/empresas/{id}/validacion) y notificar al reclutador. | E8: Alta | F8: 0
B9: RF-04 | C9: Validación de RFC | D9: Verificar que el RFC tenga formato válido y no esté registrado por otra empresa. | E9: Alta | F9: 0
B10: RF-05 | C10: CRUD de empresas | D10: Crear, editar y dar de baja lógica empresas; permitir corregir razón social y RFC de empresas validadas. | E10: Media | F10: 0
B11: RF-06 | C11: Suspensión | D11: Suspender una empresa con motivo; sus vacantes publicadas pasan a «suspendida» y se notifica a los postulados. | E11: Alta | F11: 0
B14: Requerimientos No Funcionales
B15: Interfaz : WEB-04 — Empresas y validación · Accesibilidad, Pantallas de administración web, Notificaciones
B16: ID | C16: Nombre | D16: Descripción | E16: Prioridad | F16: Avance
B17: RNF-ACC-01 | C17: ='RNF Accesibilidad'!C6 -> Estándar de accesibilidad | D17: ='RNF Accesibilidad'!D6 -> Las interfaces cumplen las pautas WCAG 2.1 nivel AA. | E17: ='RNF Accesibilidad'!E6 -> Alta | F17: ='RNF Accesibilidad'!F6 -> 0
B18: RNF-ACC-02 | C18: ='RNF Accesibilidad'!C7 -> Lectores de pantalla | D18: ='RNF Accesibilidad'!D7 -> Todos los elementos interactivos tienen etiqueta, rol y estado accesibles (accessibilityLabel/Role/State en React Native; HTML semántico y ARIA en Laravel) y funcionan con TalkBack, VoiceOver y NVDA. | E18: ='RNF Accesibilidad'!E7 -> Alta | F18: ='RNF Accesibilidad'!F7 -> 0
B19: RNF-ACC-03 | C19: ='RNF Accesibilidad'!C8 -> Contraste | D19: ='RNF Accesibilidad'!D8 -> Contraste mínimo de 4.5:1 para texto normal y 3:1 para texto grande y componentes de interfaz. | E19: ='RNF Accesibilidad'!E8 -> Alta | F19: ='RNF Accesibilidad'!F8 -> 0
B20: RNF-ACC-04 | C20: ='RNF Accesibilidad'!C9 -> Texto escalable | D20: ='RNF Accesibilidad'!D9 -> La interfaz respeta el tamaño de fuente del sistema y admite hasta 200 % de ampliación sin pérdida de contenido ni funcionalidad. | E20: ='RNF Accesibilidad'!E9 -> Alta | F20: ='RNF Accesibilidad'!F9 -> 0
B21: RNF-ACC-05 | C21: ='RNF Accesibilidad'!C10 -> Áreas táctiles | D21: ='RNF Accesibilidad'!D10 -> Los componentes táctiles tienen un área mínima de 48 × 48 dp en Android y 44 × 44 pt en iOS. | E21: ='RNF Accesibilidad'!E10 -> Alta | F21: ='RNF Accesibilidad'!F10 -> 0
B22: RNF-ACC-06 | C22: ='RNF Accesibilidad'!C11 -> Información no dependiente del color | D22: ='RNF Accesibilidad'!D11 -> Estados, errores y porcentajes se comunican con texto o ícono además del color. | E22: ='RNF Accesibilidad'!E11 -> Alta | F22: ='RNF Accesibilidad'!F11 -> 0
B23: RNF-ACC-07 | C23: ='RNF Accesibilidad'!C12 -> Navegación por teclado | D23: ='RNF Accesibilidad'!D12 -> El panel web puede operarse completamente con teclado y la app admite teclado externo y control por interruptores (Switch Access / Control por botón), con foco visible y orden lógico. | E23: ='RNF Accesibilidad'!E12 -> Alta | F23: ='RNF Accesibilidad'!F12 -> 0
B24: RNF-ACC-08 | C24: ='RNF Accesibilidad'!C13 -> Lenguaje claro | D24: ='RNF Accesibilidad'!D13 -> Textos en lenguaje claro y sin tecnicismos; los errores de formulario indican qué campo falla y cómo corregirlo. | E24: ='RNF Accesibilidad'!E13 -> Media | F24: ='RNF Accesibilidad'!F13 -> 0
B25: RNF-ACC-09 | C25: ='RNF Accesibilidad'!C14 -> Movimiento reducido | D25: ='RNF Accesibilidad'!D14 -> Se respeta la preferencia de «reducir movimiento» del sistema y no hay contenido parpadeante. | E25: ='RNF Accesibilidad'!E14 -> Baja | F25: ='RNF Accesibilidad'!F14 -> 0
B26: RNF-WEB-01 | C26: ='RNF CRUD Web'!C6 -> Desempeño | D26: ='RNF CRUD Web'!D6 -> Listados paginados de 25 registros con tiempo de respuesta ≤ 1 s. | E26: ='RNF CRUD Web'!E6 -> Alta | F26: ='RNF CRUD Web'!F6 -> 0
B27: RNF-WEB-02 | C27: ='RNF CRUD Web'!C7 -> Validación | D27: ='RNF CRUD Web'!D7 -> Validación en cliente y servidor con mensajes específicos por campo. | E27: ='RNF CRUD Web'!E7 -> Alta | F27: ='RNF CRUD Web'!F7 -> 0
B28: RNF-WEB-03 | C28: ='RNF CRUD Web'!C8 -> Compatibilidad | D28: ='RNF CRUD Web'!D8 -> Funciona en Chrome, Firefox y Edge en sus dos versiones más recientes, en resoluciones desde 1280 px de ancho. | E28: ='RNF CRUD Web'!E8 -> Media | F28: ='RNF CRUD Web'!F8 -> 0
B29: RNF-WEB-04 | C29: ='RNF CRUD Web'!C9 -> Auditoría | D29: ='RNF CRUD Web'!D9 -> Toda creación, edición, validación, suspensión o cambio de estado queda registrado en bitácora con usuario, fecha y hora, valor anterior y valor nuevo. | E29: ='RNF CRUD Web'!E9 -> Alta | F29: ='RNF CRUD Web'!F9 -> 0
B30: RNF-WEB-05 | C30: ='RNF CRUD Web'!C10 -> Confirmación de acciones críticas | D30: ='RNF CRUD Web'!D10 -> Suspender, rechazar o dar de baja requiere confirmación y motivo. | E30: ='RNF CRUD Web'!E10 -> Media | F30: ='RNF CRUD Web'!F10 -> 0
B31: RNF-NOT-01 | C31: ='RNF Notificaciones'!C6 -> Tiempo de entrega | D31: ='RNF Notificaciones'!D6 -> Las notificaciones push se envían en ≤ 1 min y los correos en ≤ 5 min tras el evento. | E31: ='RNF Notificaciones'!E6 -> Media | F31: ='RNF Notificaciones'!F6 -> 0
B32: RNF-NOT-02 | C32: ='RNF Notificaciones'!C7 -> Confiabilidad | D32: ='RNF Notificaciones'!D7 -> Los envíos fallidos se reintentan hasta 3 veces; el fallo de un canal no bloquea la operación que lo generó. | E32: ='RNF Notificaciones'!E7 -> Alta | F32: ='RNF Notificaciones'!F7 -> 0
B33: RNF-NOT-03 | C33: ='RNF Notificaciones'!C8 -> Correos accesibles | D33: ='RNF Notificaciones'!D8 -> Los correos incluyen versión en texto plano, estructura semántica y enlaces descriptivos. | E33: ='RNF Notificaciones'!E8 -> Media | F33: ='RNF Notificaciones'!F8 -> 0
B34: RNF-NOT-04 | C34: ='RNF Notificaciones'!C9 -> Contenido mínimo | D34: ='RNF Notificaciones'!D9 -> Las notificaciones push no incluyen datos personales sensibles; el detalle se consulta dentro de la app. | E34: ='RNF Notificaciones'!E9 -> Alta | F34: ='RNF Notificaciones'!F9 -> 0
B35: Los RNF provienen de las hojas generales «RNF …» y se actualizan automáticamente; edita el texto y el avance en su hoja general.
B38: Elaborado por: | C38: Alan David Santiago de Vicente, Ricardo Méndez Rodríguez, Eduardo Daniel Licea González
B39: Responsable: | C39: Equipo IncluTec — Ingeniería en Sistemas Computacionales
B40: Dependencias: | C40: API REST (FastAPI), Base de datos PostgreSQL; servicio de correo
B41: Entrega: | C41: 28 de octubre de 2026
B44: Acotaciones de Avance
B45: 100% | C45: Completada
B46: 50% | C46: En proceso
B47: 0% | C47: No Iniciada
B50: Autorizado:

Sheet WEB-05 Vacantes
B1: ← Índice
B3: Requerimientos Funcionales
B4: Interfaz : WEB-05 — Vacantes (moderación)
B5: ID | C5: Requerimiento | D5: Descripción | E5: Prioridad | F5: Avance
B6: RF-01 | C6: Listado global | D6: Listar todas las vacantes vía GET /admin/vacantes con título, empresa, estado, fecha de publicación, postulados y número de reportes. | E6: Alta | F6: 0
B7: RF-02 | C7: Filtros | D7: Filtrar por empresa, estado, categoría, modalidad y «con reportes». | E7: Media | F7: 0
B8: RF-03 | C8: Detalle | D8: Consultar el detalle completo de la vacante, incluida la sección de accesibilidad. | E8: Media | F8: 0
B9: RF-04 | C9: Suspender y reactivar | D9: Suspender una vacante con motivo (PATCH /admin/vacantes/{id}/estado), notificando al reclutador y a los postulados; permitir reactivarla. | E9: Alta | F9: 0
B12: Requerimientos No Funcionales
B13: Interfaz : WEB-05 — Vacantes (moderación) · Accesibilidad, Pantallas de administración web
B14: ID | C14: Nombre | D14: Descripción | E14: Prioridad | F14: Avance
B15: RNF-ACC-01 | C15: ='RNF Accesibilidad'!C6 -> Estándar de accesibilidad | D15: ='RNF Accesibilidad'!D6 -> Las interfaces cumplen las pautas WCAG 2.1 nivel AA. | E15: ='RNF Accesibilidad'!E6 -> Alta | F15: ='RNF Accesibilidad'!F6 -> 0
B16: RNF-ACC-02 | C16: ='RNF Accesibilidad'!C7 -> Lectores de pantalla | D16: ='RNF Accesibilidad'!D7 -> Todos los elementos interactivos tienen etiqueta, rol y estado accesibles (accessibilityLabel/Role/State en React Native; HTML semántico y ARIA en Laravel) y funcionan con TalkBack, VoiceOver y NVDA. | E16: ='RNF Accesibilidad'!E7 -> Alta | F16: ='RNF Accesibilidad'!F7 -> 0
B17: RNF-ACC-03 | C17: ='RNF Accesibilidad'!C8 -> Contraste | D17: ='RNF Accesibilidad'!D8 -> Contraste mínimo de 4.5:1 para texto normal y 3:1 para texto grande y componentes de interfaz. | E17: ='RNF Accesibilidad'!E8 -> Alta | F17: ='RNF Accesibilidad'!F8 -> 0
B18: RNF-ACC-04 | C18: ='RNF Accesibilidad'!C9 -> Texto escalable | D18: ='RNF Accesibilidad'!D9 -> La interfaz respeta el tamaño de fuente del sistema y admite hasta 200 % de ampliación sin pérdida de contenido ni funcionalidad. | E18: ='RNF Accesibilidad'!E9 -> Alta | F18: ='RNF Accesibilidad'!F9 -> 0
B19: RNF-ACC-05 | C19: ='RNF Accesibilidad'!C10 -> Áreas táctiles | D19: ='RNF Accesibilidad'!D10 -> Los componentes táctiles tienen un área mínima de 48 × 48 dp en Android y 44 × 44 pt en iOS. | E19: ='RNF Accesibilidad'!E10 -> Alta | F19: ='RNF Accesibilidad'!F10 -> 0
B20: RNF-ACC-06 | C20: ='RNF Accesibilidad'!C11 -> Información no dependiente del color | D20: ='RNF Accesibilidad'!D11 -> Estados, errores y porcentajes se comunican con texto o ícono además del color. | E20: ='RNF Accesibilidad'!E11 -> Alta | F20: ='RNF Accesibilidad'!F11 -> 0
B21: RNF-ACC-07 | C21: ='RNF Accesibilidad'!C12 -> Navegación por teclado | D21: ='RNF Accesibilidad'!D12 -> El panel web puede operarse completamente con teclado y la app admite teclado externo y control por interruptores (Switch Access / Control por botón), con foco visible y orden lógico. | E21: ='RNF Accesibilidad'!E12 -> Alta | F21: ='RNF Accesibilidad'!F12 -> 0
B22: RNF-ACC-08 | C22: ='RNF Accesibilidad'!C13 -> Lenguaje claro | D22: ='RNF Accesibilidad'!D13 -> Textos en lenguaje claro y sin tecnicismos; los errores de formulario indican qué campo falla y cómo corregirlo. | E22: ='RNF Accesibilidad'!E13 -> Media | F22: ='RNF Accesibilidad'!F13 -> 0
B23: RNF-ACC-09 | C23: ='RNF Accesibilidad'!C14 -> Movimiento reducido | D23: ='RNF Accesibilidad'!D14 -> Se respeta la preferencia de «reducir movimiento» del sistema y no hay contenido parpadeante. | E23: ='RNF Accesibilidad'!E14 -> Baja | F23: ='RNF Accesibilidad'!F14 -> 0
B24: RNF-WEB-01 | C24: ='RNF CRUD Web'!C6 -> Desempeño | D24: ='RNF CRUD Web'!D6 -> Listados paginados de 25 registros con tiempo de respuesta ≤ 1 s. | E24: ='RNF CRUD Web'!E6 -> Alta | F24: ='RNF CRUD Web'!F6 -> 0
B25: RNF-WEB-02 | C25: ='RNF CRUD Web'!C7 -> Validación | D25: ='RNF CRUD Web'!D7 -> Validación en cliente y servidor con mensajes específicos por campo. | E25: ='RNF CRUD Web'!E7 -> Alta | F25: ='RNF CRUD Web'!F7 -> 0
B26: RNF-WEB-03 | C26: ='RNF CRUD Web'!C8 -> Compatibilidad | D26: ='RNF CRUD Web'!D8 -> Funciona en Chrome, Firefox y Edge en sus dos versiones más recientes, en resoluciones desde 1280 px de ancho. | E26: ='RNF CRUD Web'!E8 -> Media | F26: ='RNF CRUD Web'!F8 -> 0
B27: RNF-WEB-04 | C27: ='RNF CRUD Web'!C9 -> Auditoría | D27: ='RNF CRUD Web'!D9 -> Toda creación, edición, validación, suspensión o cambio de estado queda registrado en bitácora con usuario, fecha y hora, valor anterior y valor nuevo. | E27: ='RNF CRUD Web'!E9 -> Alta | F27: ='RNF CRUD Web'!F9 -> 0
B28: RNF-WEB-05 | C28: ='RNF CRUD Web'!C10 -> Confirmación de acciones críticas | D28: ='RNF CRUD Web'!D10 -> Suspender, rechazar o dar de baja requiere confirmación y motivo. | E28: ='RNF CRUD Web'!E10 -> Media | F28: ='RNF CRUD Web'!F10 -> 0
B29: Los RNF provienen de las hojas generales «RNF …» y se actualizan automáticamente; edita el texto y el avance en su hoja general.
B32: Elaborado por: | C32: Alan David Santiago de Vicente, Ricardo Méndez Rodríguez, Eduardo Daniel Licea González
B33: Responsable: | C33: Equipo IncluTec — Ingeniería en Sistemas Computacionales
B34: Dependencias: | C34: API REST (FastAPI), Base de datos PostgreSQL
B35: Entrega: | C35: 28 de octubre de 2026
B38: Acotaciones de Avance
B39: 100% | C39: Completada
B40: 50% | C40: En proceso
B41: 0% | C41: No Iniciada
B44: Autorizado:

Sheet WEB-06 Categ. y habilidades
B1: ← Índice
B3: Requerimientos Funcionales
B4: Interfaz : WEB-06 — Categorías y habilidades
B5: ID | C5: Requerimiento | D5: Descripción | E5: Prioridad | F5: Avance
B6: RF-01 | C6: Categorías de vacante | D6: Listar, crear, editar y desactivar categorías (áreas laborales) con nombre único y descripción. | E6: Alta | F6: 0
B7: RF-02 | C7: Habilidades | D7: Listar, crear, editar y desactivar habilidades con nombre único y categoría asociada. | E7: Alta | F7: 0
B8: RF-03 | C8: Protección de integridad | D8: No permitir eliminar una categoría o habilidad en uso; solo desactivarla, para que deje de ofrecerse en nuevos registros. | E8: Alta | F8: 0
B9: RF-04 | C9: Búsqueda | D9: Buscar habilidades por nombre y mostrar cuántos candidatos y vacantes las usan. | E9: Baja | F9: 0
B12: Requerimientos No Funcionales
B13: Interfaz : WEB-06 — Categorías y habilidades · Accesibilidad, Pantallas de administración web
B14: ID | C14: Nombre | D14: Descripción | E14: Prioridad | F14: Avance
B15: RNF-ACC-01 | C15: ='RNF Accesibilidad'!C6 -> Estándar de accesibilidad | D15: ='RNF Accesibilidad'!D6 -> Las interfaces cumplen las pautas WCAG 2.1 nivel AA. | E15: ='RNF Accesibilidad'!E6 -> Alta | F15: ='RNF Accesibilidad'!F6 -> 0
B16: RNF-ACC-02 | C16: ='RNF Accesibilidad'!C7 -> Lectores de pantalla | D16: ='RNF Accesibilidad'!D7 -> Todos los elementos interactivos tienen etiqueta, rol y estado accesibles (accessibilityLabel/Role/State en React Native; HTML semántico y ARIA en Laravel) y funcionan con TalkBack, VoiceOver y NVDA. | E16: ='RNF Accesibilidad'!E7 -> Alta | F16: ='RNF Accesibilidad'!F7 -> 0
B17: RNF-ACC-03 | C17: ='RNF Accesibilidad'!C8 -> Contraste | D17: ='RNF Accesibilidad'!D8 -> Contraste mínimo de 4.5:1 para texto normal y 3:1 para texto grande y componentes de interfaz. | E17: ='RNF Accesibilidad'!E8 -> Alta | F17: ='RNF Accesibilidad'!F8 -> 0
B18: RNF-ACC-04 | C18: ='RNF Accesibilidad'!C9 -> Texto escalable | D18: ='RNF Accesibilidad'!D9 -> La interfaz respeta el tamaño de fuente del sistema y admite hasta 200 % de ampliación sin pérdida de contenido ni funcionalidad. | E18: ='RNF Accesibilidad'!E9 -> Alta | F18: ='RNF Accesibilidad'!F9 -> 0
B19: RNF-ACC-05 | C19: ='RNF Accesibilidad'!C10 -> Áreas táctiles | D19: ='RNF Accesibilidad'!D10 -> Los componentes táctiles tienen un área mínima de 48 × 48 dp en Android y 44 × 44 pt en iOS. | E19: ='RNF Accesibilidad'!E10 -> Alta | F19: ='RNF Accesibilidad'!F10 -> 0
B20: RNF-ACC-06 | C20: ='RNF Accesibilidad'!C11 -> Información no dependiente del color | D20: ='RNF Accesibilidad'!D11 -> Estados, errores y porcentajes se comunican con texto o ícono además del color. | E20: ='RNF Accesibilidad'!E11 -> Alta | F20: ='RNF Accesibilidad'!F11 -> 0
B21: RNF-ACC-07 | C21: ='RNF Accesibilidad'!C12 -> Navegación por teclado | D21: ='RNF Accesibilidad'!D12 -> El panel web puede operarse completamente con teclado y la app admite teclado externo y control por interruptores (Switch Access / Control por botón), con foco visible y orden lógico. | E21: ='RNF Accesibilidad'!E12 -> Alta | F21: ='RNF Accesibilidad'!F12 -> 0
B22: RNF-ACC-08 | C22: ='RNF Accesibilidad'!C13 -> Lenguaje claro | D22: ='RNF Accesibilidad'!D13 -> Textos en lenguaje claro y sin tecnicismos; los errores de formulario indican qué campo falla y cómo corregirlo. | E22: ='RNF Accesibilidad'!E13 -> Media | F22: ='RNF Accesibilidad'!F13 -> 0
B23: RNF-ACC-09 | C23: ='RNF Accesibilidad'!C14 -> Movimiento reducido | D23: ='RNF Accesibilidad'!D14 -> Se respeta la preferencia de «reducir movimiento» del sistema y no hay contenido parpadeante. | E23: ='RNF Accesibilidad'!E14 -> Baja | F23: ='RNF Accesibilidad'!F14 -> 0
B24: RNF-WEB-01 | C24: ='RNF CRUD Web'!C6 -> Desempeño | D24: ='RNF CRUD Web'!D6 -> Listados paginados de 25 registros con tiempo de respuesta ≤ 1 s. | E24: ='RNF CRUD Web'!E6 -> Alta | F24: ='RNF CRUD Web'!F6 -> 0
B25: RNF-WEB-02 | C25: ='RNF CRUD Web'!C7 -> Validación | D25: ='RNF CRUD Web'!D7 -> Validación en cliente y servidor con mensajes específicos por campo. | E25: ='RNF CRUD Web'!E7 -> Alta | F25: ='RNF CRUD Web'!F7 -> 0
B26: RNF-WEB-03 | C26: ='RNF CRUD Web'!C8 -> Compatibilidad | D26: ='RNF CRUD Web'!D8 -> Funciona en Chrome, Firefox y Edge en sus dos versiones más recientes, en resoluciones desde 1280 px de ancho. | E26: ='RNF CRUD Web'!E8 -> Media | F26: ='RNF CRUD Web'!F8 -> 0
B27: RNF-WEB-04 | C27: ='RNF CRUD Web'!C9 -> Auditoría | D27: ='RNF CRUD Web'!D9 -> Toda creación, edición, validación, suspensión o cambio de estado queda registrado en bitácora con usuario, fecha y hora, valor anterior y valor nuevo. | E27: ='RNF CRUD Web'!E9 -> Alta | F27: ='RNF CRUD Web'!F9 -> 0
B28: RNF-WEB-05 | C28: ='RNF CRUD Web'!C10 -> Confirmación de acciones críticas | D28: ='RNF CRUD Web'!D10 -> Suspender, rechazar o dar de baja requiere confirmación y motivo. | E28: ='RNF CRUD Web'!E10 -> Media | F28: ='RNF CRUD Web'!F10 -> 0
B29: Los RNF provienen de las hojas generales «RNF …» y se actualizan automáticamente; edita el texto y el avance en su hoja general.
B32: Elaborado por: | C32: Alan David Santiago de Vicente, Ricardo Méndez Rodríguez, Eduardo Daniel Licea González
B33: Responsable: | C33: Equipo IncluTec — Ingeniería en Sistemas Computacionales
B34: Dependencias: | C34: API REST (FastAPI), Base de datos PostgreSQL
B35: Entrega: | C35: 28 de octubre de 2026
B38: Acotaciones de Avance
B39: 100% | C39: Completada
B40: 50% | C40: En proceso
B41: 0% | C41: No Iniciada
B44: Autorizado:

Sheet WEB-07 Catálogos
B1: ← Índice
B3: Requerimientos Funcionales
B4: Interfaz : WEB-07 — Catálogos
B5: ID | C5: Requerimiento | D5: Descripción | E5: Prioridad | F5: Avance
B6: RF-01 | C6: Ajustes y condiciones de accesibilidad | D6: Administrar el catálogo de ajustes razonables y condiciones de accesibilidad con nombre, descripción en lenguaje claro y categoría (movilidad, visual, auditiva, comunicación, cognitiva/psicosocial, general). | E6: Alta | F6: 0
B7: RF-02 | C7: Catálogos generales | D7: Administrar modalidades de trabajo, jornadas, tipos de contrato, niveles educativos, sectores y tamaños de empresa. | E7: Alta | F7: 0
B8: RF-03 | C8: Motivos de reporte | D8: Administrar los motivos disponibles para reportar vacantes, empresas o candidatos. | E8: Media | F8: 0
B9: RF-04 | C9: Integridad | D9: Validar nombres únicos por catálogo y aplicar desactivación en lugar de borrado cuando el registro esté en uso. | E9: Alta | F9: 0
B12: Requerimientos No Funcionales
B13: Interfaz : WEB-07 — Catálogos · Accesibilidad, Pantallas de administración web
B14: ID | C14: Nombre | D14: Descripción | E14: Prioridad | F14: Avance
B15: RNF-ACC-01 | C15: ='RNF Accesibilidad'!C6 -> Estándar de accesibilidad | D15: ='RNF Accesibilidad'!D6 -> Las interfaces cumplen las pautas WCAG 2.1 nivel AA. | E15: ='RNF Accesibilidad'!E6 -> Alta | F15: ='RNF Accesibilidad'!F6 -> 0
B16: RNF-ACC-02 | C16: ='RNF Accesibilidad'!C7 -> Lectores de pantalla | D16: ='RNF Accesibilidad'!D7 -> Todos los elementos interactivos tienen etiqueta, rol y estado accesibles (accessibilityLabel/Role/State en React Native; HTML semántico y ARIA en Laravel) y funcionan con TalkBack, VoiceOver y NVDA. | E16: ='RNF Accesibilidad'!E7 -> Alta | F16: ='RNF Accesibilidad'!F7 -> 0
B17: RNF-ACC-03 | C17: ='RNF Accesibilidad'!C8 -> Contraste | D17: ='RNF Accesibilidad'!D8 -> Contraste mínimo de 4.5:1 para texto normal y 3:1 para texto grande y componentes de interfaz. | E17: ='RNF Accesibilidad'!E8 -> Alta | F17: ='RNF Accesibilidad'!F8 -> 0
B18: RNF-ACC-04 | C18: ='RNF Accesibilidad'!C9 -> Texto escalable | D18: ='RNF Accesibilidad'!D9 -> La interfaz respeta el tamaño de fuente del sistema y admite hasta 200 % de ampliación sin pérdida de contenido ni funcionalidad. | E18: ='RNF Accesibilidad'!E9 -> Alta | F18: ='RNF Accesibilidad'!F9 -> 0
B19: RNF-ACC-05 | C19: ='RNF Accesibilidad'!C10 -> Áreas táctiles | D19: ='RNF Accesibilidad'!D10 -> Los componentes táctiles tienen un área mínima de 48 × 48 dp en Android y 44 × 44 pt en iOS. | E19: ='RNF Accesibilidad'!E10 -> Alta | F19: ='RNF Accesibilidad'!F10 -> 0
B20: RNF-ACC-06 | C20: ='RNF Accesibilidad'!C11 -> Información no dependiente del color | D20: ='RNF Accesibilidad'!D11 -> Estados, errores y porcentajes se comunican con texto o ícono además del color. | E20: ='RNF Accesibilidad'!E11 -> Alta | F20: ='RNF Accesibilidad'!F11 -> 0
B21: RNF-ACC-07 | C21: ='RNF Accesibilidad'!C12 -> Navegación por teclado | D21: ='RNF Accesibilidad'!D12 -> El panel web puede operarse completamente con teclado y la app admite teclado externo y control por interruptores (Switch Access / Control por botón), con foco visible y orden lógico. | E21: ='RNF Accesibilidad'!E12 -> Alta | F21: ='RNF Accesibilidad'!F12 -> 0
B22: RNF-ACC-08 | C22: ='RNF Accesibilidad'!C13 -> Lenguaje claro | D22: ='RNF Accesibilidad'!D13 -> Textos en lenguaje claro y sin tecnicismos; los errores de formulario indican qué campo falla y cómo corregirlo. | E22: ='RNF Accesibilidad'!E13 -> Media | F22: ='RNF Accesibilidad'!F13 -> 0
B23: RNF-ACC-09 | C23: ='RNF Accesibilidad'!C14 -> Movimiento reducido | D23: ='RNF Accesibilidad'!D14 -> Se respeta la preferencia de «reducir movimiento» del sistema y no hay contenido parpadeante. | E23: ='RNF Accesibilidad'!E14 -> Baja | F23: ='RNF Accesibilidad'!F14 -> 0
B24: RNF-WEB-01 | C24: ='RNF CRUD Web'!C6 -> Desempeño | D24: ='RNF CRUD Web'!D6 -> Listados paginados de 25 registros con tiempo de respuesta ≤ 1 s. | E24: ='RNF CRUD Web'!E6 -> Alta | F24: ='RNF CRUD Web'!F6 -> 0
B25: RNF-WEB-02 | C25: ='RNF CRUD Web'!C7 -> Validación | D25: ='RNF CRUD Web'!D7 -> Validación en cliente y servidor con mensajes específicos por campo. | E25: ='RNF CRUD Web'!E7 -> Alta | F25: ='RNF CRUD Web'!F7 -> 0
B26: RNF-WEB-03 | C26: ='RNF CRUD Web'!C8 -> Compatibilidad | D26: ='RNF CRUD Web'!D8 -> Funciona en Chrome, Firefox y Edge en sus dos versiones más recientes, en resoluciones desde 1280 px de ancho. | E26: ='RNF CRUD Web'!E8 -> Media | F26: ='RNF CRUD Web'!F8 -> 0
B27: RNF-WEB-04 | C27: ='RNF CRUD Web'!C9 -> Auditoría | D27: ='RNF CRUD Web'!D9 -> Toda creación, edición, validación, suspensión o cambio de estado queda registrado en bitácora con usuario, fecha y hora, valor anterior y valor nuevo. | E27: ='RNF CRUD Web'!E9 -> Alta | F27: ='RNF CRUD Web'!F9 -> 0
B28: RNF-WEB-05 | C28: ='RNF CRUD Web'!C10 -> Confirmación de acciones críticas | D28: ='RNF CRUD Web'!D10 -> Suspender, rechazar o dar de baja requiere confirmación y motivo. | E28: ='RNF CRUD Web'!E10 -> Media | F28: ='RNF CRUD Web'!F10 -> 0
B29: Los RNF provienen de las hojas generales «RNF …» y se actualizan automáticamente; edita el texto y el avance en su hoja general.
B32: Elaborado por: | C32: Alan David Santiago de Vicente, Ricardo Méndez Rodríguez, Eduardo Daniel Licea González
B33: Responsable: | C33: Equipo IncluTec — Ingeniería en Sistemas Computacionales
B34: Dependencias: | C34: API REST (FastAPI), Base de datos PostgreSQL
B35: Entrega: | C35: 28 de octubre de 2026
B38: Acotaciones de Avance
B39: 100% | C39: Completada
B40: 50% | C40: En proceso
B41: 0% | C41: No Iniciada
B44: Autorizado:

Sheet WEB-08 Reportes-incidencias
B1: ← Índice
B3: Requerimientos Funcionales
B4: Interfaz : WEB-08 — Reportes e incidencias
B5: ID | C5: Requerimiento | D5: Descripción | E5: Prioridad | F5: Avance
B6: RF-01 | C6: Bandeja de reportes | D6: Listar reportes vía GET /admin/reportes con tipo (vacante, empresa, candidato), motivo, fecha, quién reporta y estado (abierto, en revisión, resuelto, descartado). | E6: Alta | F6: 0
B7: RF-02 | C7: Filtros | D7: Filtrar por estado, tipo y motivo; ordenar por antigüedad. | E7: Media | F7: 0
B8: RF-03 | C8: Detalle del reporte | D8: Mostrar el reporte junto con el elemento reportado y los reportes previos contra el mismo elemento. | E8: Alta | F8: 0
B9: RF-04 | C9: Seguimiento de la incidencia | D9: Cambiar el estado del reporte registrando una resolución obligatoria al cerrarlo (PATCH /admin/reportes/{id}); cada cambio queda en el historial. | E9: Alta | F9: 0
B10: RF-05 | C10: Acciones derivadas | D10: Desde el reporte, suspender la vacante, la empresa o el usuario reportado sin salir de la pantalla. | E10: Alta | F10: 0
B11: RF-06 | C11: Aviso a quien reporta | D11: Notificar a quien reportó cuando su reporte se resuelve o se descarta, sin revelar detalles de la sanción. | E11: Media | F11: 0
B14: Requerimientos No Funcionales
B15: Interfaz : WEB-08 — Reportes e incidencias · Accesibilidad, Pantallas de administración web, Notificaciones
B16: ID | C16: Nombre | D16: Descripción | E16: Prioridad | F16: Avance
B17: RNF-ACC-01 | C17: ='RNF Accesibilidad'!C6 -> Estándar de accesibilidad | D17: ='RNF Accesibilidad'!D6 -> Las interfaces cumplen las pautas WCAG 2.1 nivel AA. | E17: ='RNF Accesibilidad'!E6 -> Alta | F17: ='RNF Accesibilidad'!F6 -> 0
B18: RNF-ACC-02 | C18: ='RNF Accesibilidad'!C7 -> Lectores de pantalla | D18: ='RNF Accesibilidad'!D7 -> Todos los elementos interactivos tienen etiqueta, rol y estado accesibles (accessibilityLabel/Role/State en React Native; HTML semántico y ARIA en Laravel) y funcionan con TalkBack, VoiceOver y NVDA. | E18: ='RNF Accesibilidad'!E7 -> Alta | F18: ='RNF Accesibilidad'!F7 -> 0
B19: RNF-ACC-03 | C19: ='RNF Accesibilidad'!C8 -> Contraste | D19: ='RNF Accesibilidad'!D8 -> Contraste mínimo de 4.5:1 para texto normal y 3:1 para texto grande y componentes de interfaz. | E19: ='RNF Accesibilidad'!E8 -> Alta | F19: ='RNF Accesibilidad'!F8 -> 0
B20: RNF-ACC-04 | C20: ='RNF Accesibilidad'!C9 -> Texto escalable | D20: ='RNF Accesibilidad'!D9 -> La interfaz respeta el tamaño de fuente del sistema y admite hasta 200 % de ampliación sin pérdida de contenido ni funcionalidad. | E20: ='RNF Accesibilidad'!E9 -> Alta | F20: ='RNF Accesibilidad'!F9 -> 0
B21: RNF-ACC-05 | C21: ='RNF Accesibilidad'!C10 -> Áreas táctiles | D21: ='RNF Accesibilidad'!D10 -> Los componentes táctiles tienen un área mínima de 48 × 48 dp en Android y 44 × 44 pt en iOS. | E21: ='RNF Accesibilidad'!E10 -> Alta | F21: ='RNF Accesibilidad'!F10 -> 0
B22: RNF-ACC-06 | C22: ='RNF Accesibilidad'!C11 -> Información no dependiente del color | D22: ='RNF Accesibilidad'!D11 -> Estados, errores y porcentajes se comunican con texto o ícono además del color. | E22: ='RNF Accesibilidad'!E11 -> Alta | F22: ='RNF Accesibilidad'!F11 -> 0
B23: RNF-ACC-07 | C23: ='RNF Accesibilidad'!C12 -> Navegación por teclado | D23: ='RNF Accesibilidad'!D12 -> El panel web puede operarse completamente con teclado y la app admite teclado externo y control por interruptores (Switch Access / Control por botón), con foco visible y orden lógico. | E23: ='RNF Accesibilidad'!E12 -> Alta | F23: ='RNF Accesibilidad'!F12 -> 0
B24: RNF-ACC-08 | C24: ='RNF Accesibilidad'!C13 -> Lenguaje claro | D24: ='RNF Accesibilidad'!D13 -> Textos en lenguaje claro y sin tecnicismos; los errores de formulario indican qué campo falla y cómo corregirlo. | E24: ='RNF Accesibilidad'!E13 -> Media | F24: ='RNF Accesibilidad'!F13 -> 0
B25: RNF-ACC-09 | C25: ='RNF Accesibilidad'!C14 -> Movimiento reducido | D25: ='RNF Accesibilidad'!D14 -> Se respeta la preferencia de «reducir movimiento» del sistema y no hay contenido parpadeante. | E25: ='RNF Accesibilidad'!E14 -> Baja | F25: ='RNF Accesibilidad'!F14 -> 0
B26: RNF-WEB-01 | C26: ='RNF CRUD Web'!C6 -> Desempeño | D26: ='RNF CRUD Web'!D6 -> Listados paginados de 25 registros con tiempo de respuesta ≤ 1 s. | E26: ='RNF CRUD Web'!E6 -> Alta | F26: ='RNF CRUD Web'!F6 -> 0
B27: RNF-WEB-02 | C27: ='RNF CRUD Web'!C7 -> Validación | D27: ='RNF CRUD Web'!D7 -> Validación en cliente y servidor con mensajes específicos por campo. | E27: ='RNF CRUD Web'!E7 -> Alta | F27: ='RNF CRUD Web'!F7 -> 0
B28: RNF-WEB-03 | C28: ='RNF CRUD Web'!C8 -> Compatibilidad | D28: ='RNF CRUD Web'!D8 -> Funciona en Chrome, Firefox y Edge en sus dos versiones más recientes, en resoluciones desde 1280 px de ancho. | E28: ='RNF CRUD Web'!E8 -> Media | F28: ='RNF CRUD Web'!F8 -> 0
B29: RNF-WEB-04 | C29: ='RNF CRUD Web'!C9 -> Auditoría | D29: ='RNF CRUD Web'!D9 -> Toda creación, edición, validación, suspensión o cambio de estado queda registrado en bitácora con usuario, fecha y hora, valor anterior y valor nuevo. | E29: ='RNF CRUD Web'!E9 -> Alta | F29: ='RNF CRUD Web'!F9 -> 0
B30: RNF-WEB-05 | C30: ='RNF CRUD Web'!C10 -> Confirmación de acciones críticas | D30: ='RNF CRUD Web'!D10 -> Suspender, rechazar o dar de baja requiere confirmación y motivo. | E30: ='RNF CRUD Web'!E10 -> Media | F30: ='RNF CRUD Web'!F10 -> 0
B31: RNF-NOT-01 | C31: ='RNF Notificaciones'!C6 -> Tiempo de entrega | D31: ='RNF Notificaciones'!D6 -> Las notificaciones push se envían en ≤ 1 min y los correos en ≤ 5 min tras el evento. | E31: ='RNF Notificaciones'!E6 -> Media | F31: ='RNF Notificaciones'!F6 -> 0
B32: RNF-NOT-02 | C32: ='RNF Notificaciones'!C7 -> Confiabilidad | D32: ='RNF Notificaciones'!D7 -> Los envíos fallidos se reintentan hasta 3 veces; el fallo de un canal no bloquea la operación que lo generó. | E32: ='RNF Notificaciones'!E7 -> Alta | F32: ='RNF Notificaciones'!F7 -> 0
B33: RNF-NOT-03 | C33: ='RNF Notificaciones'!C8 -> Correos accesibles | D33: ='RNF Notificaciones'!D8 -> Los correos incluyen versión en texto plano, estructura semántica y enlaces descriptivos. | E33: ='RNF Notificaciones'!E8 -> Media | F33: ='RNF Notificaciones'!F8 -> 0
B34: RNF-NOT-04 | C34: ='RNF Notificaciones'!C9 -> Contenido mínimo | D34: ='RNF Notificaciones'!D9 -> Las notificaciones push no incluyen datos personales sensibles; el detalle se consulta dentro de la app. | E34: ='RNF Notificaciones'!E9 -> Alta | F34: ='RNF Notificaciones'!F9 -> 0
B35: Los RNF provienen de las hojas generales «RNF …» y se actualizan automáticamente; edita el texto y el avance en su hoja general.
B38: Elaborado por: | C38: Alan David Santiago de Vicente, Ricardo Méndez Rodríguez, Eduardo Daniel Licea González
B39: Responsable: | C39: Equipo IncluTec — Ingeniería en Sistemas Computacionales
B40: Dependencias: | C40: API REST (FastAPI), Base de datos PostgreSQL; servicio de notificaciones
B41: Entrega: | C41: 28 de octubre de 2026
B44: Acotaciones de Avance
B45: 100% | C45: Completada
B46: 50% | C46: En proceso
B47: 0% | C47: No Iniciada
B50: Autorizado:

Sheet API
B1: ← Índice
B3: Requerimientos Funcionales
B4: Interfaz : API — FastAPI (objetivos del API)
B5: ID | C5: Requerimiento | D5: Descripción | E5: Prioridad | F5: Avance
B6: RF-01 | C6: Autenticación y cuentas | D6: Exponer POST /auth/login, GET /auth/me, POST /auth/logout, registro de candidato y reclutador, recuperación y cambio de contraseña. Emitir JWT firmado HS256 con expiración configurable (por defecto 8 h). | E6: Alta | F6: 0
B7: RF-02 | C7: Autorización por rol y propiedad | D7: Proteger cada endpoint por rol (candidato, reclutador, administrador) y por propiedad: un reclutador solo accede a vacantes y postulaciones de su empresa, y un candidato solo a sus propios datos. | E7: Alta | F7: 0
B8: RF-03 | C8: Perfil y CV del candidato | D8: Exponer /candidatos/me con sus subrecursos de experiencias, formaciones, habilidades, preferencias y necesidades de ajuste. | E8: Alta | F8: 0
B9: RF-04 | C9: Empresas y validación | D9: Exponer /empresas (directorio público de validadas), /empresas/me y /admin/empresas, con el flujo de validación pendiente → validada / rechazada y la suspensión. | E9: Alta | F9: 0
B10: RF-05 | C10: Vacantes y búsqueda | D10: Exponer el CRUD de vacantes con estados (borrador, publicada, pausada, cerrada, suspendida) y la búsqueda con filtros combinables y paginación. | E10: Alta | F10: 0
B11: RF-06 | C11: Motor de compatibilidad | D11: Calcular para el candidato C = 0.40·H + 0.30·A + 0.15·M + 0.15·F, donde H = (2·obligatorias cumplidas + deseables cumplidas) / (2·obligatorias + deseables); A = necesidades cubiertas / necesidades registradas (1 si no registró); M = 1 si la modalidad coincide con su preferencia, 0.5 si la vacante es híbrida, 0 en otro caso; F = 1 si cumple la formación mínima, 0.5 si la cursa, 0 si no. Para el reclutador se usa solo (0.40·H + 0.15·M + 0.15·F) / 0.70, sin el componente A. | E11: Alta | F11: 0
B12: RF-07 | C12: Postulaciones y transiciones | D12: Exponer /postulaciones; validar transiciones de estado permitidas, impedir postulaciones duplicadas y registrar cada cambio en el historial con fecha, usuario y mensaje. | E12: Alta | F12: 0
B13: RF-08 | C13: Entrevistas | D13: Exponer /horarios-entrevista y /entrevistas; agendar un horario dentro de una transacción con bloqueo, para que dos candidatos no puedan tomar el mismo (409 si ya está ocupado). | E13: Alta | F13: 0
B14: RF-09 | C14: Notificaciones | D14: Generar notificaciones en la app para cada evento (cambio de estado, entrevista agendada, cancelada o próxima, empresa validada o rechazada, nuevo postulado, reporte resuelto) y enviarlas por push (Expo) y correo (SMTP) en segundo plano según las preferencias del usuario. | E14: Alta | F14: 0
B15: RF-10 | C15: Reportes e incidencias | D15: Exponer POST /reportes para usuarios autenticados y /admin/reportes para su seguimiento, con historial de estados y acciones de suspensión. | E15: Alta | F15: 0
B16: RF-11 | C16: Catálogos | D16: Exponer GET /catalogos/{tipo} para las apps y el CRUD /admin/catalogos/{tipo}, /admin/categorias y /admin/habilidades para el administrador. | E16: Alta | F16: 0
B17: RF-12 | C17: Estadísticas y exportación | D17: Exponer /admin/estadisticas con indicadores agregados y filtros de fecha, y la exportación a PDF y XLSX. | E17: Alta | F17: 0
B18: RF-13 | C18: Contratos consistentes | D18: Todas las respuestas en JSON; errores con códigos HTTP estándar y cuerpo {"detail": "..."}; listados paginados con {items, total, page, size}. | E18: Media | F18: 0
B21: Requerimientos No Funcionales
B22: Interfaz : API — FastAPI (objetivos del API) · Privacidad y datos sensibles, API REST
B23: ID | C23: Nombre | D23: Descripción | E23: Prioridad | F23: Avance
B24: RNF-PRV-01 | C24: ='RNF Privacidad'!C6 -> Cumplimiento legal | D24: ='RNF Privacidad'!D6 -> El tratamiento de datos personales cumple la Ley Federal de Protección de Datos Personales en Posesión de los Particulares, con aviso de privacidad y consentimiento expreso para datos sensibles. | E24: ='RNF Privacidad'!E6 -> Alta | F24: ='RNF Privacidad'!F6 -> 0
B25: RNF-PRV-02 | C25: ='RNF Privacidad'!C7 -> Minimización de datos | D25: ='RNF Privacidad'!D7 -> El sistema registra necesidades de ajuste y no diagnósticos, tipos de discapacidad ni documentos médicos. | E25: ='RNF Privacidad'!E7 -> Alta | F25: ='RNF Privacidad'!F7 -> 0
B26: RNF-PRV-03 | C26: ='RNF Privacidad'!C8 -> Control del candidato | D26: ='RNF Privacidad'!D8 -> Las necesidades de ajuste solo son visibles para el candidato y para las empresas a cuyas vacantes se postuló con consentimiento; el administrador solo ve datos agregados. | E26: ='RNF Privacidad'!E8 -> Alta | F26: ='RNF Privacidad'!F8 -> 0
B27: RNF-PRV-04 | C27: ='RNF Privacidad'!C9 -> Derechos ARCO | D27: ='RNF Privacidad'!D9 -> El candidato puede consultar, corregir y eliminar sus datos; la eliminación anonimiza sus postulaciones históricas en un plazo máximo de 30 días. | E27: ='RNF Privacidad'!E9 -> Alta | F27: ='RNF Privacidad'!F9 -> 0
B28: RNF-PRV-05 | C28: ='RNF Privacidad'!C10 -> Registros sin datos sensibles | D28: ='RNF Privacidad'!D10 -> Los logs del servidor y los mensajes push no incluyen necesidades de ajuste ni datos de contacto. | E28: ='RNF Privacidad'!E10 -> Alta | F28: ='RNF Privacidad'!F10 -> 0
B29: RNF-API-01 | C29: ='RNF API'!C6 -> Disponibilidad | D29: ='RNF API'!D6 -> Disponibilidad ≥ 99 % mensual. | E29: ='RNF API'!E6 -> Alta | F29: ='RNF API'!F6 -> 0
B30: RNF-API-02 | C30: ='RNF API'!C7 -> Desempeño | D30: ='RNF API'!D7 -> Percentil 95 de latencia ≤ 300 ms en endpoints de operación y ≤ 1 s en búsqueda con compatibilidad y en estadísticas. | E30: ='RNF API'!E7 -> Alta | F30: ='RNF API'!F7 -> 0
B31: RNF-API-03 | C31: ='RNF API'!C8 -> Documentación | D31: ='RNF API'!D8 -> Especificación OpenAPI 3 autogenerada por FastAPI y accesible en /docs; rutas versionadas bajo /api/v1. | E31: ='RNF API'!E8 -> Alta | F31: ='RNF API'!F8 -> 0
B32: RNF-API-04 | C32: ='RNF API'!C9 -> Seguridad | D32: ='RNF API'!D9 -> Todos los endpoints, excepto login, registro y recuperación de contraseña, requieren JWT válido; CORS restringido a los orígenes autorizados; validación de entrada con Pydantic. | E32: ='RNF API'!E9 -> Alta | F32: ='RNF API'!F9 -> 0
B33: RNF-API-05 | C33: ='RNF API'!C10 -> Persistencia atómica | D33: ='RNF API'!D10 -> Las operaciones con varios cambios (agendar entrevista, cambio de estado con historial, suspensión en cascada) se ejecutan en transacciones de PostgreSQL. | E33: ='RNF API'!E10 -> Alta | F33: ='RNF API'!F10 -> 0
B34: RNF-API-06 | C34: ='RNF API'!C11 -> Escalabilidad del cálculo | D34: ='RNF API'!D11 -> La compatibilidad se precalcula y se actualiza cuando cambia el CV del candidato o la vacante, sin recalcular en cada consulta. | E34: ='RNF API'!E11 -> Media | F34: ='RNF API'!F11 -> 0
B35: Los RNF provienen de las hojas generales «RNF …» y se actualizan automáticamente; edita el texto y el avance en su hoja general.
B38: Elaborado por: | C38: Alan David Santiago de Vicente, Ricardo Méndez Rodríguez, Eduardo Daniel Licea González
B39: Responsable: | C39: Equipo IncluTec — Ingeniería en Sistemas Computacionales
B40: Dependencias: | C40: Base de datos PostgreSQL; SMTP; Expo Push
B41: Entrega: | C41: 28 de octubre de 2026
B44: Acotaciones de Avance
B45: 100% | C45: Completada
B46: 50% | C46: En proceso
B47: 0% | C47: No Iniciada
B50: Autorizado:

Sheet RNF Accesibilidad
B1: ← Índice
B3: Requerimientos No Funcionales
B4: Interfaz : Accesibilidad (todas las interfaces móviles y web) · aplica a MOV-*, CAN-*, REC-*, WEB-*
B5: ID | C5: Nombre | D5: Descripción | E5: Prioridad | F5: Avance
B6: RNF-ACC-01 | C6: Estándar de accesibilidad | D6: Las interfaces cumplen las pautas WCAG 2.1 nivel AA. | E6: Alta | F6: 0
B7: RNF-ACC-02 | C7: Lectores de pantalla | D7: Todos los elementos interactivos tienen etiqueta, rol y estado accesibles (accessibilityLabel/Role/State en React Native; HTML semántico y ARIA en Laravel) y funcionan con TalkBack, VoiceOver y NVDA. | E7: Alta | F7: 0
B8: RNF-ACC-03 | C8: Contraste | D8: Contraste mínimo de 4.5:1 para texto normal y 3:1 para texto grande y componentes de interfaz. | E8: Alta | F8: 0
B9: RNF-ACC-04 | C9: Texto escalable | D9: La interfaz respeta el tamaño de fuente del sistema y admite hasta 200 % de ampliación sin pérdida de contenido ni funcionalidad. | E9: Alta | F9: 0
B10: RNF-ACC-05 | C10: Áreas táctiles | D10: Los componentes táctiles tienen un área mínima de 48 × 48 dp en Android y 44 × 44 pt en iOS. | E10: Alta | F10: 0
B11: RNF-ACC-06 | C11: Información no dependiente del color | D11: Estados, errores y porcentajes se comunican con texto o ícono además del color. | E11: Alta | F11: 0
B12: RNF-ACC-07 | C12: Navegación por teclado | D12: El panel web puede operarse completamente con teclado y la app admite teclado externo y control por interruptores (Switch Access / Control por botón), con foco visible y orden lógico. | E12: Alta | F12: 0
B13: RNF-ACC-08 | C13: Lenguaje claro | D13: Textos en lenguaje claro y sin tecnicismos; los errores de formulario indican qué campo falla y cómo corregirlo. | E13: Media | F13: 0
B14: RNF-ACC-09 | C14: Movimiento reducido | D14: Se respeta la preferencia de «reducir movimiento» del sistema y no hay contenido parpadeante. | E14: Baja | F14: 0
B17: Elaborado por: | C17: Alan David Santiago de Vicente, Ricardo Méndez Rodríguez, Eduardo Daniel Licea González
B18: Responsable: | C18: Equipo IncluTec — Ingeniería en Sistemas Computacionales
B19: Dependencias: | C19: Aplica a las interfaces del grupo indicado en el campo superior.
B20: Entrega: | C20: 28 de octubre de 2026
B23: Acotaciones de Avance
B24: 100% | C24: Completada
B25: 50% | C25: En proceso
B26: 0% | C26: No Iniciada
B29: Autorizado:

Sheet RNF Autenticación
B1: ← Índice
B3: Requerimientos No Funcionales
B4: Interfaz : Inicio de sesión, registro y recuperación · aplica a MOV-01, MOV-02, MOV-03, WEB-01
B5: ID | C5: Nombre | D5: Descripción | E5: Prioridad | F5: Avance
B6: RNF-AUT-01 | C6: Seguridad — contraseñas | D6: Las contraseñas se almacenan únicamente como hash bcrypt (cost ≥ 10); nunca en texto plano ni en registros. | E6: Alta | F6: 0
B7: RNF-AUT-02 | C7: Seguridad — tokens | D7: JWT firmado HS256 con expiración de 8 h; transporte HTTPS obligatorio; almacenamiento en expo-secure-store (móvil) y en la sesión del servidor Laravel (web). | E7: Alta | F7: 0
B8: RNF-AUT-03 | C8: Protección contra fuerza bruta | D8: Bloqueo temporal de 15 minutos tras 5 intentos fallidos consecutivos por cuenta o por IP. | E8: Alta | F8: 0
B9: RNF-AUT-04 | C9: Mensajes neutros | D9: Los mensajes de error no revelan si un correo existe en el sistema. | E9: Media | F9: 0
B10: RNF-AUT-05 | C10: Desempeño | D10: El inicio de sesión responde en ≤ 1.5 s en el percentil 95. | E10: Media | F10: 0
B13: Elaborado por: | C13: Alan David Santiago de Vicente, Ricardo Méndez Rodríguez, Eduardo Daniel Licea González
B14: Responsable: | C14: Equipo IncluTec — Ingeniería en Sistemas Computacionales
B15: Dependencias: | C15: Aplica a las interfaces del grupo indicado en el campo superior.
B16: Entrega: | C16: 28 de octubre de 2026
B19: Acotaciones de Avance
B20: 100% | C20: Completada
B21: 50% | C21: En proceso
B22: 0% | C22: No Iniciada
B25: Autorizado:

Sheet RNF Privacidad
B1: ← Índice
B3: Requerimientos No Funcionales
B4: Interfaz : Privacidad y datos sensibles · aplica a MOV-02, CAN-02, CAN-03, CAN-04, REC-05, WEB-03, API
B5: ID | C5: Nombre | D5: Descripción | E5: Prioridad | F5: Avance
